Workbook

Sheet 00参数面板
A1: RUNE PROTOCOL · 参数面板 ⚡ 只需修改黄色格，全部分析表自动联动更新
A2: 🔒 固定常量 | C2: 📝 可变输入(黄色) | E2: 📊 计算结果 | F2: ← 说明/公式
A4: A · 项目募资架构（节点总融资800万U）
A5: 参数名称 | B5: 类型 | C5: 数值 | D5: 单位 | E5: 说明 | F5: 占总募集%
A6: 总募集资金 | B6: 🔒固定 | C6: 8000000 | D6: U | E6: 节点总融资 | F6: —
A7: 母TOKEN底池TLP | B7: 🔒固定 | C7: 2800000 | D7: U | E7: 开盘满足第1批 | F7: ='00参数面板'!$C$7/'00参数面板'!$C$6
A8: 子TOKEN LP底池 | B8: 🔒固定 | C8: 500000 | D8: U | E8: 子币流动性 | F8: ='00参数面板'!$C$8/'00参数面板'!$C$6
A9: 运营资金 | B9: 🔒固定 | C9: 2100000 | D9: U | E9: 日常运营 | F9: ='00参数面板'!$C$9/'00参数面板'!$C$6
A10: 国库资金 | B10: 🔒固定 | C10: 2600000 | D10: U | E10: 战略储备 | F10: ='00参数面板'!$C$10/'00参数面板'!$C$6
A12: B · 母TOKEN（符）— 修改D20/D21可调整目标价
A13: 开盘价 | B13: 🔒固定 | C13: 0.028 | D13: $/枚 | E13: DO上线初始定价 | F13: —
A14: 每日销毁率 | B14: 🔒固定 | C14: 0.002 | D14: %/天 | E14: 写死合约0.2%/天 | F14: —
A15: 发行总量 | B15: 🔒固定 | C15: 210000000 | D15: 枚 | E15: 合约写死永不增发 | F15: —
A16: 初始销毁量 | B16: 🔒固定 | C16: 70000000 | D16: 枚 | E16: 锁入黑洞 | F16: ='00参数面板'!$C$15/3
A17: TLP流动池 | B17: 🔒固定 | C17: 100000000 | D17: 枚 | E17: 永不增减 | F17: ='00参数面板'!$C$15*100/210
A18: 节点空投总量 | B18: 🔒固定 | C18: 10000000 | D18: 枚 | E18: 四批底池联动 | F18: ='00参数面板'!$C$15*10/210
A19: 24月通缩周期 | B19: 🔒固定 | C19: 12-18月 | D19: 月 | E19: 完整通缩预计用时 | F19: —
A20: 24月目标价(低) | B20: 📝可变 | C20: 2.24 | D20: $/枚 | E20: 80×目标 ← 可修改 | F20: ='00参数面板'!$C$13*80
A21: 24月目标价(高) | B21: 📝可变 | C21: 3.36 | D21: $/枚 | E21: 120×目标 ← 可修改 | F21: ='00参数面板'!$C$13*120
A24: C · 子TOKEN（符火）— 修改D28/D29可调整目标价
A25: 初始价格 | B25: 🔒固定 | C25: 0.038 | D25: $/枚 | E25: 稀缺溢价定价 | F25: —
A26: 每日燃烧率 | B26: 🔒固定 | C26: 0.002 | D26: %/天 | E26: 写死合约0.2%/天 | F26: —
A27: 发行总量 | B27: 🔒固定 | C27: 13100000 | D27: 枚 | E27: 母币的6.24%稀缺16× | F27: —
A28: 24月目标价(低) | B28: 📝可变 | C28: 3.04 | D28: $/枚 | E28: 80×目标 ← 可修改 | F28: ='00参数面板'!$C$25*80
A29: 24月目标价(高) | B29: 📝可变 | C29: 4.56 | D29: $/枚 | E29: 120×目标 ← 可修改 | F29: ='00参数面板'!$C$25*120
A31: D · 节点产品参数表（4级）— 此表数据被所有分析Sheet引用
A32: 节点等级 | B32: 英文 | C32: 投资额(U) | D32: 席位数 | E32: 母TOKEN私募价($) | F32: 日USDT收益(U) | G32: 权重系数 | H32: 空投总量(枚) | I32: 每席空投(枚)
A33: 符胚 | B33: PIONEER | C33: 2500 | D33: 800 | E33: 0.026 | F33: 11.7 | G33: 1 | H33: 2000000 | I33: ='00参数面板'!$H$33/'00参数面板'!$D$33
A34: 符印 | B34: BUILDER | C34: 5000 | D34: 400 | E34: 0.024 | F34: 23.4 | G34: 1.2 | H34: 2300000 | I34: ='00参数面板'!$H$34/'00参数面板'!$D$34
A35: 符主 | B35: GUARDIAN | C35: 10000 | D35: 200 | E35: 0.02 | F35: 46.8 | G35: 1.6 | H35: 2700000 | I35: ='00参数面板'!$H$35/'00参数面板'!$D$35
A36: 符魂 | B36: STRATEGIC | C36: 50000 | D36: 40 | E36: 0.016 | F36: 234 | G36: 2 | H36: 3000000 | I36: ='00参数面板'!$H$36/'00参数面板'!$D$36
A39: E · 价格阶段定义表 — ⑤⑥行为可变目标价，引用B/C模块预测值
A40: 阶段 | B40: 触发说明 | C40: 母TOKEN价($) | D40: 子TOKEN价($) | E40: 母币涨幅× | F40: 说明
A41: ① 开盘 | B41: DO上线当日 | C41: 0.028 | D41: 0.038 | E41: ='00参数面板'!$C$41/'00参数面板'!$C$41 | F41: DO上线当日
A42: ② 第2批触发 | B42: TLP≥700万 | C42: 0.07 | D42: 0.095 | E42: ='00参数面板'!$C$42/'00参数面板'!$C$41 | F42: TLP≥700万
A43: ③ 第3批触发 | B43: TLP≥1750万 | C43: 0.175 | D43: 0.238 | E43: ='00参数面板'!$C$43/'00参数面板'!$C$41 | F43: TLP≥1750万
A44: ④ 第4批触发 | B44: TLP≥3500万/180天 | C44: 0.35 | D44: 0.475 | E44: ='00参数面板'!$C$44/'00参数面板'!$C$41 | F44: TLP≥3500万/180天
A45: ⑤ 目标价(低) | B45: 80×预测 | C45: ='00参数面板'!$C$20 | D45: ='00参数面板'!$C$28 | E45: ='00参数面板'!$C$45/'00参数面板'!$C$41 | F45: 80×预测
A46: ⑥ 目标价(高) | B46: 120×预测 | C46: ='00参数面板'!$C$21 | D46: ='00参数面板'!$C$29 | E46: ='00参数面板'!$C$46/'00参数面板'!$C$41 | F46: 120×预测

Sheet 01母币走势分析
A1: 母TOKEN（符）价格走势 × 各节点收益发展分析
A2: 🔒 固定常量 | D2: 📝 可变输入（引用参数面板⑤⑥） | G2: 📊 计算结果（公式联动） | K2: 修改参数面板D20/D21目标价 → 本表自动更新
A4: ① 母TOKEN价格阶段定义（均引用参数面板E模块）
A5: 阶段 | B5: 触发说明 | C5: 母TOKEN价($) | D5: 类型 | E5: 母币涨幅(×) | F5: 价格来源公式
A6: ='00参数面板'!$A$41 | B6: ='00参数面板'!$B$41 | C6: ='00参数面板'!$C$41 | D6: 🔒固定 | E6: ='00参数面板'!$C$41/'00参数面板'!$C$41 | F6: 引用参数面板E!C41
A7: ='00参数面板'!$A$42 | B7: ='00参数面板'!$B$42 | C7: ='00参数面板'!$C$42 | D7: 🔒固定 | E7: ='00参数面板'!$C$42/'00参数面板'!$C$41 | F7: 引用参数面板E!C42
A8: ='00参数面板'!$A$43 | B8: ='00参数面板'!$B$43 | C8: ='00参数面板'!$C$43 | D8: 🔒固定 | E8: ='00参数面板'!$C$43/'00参数面板'!$C$41 | F8: 引用参数面板E!C43
A9: ='00参数面板'!$A$44 | B9: ='00参数面板'!$B$44 | C9: ='00参数面板'!$C$44 | D9: 🔒固定 | E9: ='00参数面板'!$C$44/'00参数面板'!$C$41 | F9: 引用参数面板E!C44
A10: ='00参数面板'!$A$45 | B10: ='00参数面板'!$B$45 | C10: ='00参数面板'!$C$45 | D10: 📝可变 | E10: ='00参数面板'!$C$45/'00参数面板'!$C$41 | F10: 引用参数面板E!C45
A11: ='00参数面板'!$A$46 | B11: ='00参数面板'!$B$46 | C11: ='00参数面板'!$C$46 | D11: 📝可变 | E11: ='00参数面板'!$C$46/'00参数面板'!$C$41 | F11: 引用参数面板E!C46
A14: ② 各节点收益矩阵（所有数值为Excel公式，随参数面板自动联动）
A15: 节点 | B15: 投资额(U) | C15: 私募价($) | D15: 获母TOKEN(枚) | E15: 价格阶段 | F15: 母TOKEN价($) | G15: 涨幅× | H15: 持仓市值(U) | I15: 市值/成本× | J15: 日USDT(U) | K15: 30天USDT(U) | L15: 空投价值(U) | M15: 总资产(U) | N15: 总资产/成本× | O15: 触发条件
A16: ='00参数面板'!$A$33 | B16: ='00参数面板'!$C$33 | C16: ='00参数面板'!$E$33 | D16: ='00参数面板'!$C$33/'00参数面板'!$E$33 | E16: ='00参数面板'!$A$41 | F16: ='00参数面板'!$C$41 | G16: ='00参数面板'!$C$41/'00参数面板'!$C$41 | H16: =('00参数面板'!$C$33/'00参数面板'!$E$33)*'00参数面板'!$C$41 | I16: =(('00参数面板'!$C$33/'00参数面板'!$E$33)*'00参数面板'!$C$41)/'00参数面板'!$C$33 | J16: ='00参数面板'!$F$33 | K16: ='00参数面板'!$F$33*30 | L16: ='00参数面板'!$H$33*'00参数面板'!$C$41 | M16: =(('00参数面板'!$C$33/'00参数面板'!$E$33)*'00参数面板'!$C$41)+('00参数面板'!$F$33*30)+('00参数面板'!$H$33*'00参数面板'!$C$41) | N16: =((('00参数面板'!$C$33/'00参数面板'!$E$33)*'00参数面板'!$C$41)+('00参数面板'!$F$33*30)+('00参数面板'!$H$33*'00参数面板'!$C$41))/'00参数面板'!$C$33 | O16: ='00参数面板'!$B$41
A17: ='00参数面板'!$A$33 | B17: ='00参数面板'!$C$33 | C17: ='00参数面板'!$E$33 | D17: ='00参数面板'!$C$33/'00参数面板'!$E$33 | E17: ='00参数面板'!$A$42 | F17: ='00参数面板'!$C$42 | G17: ='00参数面板'!$C$42/'00参数面板'!$C$41 | H17: =('00参数面板'!$C$33/'00参数面板'!$E$33)*'00参数面板'!$C$42 | I17: =(('00参数面板'!$C$33/'00参数面板'!$E$33)*'00参数面板'!$C$42)/'00参数面板'!$C$33 | J17: ='00参数面板'!$F$33 | K17: ='00参数面板'!$F$33*30 | L17: ='00参数面板'!$H$33*'00参数面板'!$C$42 | M17: =(('00参数面板'!$C$33/'00参数面板'!$E$33)*'00参数面板'!$C$42)+('00参数面板'!$F$33*30)+('00参数面板'!$H$33*'00参数面板'!$C$42) | N17: =((('00参数面板'!$C$33/'00参数面板'!$E$33)*'00参数面板'!$C$42)+('00参数面板'!$F$33*30)+('00参数面板'!$H$33*'00参数面板'!$C$42))/'00参数面板'!$C$33 | O17: ='00参数面板'!$B$42
A18: ='00参数面板'!$A$33 | B18: ='00参数面板'!$C$33 | C18: ='00参数面板'!$E$33 | D18: ='00参数面板'!$C$33/'00参数面板'!$E$33 | E18: ='00参数面板'!$A$43 | F18: ='00参数面板'!$C$43 | G18: ='00参数面板'!$C$43/'00参数面板'!$C$41 | H18: =('00参数面板'!$C$33/'00参数面板'!$E$33)*'00参数面板'!$C$43 | I18: =(('00参数面板'!$C$33/'00参数面板'!$E$33)*'00参数面板'!$C$43)/'00参数面板'!$C$33 | J18: ='00参数面板'!$F$33 | K18: ='00参数面板'!$F$33*30 | L18: ='00参数面板'!$H$33*'00参数面板'!$C$43 | M18: =(('00参数面板'!$C$33/'00参数面板'!$E$33)*'00参数面板'!$C$43)+('00参数面板'!$F$33*30)+('00参数面板'!$H$33*'00参数面板'!$C$43) | N18: =((('00参数面板'!$C$33/'00参数面板'!$E$33)*'00参数面板'!$C$43)+('00参数面板'!$F$33*30)+('00参数面板'!$H$33*'00参数面板'!$C$43))/'00参数面板'!$C$33 | O18: ='00参数面板'!$B$43
A19: ='00参数面板'!$A$33 | B19: ='00参数面板'!$C$33 | C19: ='00参数面板'!$E$33 | D19: ='00参数面板'!$C$33/'00参数面板'!$E$33 | E19: ='00参数面板'!$A$44 | F19: ='00参数面板'!$C$44 | G19: ='00参数面板'!$C$44/'00参数面板'!$C$41 | H19: =('00参数面板'!$C$33/'00参数面板'!$E$33)*'00参数面板'!$C$44 | I19: =(('00参数面板'!$C$33/'00参数面板'!$E$33)*'00参数面板'!$C$44)/'00参数面板'!$C$33 | J19: ='00参数面板'!$F$33 | K19: ='00参数面板'!$F$33*30 | L19: ='00参数面板'!$H$33*'00参数面板'!$C$44 | M19: =(('00参数面板'!$C$33/'00参数面板'!$E$33)*'00参数面板'!$C$44)+('00参数面板'!$F$33*30)+('00参数面板'!$H$33*'00参数面板'!$C$44) | N19: =((('00参数面板'!$C$33/'00参数面板'!$E$33)*'00参数面板'!$C$44)+('00参数面板'!$F$33*30)+('00参数面板'!$H$33*'00参数面板'!$C$44))/'00参数面板'!$C$33 | O19: ='00参数面板'!$B$44
A20: ='00参数面板'!$A$33 | B20: ='00参数面板'!$C$33 | C20: ='00参数面板'!$E$33 | D20: ='00参数面板'!$C$33/'00参数面板'!$E$33 | E20: ='00参数面板'!$A$45 | F20: ='00参数面板'!$C$45 | G20: ='00参数面板'!$C$45/'00参数面板'!$C$41 | H20: =('00参数面板'!$C$33/'00参数面板'!$E$33)*'00参数面板'!$C$45 | I20: =(('00参数面板'!$C$33/'00参数面板'!$E$33)*'00参数面板'!$C$45)/'00参数面板'!$C$33 | J20: ='00参数面板'!$F$33 | K20: ='00参数面板'!$F$33*30 | L20: ='00参数面板'!$H$33*'00参数面板'!$C$45 | M20: =(('00参数面板'!$C$33/'00参数面板'!$E$33)*'00参数面板'!$C$45)+('00参数面板'!$F$33*30)+('00参数面板'!$H$33*'00参数面板'!$C$45) | N20: =((('00参数面板'!$C$33/'00参数面板'!$E$33)*'00参数面板'!$C$45)+('00参数面板'!$F$33*30)+('00参数面板'!$H$33*'00参数面板'!$C$45))/'00参数面板'!$C$33 | O20: ='00参数面板'!$B$45
A21: ='00参数面板'!$A$33 | B21: ='00参数面板'!$C$33 | C21: ='00参数面板'!$E$33 | D21: ='00参数面板'!$C$33/'00参数面板'!$E$33 | E21: ='00参数面板'!$A$46 | F21: ='00参数面板'!$C$46 | G21: ='00参数面板'!$C$46/'00参数面板'!$C$41 | H21: =('00参数面板'!$C$33/'00参数面板'!$E$33)*'00参数面板'!$C$46 | I21: =(('00参数面板'!$C$33/'00参数面板'!$E$33)*'00参数面板'!$C$46)/'00参数面板'!$C$33 | J21: ='00参数面板'!$F$33 | K21: ='00参数面板'!$F$33*30 | L21: ='00参数面板'!$H$33*'00参数面板'!$C$46 | M21: =(('00参数面板'!$C$33/'00参数面板'!$E$33)*'00参数面板'!$C$46)+('00参数面板'!$F$33*30)+('00参数面板'!$H$33*'00参数面板'!$C$46) | N21: =((('00参数面板'!$C$33/'00参数面板'!$E$33)*'00参数面板'!$C$46)+('00参数面板'!$F$33*30)+('00参数面板'!$H$33*'00参数面板'!$C$46))/'00参数面板'!$C$33 | O21: ='00参数面板'!$B$46
A23: ='00参数面板'!$A$34 | B23: ='00参数面板'!$C$34 | C23: ='00参数面板'!$E$34 | D23: ='00参数面板'!$C$34/'00参数面板'!$E$34 | E23: ='00参数面板'!$A$41 | F23: ='00参数面板'!$C$41 | G23: ='00参数面板'!$C$41/'00参数面板'!$C$41 | H23: =('00参数面板'!$C$34/'00参数面板'!$E$34)*'00参数面板'!$C$41 | I23: =(('00参数面板'!$C$34/'00参数面板'!$E$34)*'00参数面板'!$C$41)/'00参数面板'!$C$34 | J23: ='00参数面板'!$F$34 | K23: ='00参数面板'!$F$34*30 | L23: ='00参数面板'!$H$34*'00参数面板'!$C$41 | M23: =(('00参数面板'!$C$34/'00参数面板'!$E$34)*'00参数面板'!$C$41)+('00参数面板'!$F$34*30)+('00参数面板'!$H$34*'00参数面板'!$C$41) | N23: =((('00参数面板'!$C$34/'00参数面板'!$E$34)*'00参数面板'!$C$41)+('00参数面板'!$F$34*30)+('00参数面板'!$H$34*'00参数面板'!$C$41))/'00参数面板'!$C$34 | O23: ='00参数面板'!$B$41
A24: ='00参数面板'!$A$34 | B24: ='00参数面板'!$C$34 | C24: ='00参数面板'!$E$34 | D24: ='00参数面板'!$C$34/'00参数面板'!$E$34 | E24: ='00参数面板'!$A$42 | F24: ='00参数面板'!$C$42 | G24: ='00参数面板'!$C$42/'00参数面板'!$C$41 | H24: =('00参数面板'!$C$34/'00参数面板'!$E$34)*'00参数面板'!$C$42 | I24: =(('00参数面板'!$C$34/'00参数面板'!$E$34)*'00参数面板'!$C$42)/'00参数面板'!$C$34 | J24: ='00参数面板'!$F$34 | K24: ='00参数面板'!$F$34*30 | L24: ='00参数面板'!$H$34*'00参数面板'!$C$42 | M24: =(('00参数面板'!$C$34/'00参数面板'!$E$34)*'00参数面板'!$C$42)+('00参数面板'!$F$34*30)+('00参数面板'!$H$34*'00参数面板'!$C$42) | N24: =((('00参数面板'!$C$34/'00参数面板'!$E$34)*'00参数面板'!$C$42)+('00参数面板'!$F$34*30)+('00参数面板'!$H$34*'00参数面板'!$C$42))/'00参数面板'!$C$34 | O24: ='00参数面板'!$B$42
A25: ='00参数面板'!$A$34 | B25: ='00参数面板'!$C$34 | C25: ='00参数面板'!$E$34 | D25: ='00参数面板'!$C$34/'00参数面板'!$E$34 | E25: ='00参数面板'!$A$43 | F25: ='00参数面板'!$C$43 | G25: ='00参数面板'!$C$43/'00参数面板'!$C$41 | H25: =('00参数面板'!$C$34/'00参数面板'!$E$34)*'00参数面板'!$C$43 | I25: =(('00参数面板'!$C$34/'00参数面板'!$E$34)*'00参数面板'!$C$43)/'00参数面板'!$C$34 | J25: ='00参数面板'!$F$34 | K25: ='00参数面板'!$F$34*30 | L25: ='00参数面板'!$H$34*'00参数面板'!$C$43 | M25: =(('00参数面板'!$C$34/'00参数面板'!$E$34)*'00参数面板'!$C$43)+('00参数面板'!$F$34*30)+('00参数面板'!$H$34*'00参数面板'!$C$43) | N25: =((('00参数面板'!$C$34/'00参数面板'!$E$34)*'00参数面板'!$C$43)+('00参数面板'!$F$34*30)+('00参数面板'!$H$34*'00参数面板'!$C$43))/'00参数面板'!$C$34 | O25: ='00参数面板'!$B$43
A26: ='00参数面板'!$A$34 | B26: ='00参数面板'!$C$34 | C26: ='00参数面板'!$E$34 | D26: ='00参数面板'!$C$34/'00参数面板'!$E$34 | E26: ='00参数面板'!$A$44 | F26: ='00参数面板'!$C$44 | G26: ='00参数面板'!$C$44/'00参数面板'!$C$41 | H26: =('00参数面板'!$C$34/'00参数面板'!$E$34)*'00参数面板'!$C$44 | I26: =(('00参数面板'!$C$34/'00参数面板'!$E$34)*'00参数面板'!$C$44)/'00参数面板'!$C$34 | J26: ='00参数面板'!$F$34 | K26: ='00参数面板'!$F$34*30 | L26: ='00参数面板'!$H$34*'00参数面板'!$C$44 | M26: =(('00参数面板'!$C$34/'00参数面板'!$E$34)*'00参数面板'!$C$44)+('00参数面板'!$F$34*30)+('00参数面板'!$H$34*'00参数面板'!$C$44) | N26: =((('00参数面板'!$C$34/'00参数面板'!$E$34)*'00参数面板'!$C$44)+('00参数面板'!$F$34*30)+('00参数面板'!$H$34*'00参数面板'!$C$44))/'00参数面板'!$C$34 | O26: ='00参数面板'!$B$44
A27: ='00参数面板'!$A$34 | B27: ='00参数面板'!$C$34 | C27: ='00参数面板'!$E$34 | D27: ='00参数面板'!$C$34/'00参数面板'!$E$34 | E27: ='00参数面板'!$A$45 | F27: ='00参数面板'!$C$45 | G27: ='00参数面板'!$C$45/'00参数面板'!$C$41 | H27: =('00参数面板'!$C$34/'00参数面板'!$E$34)*'00参数面板'!$C$45 | I27: =(('00参数面板'!$C$34/'00参数面板'!$E$34)*'00参数面板'!$C$45)/'00参数面板'!$C$34 | J27: ='00参数面板'!$F$34 | K27: ='00参数面板'!$F$34*30 | L27: ='00参数面板'!$H$34*'00参数面板'!$C$45 | M27: =(('00参数面板'!$C$34/'00参数面板'!$E$34)*'00参数面板'!$C$45)+('00参数面板'!$F$34*30)+('00参数面板'!$H$34*'00参数面板'!$C$45) | N27: =((('00参数面板'!$C$34/'00参数面板'!$E$34)*'00参数面板'!$C$45)+('00参数面板'!$F$34*30)+('00参数面板'!$H$34*'00参数面板'!$C$45))/'00参数面板'!$C$34 | O27: ='00参数面板'!$B$45
A28: ='00参数面板'!$A$34 | B28: ='00参数面板'!$C$34 | C28: ='00参数面板'!$E$34 | D28: ='00参数面板'!$C$34/'00参数面板'!$E$34 | E28: ='00参数面板'!$A$46 | F28: ='00参数面板'!$C$46 | G28: ='00参数面板'!$C$46/'00参数面板'!$C$41 | H28: =('00参数面板'!$C$34/'00参数面板'!$E$34)*'00参数面板'!$C$46 | I28: =(('00参数面板'!$C$34/'00参数面板'!$E$34)*'00参数面板'!$C$46)/'00参数面板'!$C$34 | J28: ='00参数面板'!$F$34 | K28: ='00参数面板'!$F$34*30 | L28: ='00参数面板'!$H$34*'00参数面板'!$C$46 | M28: =(('00参数面板'!$C$34/'00参数面板'!$E$34)*'00参数面板'!$C$46)+('00参数面板'!$F$34*30)+('00参数面板'!$H$34*'00参数面板'!$C$46) | N28: =((('00参数面板'!$C$34/'00参数面板'!$E$34)*'00参数面板'!$C$46)+('00参数面板'!$F$34*30)+('00参数面板'!$H$34*'00参数面板'!$C$46))/'00参数面板'!$C$34 | O28: ='00参数面板'!$B$46
A30: ='00参数面板'!$A$35 | B30: ='00参数面板'!$C$35 | C30: ='00参数面板'!$E$35 | D30: ='00参数面板'!$C$35/'00参数面板'!$E$35 | E30: ='00参数面板'!$A$41 | F30: ='00参数面板'!$C$41 | G30: ='00参数面板'!$C$41/'00参数面板'!$C$41 | H30: =('00参数面板'!$C$35/'00参数面板'!$E$35)*'00参数面板'!$C$41 | I30: =(('00参数面板'!$C$35/'00参数面板'!$E$35)*'00参数面板'!$C$41)/'00参数面板'!$C$35 | J30: ='00参数面板'!$F$35 | K30: ='00参数面板'!$F$35*30 | L30: ='00参数面板'!$H$35*'00参数面板'!$C$41 | M30: =(('00参数面板'!$C$35/'00参数面板'!$E$35)*'00参数面板'!$C$41)+('00参数面板'!$F$35*30)+('00参数面板'!$H$35*'00参数面板'!$C$41) | N30: =((('00参数面板'!$C$35/'00参数面板'!$E$35)*'00参数面板'!$C$41)+('00参数面板'!$F$35*30)+('00参数面板'!$H$35*'00参数面板'!$C$41))/'00参数面板'!$C$35 | O30: ='00参数面板'!$B$41
A31: ='00参数面板'!$A$35 | B31: ='00参数面板'!$C$35 | C31: ='00参数面板'!$E$35 | D31: ='00参数面板'!$C$35/'00参数面板'!$E$35 | E31: ='00参数面板'!$A$42 | F31: ='00参数面板'!$C$42 | G31: ='00参数面板'!$C$42/'00参数面板'!$C$41 | H31: =('00参数面板'!$C$35/'00参数面板'!$E$35)*'00参数面板'!$C$42 | I31: =(('00参数面板'!$C$35/'00参数面板'!$E$35)*'00参数面板'!$C$42)/'00参数面板'!$C$35 | J31: ='00参数面板'!$F$35 | K31: ='00参数面板'!$F$35*30 | L31: ='00参数面板'!$H$35*'00参数面板'!$C$42 | M31: =(('00参数面板'!$C$35/'00参数面板'!$E$35)*'00参数面板'!$C$42)+('00参数面板'!$F$35*30)+('00参数面板'!$H$35*'00参数面板'!$C$42) | N31: =((('00参数面板'!$C$35/'00参数面板'!$E$35)*'00参数面板'!$C$42)+('00参数面板'!$F$35*30)+('00参数面板'!$H$35*'00参数面板'!$C$42))/'00参数面板'!$C$35 | O31: ='00参数面板'!$B$42
A32: ='00参数面板'!$A$35 | B32: ='00参数面板'!$C$35 | C32: ='00参数面板'!$E$35 | D32: ='00参数面板'!$C$35/'00参数面板'!$E$35 | E32: ='00参数面板'!$A$43 | F32: ='00参数面板'!$C$43 | G32: ='00参数面板'!$C$43/'00参数面板'!$C$41 | H32: =('00参数面板'!$C$35/'00参数面板'!$E$35)*'00参数面板'!$C$43 | I32: =(('00参数面板'!$C$35/'00参数面板'!$E$35)*'00参数面板'!$C$43)/'00参数面板'!$C$35 | J32: ='00参数面板'!$F$35 | K32: ='00参数面板'!$F$35*30 | L32: ='00参数面板'!$H$35*'00参数面板'!$C$43 | M32: =(('00参数面板'!$C$35/'00参数面板'!$E$35)*'00参数面板'!$C$43)+('00参数面板'!$F$35*30)+('00参数面板'!$H$35*'00参数面板'!$C$43) | N32: =((('00参数面板'!$C$35/'00参数面板'!$E$35)*'00参数面板'!$C$43)+('00参数面板'!$F$35*30)+('00参数面板'!$H$35*'00参数面板'!$C$43))/'00参数面板'!$C$35 | O32: ='00参数面板'!$B$43
A33: ='00参数面板'!$A$35 | B33: ='00参数面板'!$C$35 | C33: ='00参数面板'!$E$35 | D33: ='00参数面板'!$C$35/'00参数面板'!$E$35 | E33: ='00参数面板'!$A$44 | F33: ='00参数面板'!$C$44 | G33: ='00参数面板'!$C$44/'00参数面板'!$C$41 | H33: =('00参数面板'!$C$35/'00参数面板'!$E$35)*'00参数面板'!$C$44 | I33: =(('00参数面板'!$C$35/'00参数面板'!$E$35)*'00参数面板'!$C$44)/'00参数面板'!$C$35 | J33: ='00参数面板'!$F$35 | K33: ='00参数面板'!$F$35*30 | L33: ='00参数面板'!$H$35*'00参数面板'!$C$44 | M33: =(('00参数面板'!$C$35/'00参数面板'!$E$35)*'00参数面板'!$C$44)+('00参数面板'!$F$35*30)+('00参数面板'!$H$35*'00参数面板'!$C$44) | N33: =((('00参数面板'!$C$35/'00参数面板'!$E$35)*'00参数面板'!$C$44)+('00参数面板'!$F$35*30)+('00参数面板'!$H$35*'00参数面板'!$C$44))/'00参数面板'!$C$35 | O33: ='00参数面板'!$B$44
A34: ='00参数面板'!$A$35 | B34: ='00参数面板'!$C$35 | C34: ='00参数面板'!$E$35 | D34: ='00参数面板'!$C$35/'00参数面板'!$E$35 | E34: ='00参数面板'!$A$45 | F34: ='00参数面板'!$C$45 | G34: ='00参数面板'!$C$45/'00参数面板'!$C$41 | H34: =('00参数面板'!$C$35/'00参数面板'!$E$35)*'00参数面板'!$C$45 | I34: =(('00参数面板'!$C$35/'00参数面板'!$E$35)*'00参数面板'!$C$45)/'00参数面板'!$C$35 | J34: ='00参数面板'!$F$35 | K34: ='00参数面板'!$F$35*30 | L34: ='00参数面板'!$H$35*'00参数面板'!$C$45 | M34: =(('00参数面板'!$C$35/'00参数面板'!$E$35)*'00参数面板'!$C$45)+('00参数面板'!$F$35*30)+('00参数面板'!$H$35*'00参数面板'!$C$45) | N34: =((('00参数面板'!$C$35/'00参数面板'!$E$35)*'00参数面板'!$C$45)+('00参数面板'!$F$35*30)+('00参数面板'!$H$35*'00参数面板'!$C$45))/'00参数面板'!$C$35 | O34: ='00参数面板'!$B$45
A35: ='00参数面板'!$A$35 | B35: ='00参数面板'!$C$35 | C35: ='00参数面板'!$E$35 | D35: ='00参数面板'!$C$35/'00参数面板'!$E$35 | E35: ='00参数面板'!$A$46 | F35: ='00参数面板'!$C$46 | G35: ='00参数面板'!$C$46/'00参数面板'!$C$41 | H35: =('00参数面板'!$C$35/'00参数面板'!$E$35)*'00参数面板'!$C$46 | I35: =(('00参数面板'!$C$35/'00参数面板'!$E$35)*'00参数面板'!$C$46)/'00参数面板'!$C$35 | J35: ='00参数面板'!$F$35 | K35: ='00参数面板'!$F$35*30 | L35: ='00参数面板'!$H$35*'00参数面板'!$C$46 | M35: =(('00参数面板'!$C$35/'00参数面板'!$E$35)*'00参数面板'!$C$46)+('00参数面板'!$F$35*30)+('00参数面板'!$H$35*'00参数面板'!$C$46) | N35: =((('00参数面板'!$C$35/'00参数面板'!$E$35)*'00参数面板'!$C$46)+('00参数面板'!$F$35*30)+('00参数面板'!$H$35*'00参数面板'!$C$46))/'00参数面板'!$C$35 | O35: ='00参数面板'!$B$46
A37: ='00参数面板'!$A$36 | B37: ='00参数面板'!$C$36 | C37: ='00参数面板'!$E$36 | D37: ='00参数面板'!$C$36/'00参数面板'!$E$36 | E37: ='00参数面板'!$A$41 | F37: ='00参数面板'!$C$41 | G37: ='00参数面板'!$C$41/'00参数面板'!$C$41 | H37: =('00参数面板'!$C$36/'00参数面板'!$E$36)*'00参数面板'!$C$41 | I37: =(('00参数面板'!$C$36/'00参数面板'!$E$36)*'00参数面板'!$C$41)/'00参数面板'!$C$36 | J37: ='00参数面板'!$F$36 | K37: ='00参数面板'!$F$36*30 | L37: ='00参数面板'!$H$36*'00参数面板'!$C$41 | M37: =(('00参数面板'!$C$36/'00参数面板'!$E$36)*'00参数面板'!$C$41)+('00参数面板'!$F$36*30)+('00参数面板'!$H$36*'00参数面板'!$C$41) | N37: =((('00参数面板'!$C$36/'00参数面板'!$E$36)*'00参数面板'!$C$41)+('00参数面板'!$F$36*30)+('00参数面板'!$H$36*'00参数面板'!$C$41))/'00参数面板'!$C$36 | O37: ='00参数面板'!$B$41
A38: ='00参数面板'!$A$36 | B38: ='00参数面板'!$C$36 | C38: ='00参数面板'!$E$36 | D38: ='00参数面板'!$C$36/'00参数面板'!$E$36 | E38: ='00参数面板'!$A$42 | F38: ='00参数面板'!$C$42 | G38: ='00参数面板'!$C$42/'00参数面板'!$C$41 | H38: =('00参数面板'!$C$36/'00参数面板'!$E$36)*'00参数面板'!$C$42 | I38: =(('00参数面板'!$C$36/'00参数面板'!$E$36)*'00参数面板'!$C$42)/'00参数面板'!$C$36 | J38: ='00参数面板'!$F$36 | K38: ='00参数面板'!$F$36*30 | L38: ='00参数面板'!$H$36*'00参数面板'!$C$42 | M38: =(('00参数面板'!$C$36/'00参数面板'!$E$36)*'00参数面板'!$C$42)+('00参数面板'!$F$36*30)+('00参数面板'!$H$36*'00参数面板'!$C$42) | N38: =((('00参数面板'!$C$36/'00参数面板'!$E$36)*'00参数面板'!$C$42)+('00参数面板'!$F$36*30)+('00参数面板'!$H$36*'00参数面板'!$C$42))/'00参数面板'!$C$36 | O38: ='00参数面板'!$B$42
A39: ='00参数面板'!$A$36 | B39: ='00参数面板'!$C$36 | C39: ='00参数面板'!$E$36 | D39: ='00参数面板'!$C$36/'00参数面板'!$E$36 | E39: ='00参数面板'!$A$43 | F39: ='00参数面板'!$C$43 | G39: ='00参数面板'!$C$43/'00参数面板'!$C$41 | H39: =('00参数面板'!$C$36/'00参数面板'!$E$36)*'00参数面板'!$C$43 | I39: =(('00参数面板'!$C$36/'00参数面板'!$E$36)*'00参数面板'!$C$43)/'00参数面板'!$C$36 | J39: ='00参数面板'!$F$36 | K39: ='00参数面板'!$F$36*30 | L39: ='00参数面板'!$H$36*'00参数面板'!$C$43 | M39: =(('00参数面板'!$C$36/'00参数面板'!$E$36)*'00参数面板'!$C$43)+('00参数面板'!$F$36*30)+('00参数面板'!$H$36*'00参数面板'!$C$43) | N39: =((('00参数面板'!$C$36/'00参数面板'!$E$36)*'00参数面板'!$C$43)+('00参数面板'!$F$36*30)+('00参数面板'!$H$36*'00参数面板'!$C$43))/'00参数面板'!$C$36 | O39: ='00参数面板'!$B$43
A40: ='00参数面板'!$A$36 | B40: ='00参数面板'!$C$36 | C40: ='00参数面板'!$E$36 | D40: ='00参数面板'!$C$36/'00参数面板'!$E$36 | E40: ='00参数面板'!$A$44 | F40: ='00参数面板'!$C$44 | G40: ='00参数面板'!$C$44/'00参数面板'!$C$41 | H40: =('00参数面板'!$C$36/'00参数面板'!$E$36)*'00参数面板'!$C$44 | I40: =(('00参数面板'!$C$36/'00参数面板'!$E$36)*'00参数面板'!$C$44)/'00参数面板'!$C$36 | J40: ='00参数面板'!$F$36 | K40: ='00参数面板'!$F$36*30 | L40: ='00参数面板'!$H$36*'00参数面板'!$C$44 | M40: =(('00参数面板'!$C$36/'00参数面板'!$E$36)*'00参数面板'!$C$44)+('00参数面板'!$F$36*30)+('00参数面板'!$H$36*'00参数面板'!$C$44) | N40: =((('00参数面板'!$C$36/'00参数面板'!$E$36)*'00参数面板'!$C$44)+('00参数面板'!$F$36*30)+('00参数面板'!$H$36*'00参数面板'!$C$44))/'00参数面板'!$C$36 | O40: ='00参数面板'!$B$44
A41: ='00参数面板'!$A$36 | B41: ='00参数面板'!$C$36 | C41: ='00参数面板'!$E$36 | D41: ='00参数面板'!$C$36/'00参数面板'!$E$36 | E41: ='00参数面板'!$A$45 | F41: ='00参数面板'!$C$45 | G41: ='00参数面板'!$C$45/'00参数面板'!$C$41 | H41: =('00参数面板'!$C$36/'00参数面板'!$E$36)*'00参数面板'!$C$45 | I41: =(('00参数面板'!$C$36/'00参数面板'!$E$36)*'00参数面板'!$C$45)/'00参数面板'!$C$36 | J41: ='00参数面板'!$F$36 | K41: ='00参数面板'!$F$36*30 | L41: ='00参数面板'!$H$36*'00参数面板'!$C$45 | M41: =(('00参数面板'!$C$36/'00参数面板'!$E$36)*'00参数面板'!$C$45)+('00参数面板'!$F$36*30)+('00参数面板'!$H$36*'00参数面板'!$C$45) | N41: =((('00参数面板'!$C$36/'00参数面板'!$E$36)*'00参数面板'!$C$45)+('00参数面板'!$F$36*30)+('00参数面板'!$H$36*'00参数面板'!$C$45))/'00参数面板'!$C$36 | O41: ='00参数面板'!$B$45
A42: ='00参数面板'!$A$36 | B42: ='00参数面板'!$C$36 | C42: ='00参数面板'!$E$36 | D42: ='00参数面板'!$C$36/'00参数面板'!$E$36 | E42: ='00参数面板'!$A$46 | F42: ='00参数面板'!$C$46 | G42: ='00参数面板'!$C$46/'00参数面板'!$C$41 | H42: =('00参数面板'!$C$36/'00参数面板'!$E$36)*'00参数面板'!$C$46 | I42: =(('00参数面板'!$C$36/'00参数面板'!$E$36)*'00参数面板'!$C$46)/'00参数面板'!$C$36 | J42: ='00参数面板'!$F$36 | K42: ='00参数面板'!$F$36*30 | L42: ='00参数面板'!$H$36*'00参数面板'!$C$46 | M42: =(('00参数面板'!$C$36/'00参数面板'!$E$36)*'00参数面板'!$C$46)+('00参数面板'!$F$36*30)+('00参数面板'!$H$36*'00参数面板'!$C$46) | N42: =((('00参数面板'!$C$36/'00参数面板'!$E$36)*'00参数面板'!$C$46)+('00参数面板'!$F$36*30)+('00参数面板'!$H$36*'00参数面板'!$C$46))/'00参数面板'!$C$36 | O42: ='00参数面板'!$B$46
A45: ③ 图表数据（各节点总资产 × 价格阶段）
A46: 节点\阶段 | B46: ='00参数面板'!$A$41 | C46: ='00参数面板'!$A$42 | D46: ='00参数面板'!$A$43 | E46: ='00参数面板'!$A$44 | F46: ='00参数面板'!$A$45 | G46: ='00参数面板'!$A$46
A47: ='00参数面板'!$A$33 | B47: =M16 | C47: =M17 | D47: =M18 | E47: =M19 | F47: =M20 | G47: =M21
A48: ='00参数面板'!$A$34 | B48: =M23 | C48: =M24 | D48: =M25 | E48: =M26 | F48: =M27 | G48: =M28
A49: ='00参数面板'!$A$35 | B49: =M30 | C49: =M31 | D49: =M32 | E49: =M33 | F49: =M34 | G49: =M35
A50: ='00参数面板'!$A$36 | B50: =M37 | C50: =M38 | D50: =M39 | E50: =M40 | F50: =M41 | G50: =M42

Sheet 02子币走势分析
A1: 子TOKEN（符火）价格走势 × 通缩模型 × 节点关系分析
A2: 🔒 固定常量 | D2: 📝 可变输入 | G2: 📊 计算结果（公式联动） | J2: 修改参数面板D28/D29 → 本表自动更新
A4: ① 子TOKEN月度通缩进程（公式：初始量×(1-燃烧率)^天数）
A5: 月份 | B5: 天数 | C5: 流通量(枚) | D5: 流通占比(%) | E5: 当月燃烧(枚) | F5: 累计燃烧(枚) | G5: 累计燃烧% | H5: 通缩驱动指数 | I5: 子币支撑价($)低 | J5: 子币支撑价($)高 | K5: 备注
A6: 初始 | B6: 0 | C6: ='00参数面板'!$C$27*(1-'00参数面板'!$C$26)^0 | D6: =('00参数面板'!$C$27*(1-'00参数面板'!$C$26)^0)/'00参数面板'!$C$27 | E6: 0 | F6: ='00参数面板'!$C$27-('00参数面板'!$C$27*(1-'00参数面板'!$C$26)^0) | G6: =('00参数面板'!$C$27-('00参数面板'!$C$27*(1-'00参数面板'!$C$26)^0))/'00参数面板'!$C$27 | H6: =1/(('00参数面板'!$C$27*(1-'00参数面板'!$C$26)^0)/'00参数面板'!$C$27) | I6: ='00参数面板'!$C$25*(1/(('00参数面板'!$C$27*(1-'00参数面板'!$C$26)^0)/'00参数面板'!$C$27))*0.8 | J6: ='00参数面板'!$C$25*(1/(('00参数面板'!$C$27*(1-'00参数面板'!$C$26)^0)/'00参数面板'!$C$27))*1.2 | K6: 流通量=13,100,000枚
A7: 第1月 | B7: 30 | C7: ='00参数面板'!$C$27*(1-'00参数面板'!$C$26)^30 | D7: =('00参数面板'!$C$27*(1-'00参数面板'!$C$26)^30)/'00参数面板'!$C$27 | E7: =C6-C7 | F7: ='00参数面板'!$C$27-('00参数面板'!$C$27*(1-'00参数面板'!$C$26)^30) | G7: =('00参数面板'!$C$27-('00参数面板'!$C$27*(1-'00参数面板'!$C$26)^30))/'00参数面板'!$C$27 | H7: =1/(('00参数面板'!$C$27*(1-'00参数面板'!$C$26)^30)/'00参数面板'!$C$27) | I7: ='00参数面板'!$C$25*(1/(('00参数面板'!$C$27*(1-'00参数面板'!$C$26)^30)/'00参数面板'!$C$27))*0.8 | J7: ='00参数面板'!$C$25*(1/(('00参数面板'!$C$27*(1-'00参数面板'!$C$26)^30)/'00参数面板'!$C$27))*1.2 | K7: 流通量=12,336,374枚
A8: 第2月 | B8: 60 | C8: ='00参数面板'!$C$27*(1-'00参数面板'!$C$26)^60 | D8: =('00参数面板'!$C$27*(1-'00参数面板'!$C$26)^60)/'00参数面板'!$C$27 | E8: =C7-C8 | F8: ='00参数面板'!$C$27-('00参数面板'!$C$27*(1-'00参数面板'!$C$26)^60) | G8: =('00参数面板'!$C$27-('00参数面板'!$C$27*(1-'00参数面板'!$C$26)^60))/'00参数面板'!$C$27 | H8: =1/(('00参数面板'!$C$27*(1-'00参数面板'!$C$26)^60)/'00参数面板'!$C$27) | I8: ='00参数面板'!$C$25*(1/(('00参数面板'!$C$27*(1-'00参数面板'!$C$26)^60)/'00参数面板'!$C$27))*0.8 | J8: ='00参数面板'!$C$25*(1/(('00参数面板'!$C$27*(1-'00参数面板'!$C$26)^60)/'00参数面板'!$C$27))*1.2 | K8: 流通量=11,617,261枚
A9: 第3月 | B9: 90 | C9: ='00参数面板'!$C$27*(1-'00参数面板'!$C$26)^90 | D9: =('00参数面板'!$C$27*(1-'00参数面板'!$C$26)^90)/'00参数面板'!$C$27 | E9: =C8-C9 | F9: ='00参数面板'!$C$27-('00参数面板'!$C$27*(1-'00参数面板'!$C$26)^90) | G9: =('00参数面板'!$C$27-('00参数面板'!$C$27*(1-'00参数面板'!$C$26)^90))/'00参数面板'!$C$27 | H9: =1/(('00参数面板'!$C$27*(1-'00参数面板'!$C$26)^90)/'00参数面板'!$C$27) | I9: ='00参数面板'!$C$25*(1/(('00参数面板'!$C$27*(1-'00参数面板'!$C$26)^90)/'00参数面板'!$C$27))*0.8 | J9: ='00参数面板'!$C$25*(1/(('00参数面板'!$C$27*(1-'00参数面板'!$C$26)^90)/'00参数面板'!$C$27))*1.2 | K9: 流通量=10,940,067枚
A10: 第4月 | B10: 120 | C10: ='00参数面板'!$C$27*(1-'00参数面板'!$C$26)^120 | D10: =('00参数面板'!$C$27*(1-'00参数面板'!$C$26)^120)/'00参数面板'!$C$27 | E10: =C9-C10 | F10: ='00参数面板'!$C$27-('00参数面板'!$C$27*(1-'00参数面板'!$C$26)^120) | G10: =('00参数面板'!$C$27-('00参数面板'!$C$27*(1-'00参数面板'!$C$26)^120))/'00参数面板'!$C$27 | H10: =1/(('00参数面板'!$C$27*(1-'00参数面板'!$C$26)^120)/'00参数面板'!$C$27) | I10: ='00参数面板'!$C$25*(1/(('00参数面板'!$C$27*(1-'00参数面板'!$C$26)^120)/'00参数面板'!$C$27))*0.8 | J10: ='00参数面板'!$C$25*(1/(('00参数面板'!$C$27*(1-'00参数面板'!$C$26)^120)/'00参数面板'!$C$27))*1.2 | K10: 流通量=10,302,348枚
A11: 第5月 | B11: 150 | C11: ='00参数面板'!$C$27*(1-'00参数面板'!$C$26)^150 | D11: =('00参数面板'!$C$27*(1-'00参数面板'!$C$26)^150)/'00参数面板'!$C$27 | E11: =C10-C11 | F11: ='00参数面板'!$C$27-('00参数面板'!$C$27*(1-'00参数面板'!$C$26)^150) | G11: =('00参数面板'!$C$27-('00参数面板'!$C$27*(1-'00参数面板'!$C$26)^150))/'00参数面板'!$C$27 | H11: =1/(('00参数面板'!$C$27*(1-'00参数面板'!$C$26)^150)/'00参数面板'!$C$27) | I11: ='00参数面板'!$C$25*(1/(('00参数面板'!$C$27*(1-'00参数面板'!$C$26)^150)/'00参数面板'!$C$27))*0.8 | J11: ='00参数面板'!$C$25*(1/(('00参数面板'!$C$27*(1-'00参数面板'!$C$26)^150)/'00参数面板'!$C$27))*1.2 | K11: 流通量=9,701,803枚
A12: 第6月 | B12: 180 | C12: ='00参数面板'!$C$27*(1-'00参数面板'!$C$26)^180 | D12: =('00参数面板'!$C$27*(1-'00参数面板'!$C$26)^180)/'00参数面板'!$C$27 | E12: =C11-C12 | F12: ='00参数面板'!$C$27-('00参数面板'!$C$27*(1-'00参数面板'!$C$26)^180) | G12: =('00参数面板'!$C$27-('00参数面板'!$C$27*(1-'00参数面板'!$C$26)^180))/'00参数面板'!$C$27 | H12: =1/(('00参数面板'!$C$27*(1-'00参数面板'!$C$26)^180)/'00参数面板'!$C$27) | I12: ='00参数面板'!$C$25*(1/(('00参数面板'!$C$27*(1-'00参数面板'!$C$26)^180)/'00参数面板'!$C$27))*0.8 | J12: ='00参数面板'!$C$25*(1/(('00参数面板'!$C$27*(1-'00参数面板'!$C$26)^180)/'00参数面板'!$C$27))*1.2 | K12: 流通量=9,136,265枚
A13: 第9月 | B13: 270 | C13: ='00参数面板'!$C$27*(1-'00参数面板'!$C$26)^270 | D13: =('00参数面板'!$C$27*(1-'00参数面板'!$C$26)^270)/'00参数面板'!$C$27 | E13: =C12-C13 | F13: ='00参数面板'!$C$27-('00参数面板'!$C$27*(1-'00参数面板'!$C$26)^270) | G13: =('00参数面板'!$C$27-('00参数面板'!$C$27*(1-'00参数面板'!$C$26)^270))/'00参数面板'!$C$27 | H13: =1/(('00参数面板'!$C$27*(1-'00参数面板'!$C$26)^270)/'00参数面板'!$C$27) | I13: ='00参数面板'!$C$25*(1/(('00参数面板'!$C$27*(1-'00参数面板'!$C$26)^270)/'00参数面板'!$C$27))*0.8 | J13: ='00参数面板'!$C$25*(1/(('00参数面板'!$C$27*(1-'00参数面板'!$C$26)^270)/'00参数面板'!$C$27))*1.2 | K13: 流通量=7,629,875枚
A14: 第12月 | B14: 360 | C14: ='00参数面板'!$C$27*(1-'00参数面板'!$C$26)^360 | D14: =('00参数面板'!$C$27*(1-'00参数面板'!$C$26)^360)/'00参数面板'!$C$27 | E14: =C13-C14 | F14: ='00参数面板'!$C$27-('00参数面板'!$C$27*(1-'00参数面板'!$C$26)^360) | G14: =('00参数面板'!$C$27-('00参数面板'!$C$27*(1-'00参数面板'!$C$26)^360))/'00参数面板'!$C$27 | H14: =1/(('00参数面板'!$C$27*(1-'00参数面板'!$C$26)^360)/'00参数面板'!$C$27) | I14: ='00参数面板'!$C$25*(1/(('00参数面板'!$C$27*(1-'00参数面板'!$C$26)^360)/'00参数面板'!$C$27))*0.8 | J14: ='00参数面板'!$C$25*(1/(('00参数面板'!$C$27*(1-'00参数面板'!$C$26)^360)/'00参数面板'!$C$27))*1.2 | K14: 流通量=6,371,859枚
A15: 第15月 | B15: 450 | C15: ='00参数面板'!$C$27*(1-'00参数面板'!$C$26)^450 | D15: =('00参数面板'!$C$27*(1-'00参数面板'!$C$26)^450)/'00参数面板'!$C$27 | E15: =C14-C15 | F15: ='00参数面板'!$C$27-('00参数面板'!$C$27*(1-'00参数面板'!$C$26)^450) | G15: =('00参数面板'!$C$27-('00参数面板'!$C$27*(1-'00参数面板'!$C$26)^450))/'00参数面板'!$C$27 | H15: =1/(('00参数面板'!$C$27*(1-'00参数面板'!$C$26)^450)/'00参数面板'!$C$27) | I15: ='00参数面板'!$C$25*(1/(('00参数面板'!$C$27*(1-'00参数面板'!$C$26)^450)/'00参数面板'!$C$27))*0.8 | J15: ='00参数面板'!$C$25*(1/(('00参数面板'!$C$27*(1-'00参数面板'!$C$26)^450)/'00参数面板'!$C$27))*1.2 | K15: 流通量=5,321,264枚
A16: 第18月 | B16: 540 | C16: ='00参数面板'!$C$27*(1-'00参数面板'!$C$26)^540 | D16: =('00参数面板'!$C$27*(1-'00参数面板'!$C$26)^540)/'00参数面板'!$C$27 | E16: =C15-C16 | F16: ='00参数面板'!$C$27-('00参数面板'!$C$27*(1-'00参数面板'!$C$26)^540) | G16: =('00参数面板'!$C$27-('00参数面板'!$C$27*(1-'00参数面板'!$C$26)^540))/'00参数面板'!$C$27 | H16: =1/(('00参数面板'!$C$27*(1-'00参数面板'!$C$26)^540)/'00参数面板'!$C$27) | I16: ='00参数面板'!$C$25*(1/(('00参数面板'!$C$27*(1-'00参数面板'!$C$26)^540)/'00参数面板'!$C$27))*0.8 | J16: ='00参数面板'!$C$25*(1/(('00参数面板'!$C$27*(1-'00参数面板'!$C$26)^540)/'00参数面板'!$C$27))*1.2 | K16: 流通量=4,443,892枚
A17: 第21月 | B17: 630 | C17: ='00参数面板'!$C$27*(1-'00参数面板'!$C$26)^630 | D17: =('00参数面板'!$C$27*(1-'00参数面板'!$C$26)^630)/'00参数面板'!$C$27 | E17: =C16-C17 | F17: ='00参数面板'!$C$27-('00参数面板'!$C$27*(1-'00参数面板'!$C$26)^630) | G17: =('00参数面板'!$C$27-('00参数面板'!$C$27*(1-'00参数面板'!$C$26)^630))/'00参数面板'!$C$27 | H17: =1/(('00参数面板'!$C$27*(1-'00参数面板'!$C$26)^630)/'00参数面板'!$C$27) | I17: ='00参数面板'!$C$25*(1/(('00参数面板'!$C$27*(1-'00参数面板'!$C$26)^630)/'00参数面板'!$C$27))*0.8 | J17: ='00参数面板'!$C$25*(1/(('00参数面板'!$C$27*(1-'00参数面板'!$C$26)^630)/'00参数面板'!$C$27))*1.2 | K17: 流通量=3,711,182枚
A18: 第24月 | B18: 720 | C18: ='00参数面板'!$C$27*(1-'00参数面板'!$C$26)^720 | D18: =('00参数面板'!$C$27*(1-'00参数面板'!$C$26)^720)/'00参数面板'!$C$27 | E18: =C17-C18 | F18: ='00参数面板'!$C$27-('00参数面板'!$C$27*(1-'00参数面板'!$C$26)^720) | G18: =('00参数面板'!$C$27-('00参数面板'!$C$27*(1-'00参数面板'!$C$26)^720))/'00参数面板'!$C$27 | H18: =1/(('00参数面板'!$C$27*(1-'00参数面板'!$C$26)^720)/'00参数面板'!$C$27) | I18: ='00参数面板'!$C$25*(1/(('00参数面板'!$C$27*(1-'00参数面板'!$C$26)^720)/'00参数面板'!$C$27))*0.8 | J18: ='00参数面板'!$C$25*(1/(('00参数面板'!$C$27*(1-'00参数面板'!$C$26)^720)/'00参数面板'!$C$27))*1.2 | K18: 流通量=3,099,281枚
A21: ② 各节点 × 子TOKEN收益（打新额度+交易税分红，全公式联动）
A22: 节点 | B22: 权重 | C22: 权重占比(%) | D22: 子币阶段 | E22: 子TOKEN价($) | F22: 子币涨幅× | G22: 打新额度/席(U) | H22: 打新子TOKEN(枚) | I22: 打新价值(U) | J22: 月交易税分红/席(U) | K22: 月子币综合收益(U)
A23: ='00参数面板'!$A$33 | B23: ='00参数面板'!$G$33 | C23: =('00参数面板'!$G$33*'00参数面板'!$D$33)/('00参数面板'!$D$33*'00参数面板'!$G$33+'00参数面板'!$D$34*'00参数面板'!$G$34+'00参数面板'!$D$35*'00参数面板'!$G$35+'00参数面板'!$D$36*'00参数面板'!$G$36) | D23: ='00参数面板'!$A$41 | E23: ='00参数面板'!$D$41 | F23: ='00参数面板'!$D$41/'00参数面板'!$C$25 | G23: =500000*(('00参数面板'!$G$33*'00参数面板'!$D$33)/('00参数面板'!$D$33*'00参数面板'!$G$33+'00参数面板'!$D$34*'00参数面板'!$G$34+'00参数面板'!$D$35*'00参数面板'!$G$35+'00参数面板'!$D$36*'00参数面板'!$G$36))/'00参数面板'!$D$33 | H23: =(500000*(('00参数面板'!$G$33*'00参数面板'!$D$33)/('00参数面板'!$D$33*'00参数面板'!$G$33+'00参数面板'!$D$34*'00参数面板'!$G$34+'00参数面板'!$D$35*'00参数面板'!$G$35+'00参数面板'!$D$36*'00参数面板'!$G$36))/'00参数面板'!$D$33)/'00参数面板'!$D$41 | I23: =(500000*(('00参数面板'!$G$33*'00参数面板'!$D$33)/('00参数面板'!$D$33*'00参数面板'!$G$33+'00参数面板'!$D$34*'00参数面板'!$G$34+'00参数面板'!$D$35*'00参数面板'!$G$35+'00参数面板'!$D$36*'00参数面板'!$G$36))/'00参数面板'!$D$33) | J23: =2500000*0.05*0.4*(('00参数面板'!$G$33*'00参数面板'!$D$33)/('00参数面板'!$D$33*'00参数面板'!$G$33+'00参数面板'!$D$34*'00参数面板'!$G$34+'00参数面板'!$D$35*'00参数面板'!$G$35+'00参数面板'!$D$36*'00参数面板'!$G$36))/'00参数面板'!$D$33 | K23: =(500000*(('00参数面板'!$G$33*'00参数面板'!$D$33)/('00参数面板'!$D$33*'00参数面板'!$G$33+'00参数面板'!$D$34*'00参数面板'!$G$34+'00参数面板'!$D$35*'00参数面板'!$G$35+'00参数面板'!$D$36*'00参数面板'!$G$36))/'00参数面板'!$D$33)/12+2500000*0.05*0.4*(('00参数面板'!$G$33*'00参数面板'!$D$33)/('00参数面板'!$D$33*'00参数面板'!$G$33+'00参数面板'!$D$34*'00参数面板'!$G$34+'00参数面板'!$D$35*'00参数面板'!$G$35+'00参数面板'!$D$36*'00参数面板'!$G$36))/'00参数面板'!$D$33
A24: ='00参数面板'!$A$33 | B24: ='00参数面板'!$G$33 | C24: =('00参数面板'!$G$33*'00参数面板'!$D$33)/('00参数面板'!$D$33*'00参数面板'!$G$33+'00参数面板'!$D$34*'00参数面板'!$G$34+'00参数面板'!$D$35*'00参数面板'!$G$35+'00参数面板'!$D$36*'00参数面板'!$G$36) | D24: ='00参数面板'!$A$42 | E24: ='00参数面板'!$D$42 | F24: ='00参数面板'!$D$42/'00参数面板'!$C$25 | G24: =500000*(('00参数面板'!$G$33*'00参数面板'!$D$33)/('00参数面板'!$D$33*'00参数面板'!$G$33+'00参数面板'!$D$34*'00参数面板'!$G$34+'00参数面板'!$D$35*'00参数面板'!$G$35+'00参数面板'!$D$36*'00参数面板'!$G$36))/'00参数面板'!$D$33 | H24: =(500000*(('00参数面板'!$G$33*'00参数面板'!$D$33)/('00参数面板'!$D$33*'00参数面板'!$G$33+'00参数面板'!$D$34*'00参数面板'!$G$34+'00参数面板'!$D$35*'00参数面板'!$G$35+'00参数面板'!$D$36*'00参数面板'!$G$36))/'00参数面板'!$D$33)/'00参数面板'!$D$42 | I24: =(500000*(('00参数面板'!$G$33*'00参数面板'!$D$33)/('00参数面板'!$D$33*'00参数面板'!$G$33+'00参数面板'!$D$34*'00参数面板'!$G$34+'00参数面板'!$D$35*'00参数面板'!$G$35+'00参数面板'!$D$36*'00参数面板'!$G$36))/'00参数面板'!$D$33) | J24: =2500000*0.05*0.4*(('00参数面板'!$G$33*'00参数面板'!$D$33)/('00参数面板'!$D$33*'00参数面板'!$G$33+'00参数面板'!$D$34*'00参数面板'!$G$34+'00参数面板'!$D$35*'00参数面板'!$G$35+'00参数面板'!$D$36*'00参数面板'!$G$36))/'00参数面板'!$D$33 | K24: =(500000*(('00参数面板'!$G$33*'00参数面板'!$D$33)/('00参数面板'!$D$33*'00参数面板'!$G$33+'00参数面板'!$D$34*'00参数面板'!$G$34+'00参数面板'!$D$35*'00参数面板'!$G$35+'00参数面板'!$D$36*'00参数面板'!$G$36))/'00参数面板'!$D$33)/12+2500000*0.05*0.4*(('00参数面板'!$G$33*'00参数面板'!$D$33)/('00参数面板'!$D$33*'00参数面板'!$G$33+'00参数面板'!$D$34*'00参数面板'!$G$34+'00参数面板'!$D$35*'00参数面板'!$G$35+'00参数面板'!$D$36*'00参数面板'!$G$36))/'00参数面板'!$D$33
A25: ='00参数面板'!$A$33 | B25: ='00参数面板'!$G$33 | C25: =('00参数面板'!$G$33*'00参数面板'!$D$33)/('00参数面板'!$D$33*'00参数面板'!$G$33+'00参数面板'!$D$34*'00参数面板'!$G$34+'00参数面板'!$D$35*'00参数面板'!$G$35+'00参数面板'!$D$36*'00参数面板'!$G$36) | D25: ='00参数面板'!$A$43 | E25: ='00参数面板'!$D$43 | F25: ='00参数面板'!$D$43/'00参数面板'!$C$25 | G25: =500000*(('00参数面板'!$G$33*'00参数面板'!$D$33)/('00参数面板'!$D$33*'00参数面板'!$G$33+'00参数面板'!$D$34*'00参数面板'!$G$34+'00参数面板'!$D$35*'00参数面板'!$G$35+'00参数面板'!$D$36*'00参数面板'!$G$36))/'00参数面板'!$D$33 | H25: =(500000*(('00参数面板'!$G$33*'00参数面板'!$D$33)/('00参数面板'!$D$33*'00参数面板'!$G$33+'00参数面板'!$D$34*'00参数面板'!$G$34+'00参数面板'!$D$35*'00参数面板'!$G$35+'00参数面板'!$D$36*'00参数面板'!$G$36))/'00参数面板'!$D$33)/'00参数面板'!$D$43 | I25: =(500000*(('00参数面板'!$G$33*'00参数面板'!$D$33)/('00参数面板'!$D$33*'00参数面板'!$G$33+'00参数面板'!$D$34*'00参数面板'!$G$34+'00参数面板'!$D$35*'00参数面板'!$G$35+'00参数面板'!$D$36*'00参数面板'!$G$36))/'00参数面板'!$D$33) | J25: =2500000*0.05*0.4*(('00参数面板'!$G$33*'00参数面板'!$D$33)/('00参数面板'!$D$33*'00参数面板'!$G$33+'00参数面板'!$D$34*'00参数面板'!$G$34+'00参数面板'!$D$35*'00参数面板'!$G$35+'00参数面板'!$D$36*'00参数面板'!$G$36))/'00参数面板'!$D$33 | K25: =(500000*(('00参数面板'!$G$33*'00参数面板'!$D$33)/('00参数面板'!$D$33*'00参数面板'!$G$33+'00参数面板'!$D$34*'00参数面板'!$G$34+'00参数面板'!$D$35*'00参数面板'!$G$35+'00参数面板'!$D$36*'00参数面板'!$G$36))/'00参数面板'!$D$33)/12+2500000*0.05*0.4*(('00参数面板'!$G$33*'00参数面板'!$D$33)/('00参数面板'!$D$33*'00参数面板'!$G$33+'00参数面板'!$D$34*'00参数面板'!$G$34+'00参数面板'!$D$35*'00参数面板'!$G$35+'00参数面板'!$D$36*'00参数面板'!$G$36))/'00参数面板'!$D$33
A26: ='00参数面板'!$A$33 | B26: ='00参数面板'!$G$33 | C26: =('00参数面板'!$G$33*'00参数面板'!$D$33)/('00参数面板'!$D$33*'00参数面板'!$G$33+'00参数面板'!$D$34*'00参数面板'!$G$34+'00参数面板'!$D$35*'00参数面板'!$G$35+'00参数面板'!$D$36*'00参数面板'!$G$36) | D26: ='00参数面板'!$A$44 | E26: ='00参数面板'!$D$44 | F26: ='00参数面板'!$D$44/'00参数面板'!$C$25 | G26: =500000*(('00参数面板'!$G$33*'00参数面板'!$D$33)/('00参数面板'!$D$33*'00参数面板'!$G$33+'00参数面板'!$D$34*'00参数面板'!$G$34+'00参数面板'!$D$35*'00参数面板'!$G$35+'00参数面板'!$D$36*'00参数面板'!$G$36))/'00参数面板'!$D$33 | H26: =(500000*(('00参数面板'!$G$33*'00参数面板'!$D$33)/('00参数面板'!$D$33*'00参数面板'!$G$33+'00参数面板'!$D$34*'00参数面板'!$G$34+'00参数面板'!$D$35*'00参数面板'!$G$35+'00参数面板'!$D$36*'00参数面板'!$G$36))/'00参数面板'!$D$33)/'00参数面板'!$D$44 | I26: =(500000*(('00参数面板'!$G$33*'00参数面板'!$D$33)/('00参数面板'!$D$33*'00参数面板'!$G$33+'00参数面板'!$D$34*'00参数面板'!$G$34+'00参数面板'!$D$35*'00参数面板'!$G$35+'00参数面板'!$D$36*'00参数面板'!$G$36))/'00参数面板'!$D$33) | J26: =2500000*0.05*0.4*(('00参数面板'!$G$33*'00参数面板'!$D$33)/('00参数面板'!$D$33*'00参数面板'!$G$33+'00参数面板'!$D$34*'00参数面板'!$G$34+'00参数面板'!$D$35*'00参数面板'!$G$35+'00参数面板'!$D$36*'00参数面板'!$G$36))/'00参数面板'!$D$33 | K26: =(500000*(('00参数面板'!$G$33*'00参数面板'!$D$33)/('00参数面板'!$D$33*'00参数面板'!$G$33+'00参数面板'!$D$34*'00参数面板'!$G$34+'00参数面板'!$D$35*'00参数面板'!$G$35+'00参数面板'!$D$36*'00参数面板'!$G$36))/'00参数面板'!$D$33)/12+2500000*0.05*0.4*(('00参数面板'!$G$33*'00参数面板'!$D$33)/('00参数面板'!$D$33*'00参数面板'!$G$33+'00参数面板'!$D$34*'00参数面板'!$G$34+'00参数面板'!$D$35*'00参数面板'!$G$35+'00参数面板'!$D$36*'00参数面板'!$G$36))/'00参数面板'!$D$33
A27: ='00参数面板'!$A$33 | B27: ='00参数面板'!$G$33 | C27: =('00参数面板'!$G$33*'00参数面板'!$D$33)/('00参数面板'!$D$33*'00参数面板'!$G$33+'00参数面板'!$D$34*'00参数面板'!$G$34+'00参数面板'!$D$35*'00参数面板'!$G$35+'00参数面板'!$D$36*'00参数面板'!$G$36) | D27: ='00参数面板'!$A$45 | E27: ='00参数面板'!$D$45 | F27: ='00参数面板'!$D$45/'00参数面板'!$C$25 | G27: =500000*(('00参数面板'!$G$33*'00参数面板'!$D$33)/('00参数面板'!$D$33*'00参数面板'!$G$33+'00参数面板'!$D$34*'00参数面板'!$G$34+'00参数面板'!$D$35*'00参数面板'!$G$35+'00参数面板'!$D$36*'00参数面板'!$G$36))/'00参数面板'!$D$33 | H27: =(500000*(('00参数面板'!$G$33*'00参数面板'!$D$33)/('00参数面板'!$D$33*'00参数面板'!$G$33+'00参数面板'!$D$34*'00参数面板'!$G$34+'00参数面板'!$D$35*'00参数面板'!$G$35+'00参数面板'!$D$36*'00参数面板'!$G$36))/'00参数面板'!$D$33)/'00参数面板'!$D$45 | I27: =(500000*(('00参数面板'!$G$33*'00参数面板'!$D$33)/('00参数面板'!$D$33*'00参数面板'!$G$33+'00参数面板'!$D$34*'00参数面板'!$G$34+'00参数面板'!$D$35*'00参数面板'!$G$35+'00参数面板'!$D$36*'00参数面板'!$G$36))/'00参数面板'!$D$33) | J27: =2500000*0.05*0.4*(('00参数面板'!$G$33*'00参数面板'!$D$33)/('00参数面板'!$D$33*'00参数面板'!$G$33+'00参数面板'!$D$34*'00参数面板'!$G$34+'00参数面板'!$D$35*'00参数面板'!$G$35+'00参数面板'!$D$36*'00参数面板'!$G$36))/'00参数面板'!$D$33 | K27: =(500000*(('00参数面板'!$G$33*'00参数面板'!$D$33)/('00参数面板'!$D$33*'00参数面板'!$G$33+'00参数面板'!$D$34*'00参数面板'!$G$34+'00参数面板'!$D$35*'00参数面板'!$G$35+'00参数面板'!$D$36*'00参数面板'!$G$36))/'00参数面板'!$D$33)/12+2500000*0.05*0.4*(('00参数面板'!$G$33*'00参数面板'!$D$33)/('00参数面板'!$D$33*'00参数面板'!$G$33+'00参数面板'!$D$34*'00参数面板'!$G$34+'00参数面板'!$D$35*'00参数面板'!$G$35+'00参数面板'!$D$36*'00参数面板'!$G$36))/'00参数面板'!$D$33
A28: ='00参数面板'!$A$33 | B28: ='00参数面板'!$G$33 | C28: =('00参数面板'!$G$33*'00参数面板'!$D$33)/('00参数面板'!$D$33*'00参数面板'!$G$33+'00参数面板'!$D$34*'00参数面板'!$G$34+'00参数面板'!$D$35*'00参数面板'!$G$35+'00参数面板'!$D$36*'00参数面板'!$G$36) | D28: ='00参数面板'!$A$46 | E28: ='00参数面板'!$D$46 | F28: ='00参数面板'!$D$46/'00参数面板'!$C$25 | G28: =500000*(('00参数面板'!$G$33*'00参数面板'!$D$33)/('00参数面板'!$D$33*'00参数面板'!$G$33+'00参数面板'!$D$34*'00参数面板'!$G$34+'00参数面板'!$D$35*'00参数面板'!$G$35+'00参数面板'!$D$36*'00参数面板'!$G$36))/'00参数面板'!$D$33 | H28: =(500000*(('00参数面板'!$G$33*'00参数面板'!$D$33)/('00参数面板'!$D$33*'00参数面板'!$G$33+'00参数面板'!$D$34*'00参数面板'!$G$34+'00参数面板'!$D$35*'00参数面板'!$G$35+'00参数面板'!$D$36*'00参数面板'!$G$36))/'00参数面板'!$D$33)/'00参数面板'!$D$46 | I28: =(500000*(('00参数面板'!$G$33*'00参数面板'!$D$33)/('00参数面板'!$D$33*'00参数面板'!$G$33+'00参数面板'!$D$34*'00参数面板'!$G$34+'00参数面板'!$D$35*'00参数面板'!$G$35+'00参数面板'!$D$36*'00参数面板'!$G$36))/'00参数面板'!$D$33) | J28: =2500000*0.05*0.4*(('00参数面板'!$G$33*'00参数面板'!$D$33)/('00参数面板'!$D$33*'00参数面板'!$G$33+'00参数面板'!$D$34*'00参数面板'!$G$34+'00参数面板'!$D$35*'00参数面板'!$G$35+'00参数面板'!$D$36*'00参数面板'!$G$36))/'00参数面板'!$D$33 | K28: =(500000*(('00参数面板'!$G$33*'00参数面板'!$D$33)/('00参数面板'!$D$33*'00参数面板'!$G$33+'00参数面板'!$D$34*'00参数面板'!$G$34+'00参数面板'!$D$35*'00参数面板'!$G$35+'00参数面板'!$D$36*'00参数面板'!$G$36))/'00参数面板'!$D$33)/12+2500000*0.05*0.4*(('00参数面板'!$G$33*'00参数面板'!$D$33)/('00参数面板'!$D$33*'00参数面板'!$G$33+'00参数面板'!$D$34*'00参数面板'!$G$34+'00参数面板'!$D$35*'00参数面板'!$G$35+'00参数面板'!$D$36*'00参数面板'!$G$36))/'00参数面板'!$D$33
A30: ='00参数面板'!$A$34 | B30: ='00参数面板'!$G$34 | C30: =('00参数面板'!$G$34*'00参数面板'!$D$34)/('00参数面板'!$D$33*'00参数面板'!$G$33+'00参数面板'!$D$34*'00参数面板'!$G$34+'00参数面板'!$D$35*'00参数面板'!$G$35+'00参数面板'!$D$36*'00参数面板'!$G$36) | D30: ='00参数面板'!$A$41 | E30: ='00参数面板'!$D$41 | F30: ='00参数面板'!$D$41/'00参数面板'!$C$25 | G30: =500000*(('00参数面板'!$G$34*'00参数面板'!$D$34)/('00参数面板'!$D$33*'00参数面板'!$G$33+'00参数面板'!$D$34*'00参数面板'!$G$34+'00参数面板'!$D$35*'00参数面板'!$G$35+'00参数面板'!$D$36*'00参数面板'!$G$36))/'00参数面板'!$D$34 | H30: =(500000*(('00参数面板'!$G$34*'00参数面板'!$D$34)/('00参数面板'!$D$33*'00参数面板'!$G$33+'00参数面板'!$D$34*'00参数面板'!$G$34+'00参数面板'!$D$35*'00参数面板'!$G$35+'00参数面板'!$D$36*'00参数面板'!$G$36))/'00参数面板'!$D$34)/'00参数面板'!$D$41 | I30: =(500000*(('00参数面板'!$G$34*'00参数面板'!$D$34)/('00参数面板'!$D$33*'00参数面板'!$G$33+'00参数面板'!$D$34*'00参数面板'!$G$34+'00参数面板'!$D$35*'00参数面板'!$G$35+'00参数面板'!$D$36*'00参数面板'!$G$36))/'00参数面板'!$D$34) | J30: =2500000*0.05*0.4*(('00参数面板'!$G$34*'00参数面板'!$D$34)/('00参数面板'!$D$33*'00参数面板'!$G$33+'00参数面板'!$D$34*'00参数面板'!$G$34+'00参数面板'!$D$35*'00参数面板'!$G$35+'00参数面板'!$D$36*'00参数面板'!$G$36))/'00参数面板'!$D$34 | K30: =(500000*(('00参数面板'!$G$34*'00参数面板'!$D$34)/('00参数面板'!$D$33*'00参数面板'!$G$33+'00参数面板'!$D$34*'00参数面板'!$G$34+'00参数面板'!$D$35*'00参数面板'!$G$35+'00参数面板'!$D$36*'00参数面板'!$G$36))/'00参数面板'!$D$34)/12+2500000*0.05*0.4*(('00参数面板'!$G$34*'00参数面板'!$D$34)/('00参数面板'!$D$33*'00参数面板'!$G$33+'00参数面板'!$D$34*'00参数面板'!$G$34+'00参数面板'!$D$35*'00参数面板'!$G$35+'00参数面板'!$D$36*'00参数面板'!$G$36))/'00参数面板'!$D$34
A31: ='00参数面板'!$A$34 | B31: ='00参数面板'!$G$34 | C31: =('00参数面板'!$G$34*'00参数面板'!$D$34)/('00参数面板'!$D$33*'00参数面板'!$G$33+'00参数面板'!$D$34*'00参数面板'!$G$34+'00参数面板'!$D$35*'00参数面板'!$G$35+'00参数面板'!$D$36*'00参数面板'!$G$36) | D31: ='00参数面板'!$A$42 | E31: ='00参数面板'!$D$42 | F31: ='00参数面板'!$D$42/'00参数面板'!$C$25 | G31: =500000*(('00参数面板'!$G$34*'00参数面板'!$D$34)/('00参数面板'!$D$33*'00参数面板'!$G$33+'00参数面板'!$D$34*'00参数面板'!$G$34+'00参数面板'!$D$35*'00参数面板'!$G$35+'00参数面板'!$D$36*'00参数面板'!$G$36))/'00参数面板'!$D$34 | H31: =(500000*(('00参数面板'!$G$34*'00参数面板'!$D$34)/('00参数面板'!$D$33*'00参数面板'!$G$33+'00参数面板'!$D$34*'00参数面板'!$G$34+'00参数面板'!$D$35*'00参数面板'!$G$35+'00参数面板'!$D$36*'00参数面板'!$G$36))/'00参数面板'!$D$34)/'00参数面板'!$D$42 | I31: =(500000*(('00参数面板'!$G$34*'00参数面板'!$D$34)/('00参数面板'!$D$33*'00参数面板'!$G$33+'00参数面板'!$D$34*'00参数面板'!$G$34+'00参数面板'!$D$35*'00参数面板'!$G$35+'00参数面板'!$D$36*'00参数面板'!$G$36))/'00参数面板'!$D$34) | J31: =2500000*0.05*0.4*(('00参数面板'!$G$34*'00参数面板'!$D$34)/('00参数面板'!$D$33*'00参数面板'!$G$33+'00参数面板'!$D$34*'00参数面板'!$G$34+'00参数面板'!$D$35*'00参数面板'!$G$35+'00参数面板'!$D$36*'00参数面板'!$G$36))/'00参数面板'!$D$34 | K31: =(500000*(('00参数面板'!$G$34*'00参数面板'!$D$34)/('00参数面板'!$D$33*'00参数面板'!$G$33+'00参数面板'!$D$34*'00参数面板'!$G$34+'00参数面板'!$D$35*'00参数面板'!$G$35+'00参数面板'!$D$36*'00参数面板'!$G$36))/'00参数面板'!$D$34)/12+2500000*0.05*0.4*(('00参数面板'!$G$34*'00参数面板'!$D$34)/('00参数面板'!$D$33*'00参数面板'!$G$33+'00参数面板'!$D$34*'00参数面板'!$G$34+'00参数面板'!$D$35*'00参数面板'!$G$35+'00参数面板'!$D$36*'00参数面板'!$G$36))/'00参数面板'!$D$34
A32: ='00参数面板'!$A$34 | B32: ='00参数面板'!$G$34 | C32: =('00参数面板'!$G$34*'00参数面板'!$D$34)/('00参数面板'!$D$33*'00参数面板'!$G$33+'00参数面板'!$D$34*'00参数面板'!$G$34+'00参数面板'!$D$35*'00参数面板'!$G$35+'00参数面板'!$D$36*'00参数面板'!$G$36) | D32: ='00参数面板'!$A$43 | E32: ='00参数面板'!$D$43 | F32: ='00参数面板'!$D$43/'00参数面板'!$C$25 | G32: =500000*(('00参数面板'!$G$34*'00参数面板'!$D$34)/('00参数面板'!$D$33*'00参数面板'!$G$33+'00参数面板'!$D$34*'00参数面板'!$G$34+'00参数面板'!$D$35*'00参数面板'!$G$35+'00参数面板'!$D$36*'00参数面板'!$G$36))/'00参数面板'!$D$34 | H32: =(500000*(('00参数面板'!$G$34*'00参数面板'!$D$34)/('00参数面板'!$D$33*'00参数面板'!$G$33+'00参数面板'!$D$34*'00参数面板'!$G$34+'00参数面板'!$D$35*'00参数面板'!$G$35+'00参数面板'!$D$36*'00参数面板'!$G$36))/'00参数面板'!$D$34)/'00参数面板'!$D$43 | I32: =(500000*(('00参数面板'!$G$34*'00参数面板'!$D$34)/('00参数面板'!$D$33*'00参数面板'!$G$33+'00参数面板'!$D$34*'00参数面板'!$G$34+'00参数面板'!$D$35*'00参数面板'!$G$35+'00参数面板'!$D$36*'00参数面板'!$G$36))/'00参数面板'!$D$34) | J32: =2500000*0.05*0.4*(('00参数面板'!$G$34*'00参数面板'!$D$34)/('00参数面板'!$D$33*'00参数面板'!$G$33+'00参数面板'!$D$34*'00参数面板'!$G$34+'00参数面板'!$D$35*'00参数面板'!$G$35+'00参数面板'!$D$36*'00参数面板'!$G$36))/'00参数面板'!$D$34 | K32: =(500000*(('00参数面板'!$G$34*'00参数面板'!$D$34)/('00参数面板'!$D$33*'00参数面板'!$G$33+'00参数面板'!$D$34*'00参数面板'!$G$34+'00参数面板'!$D$35*'00参数面板'!$G$35+'00参数面板'!$D$36*'00参数面板'!$G$36))/'00参数面板'!$D$34)/12+2500000*0.05*0.4*(('00参数面板'!$G$34*'00参数面板'!$D$34)/('00参数面板'!$D$33*'00参数面板'!$G$33+'00参数面板'!$D$34*'00参数面板'!$G$34+'00参数面板'!$D$35*'00参数面板'!$G$35+'00参数面板'!$D$36*'00参数面板'!$G$36))/'00参数面板'!$D$34
A33: ='00参数面板'!$A$34 | B33: ='00参数面板'!$G$34 | C33: =('00参数面板'!$G$34*'00参数面板'!$D$34)/('00参数面板'!$D$33*'00参数面板'!$G$33+'00参数面板'!$D$34*'00参数面板'!$G$34+'00参数面板'!$D$35*'00参数面板'!$G$35+'00参数面板'!$D$36*'00参数面板'!$G$36) | D33: ='00参数面板'!$A$44 | E33: ='00参数面板'!$D$44 | F33: ='00参数面板'!$D$44/'00参数面板'!$C$25 | G33: =500000*(('00参数面板'!$G$34*'00参数面板'!$D$34)/('00参数面板'!$D$33*'00参数面板'!$G$33+'00参数面板'!$D$34*'00参数面板'!$G$34+'00参数面板'!$D$35*'00参数面板'!$G$35+'00参数面板'!$D$36*'00参数面板'!$G$36))/'00参数面板'!$D$34 | H33: =(500000*(('00参数面板'!$G$34*'00参数面板'!$D$34)/('00参数面板'!$D$33*'00参数面板'!$G$33+'00参数面板'!$D$34*'00参数面板'!$G$34+'00参数面板'!$D$35*'00参数面板'!$G$35+'00参数面板'!$D$36*'00参数面板'!$G$36))/'00参数面板'!$D$34)/'00参数面板'!$D$44 | I33: =(500000*(('00参数面板'!$G$34*'00参数面板'!$D$34)/('00参数面板'!$D$33*'00参数面板'!$G$33+'00参数面板'!$D$34*'00参数面板'!$G$34+'00参数面板'!$D$35*'00参数面板'!$G$35+'00参数面板'!$D$36*'00参数面板'!$G$36))/'00参数面板'!$D$34) | J33: =2500000*0.05*0.4*(('00参数面板'!$G$34*'00参数面板'!$D$34)/('00参数面板'!$D$33*'00参数面板'!$G$33+'00参数面板'!$D$34*'00参数面板'!$G$34+'00参数面板'!$D$35*'00参数面板'!$G$35+'00参数面板'!$D$36*'00参数面板'!$G$36))/'00参数面板'!$D$34 | K33: =(500000*(('00参数面板'!$G$34*'00参数面板'!$D$34)/('00参数面板'!$D$33*'00参数面板'!$G$33+'00参数面板'!$D$34*'00参数面板'!$G$34+'00参数面板'!$D$35*'00参数面板'!$G$35+'00参数面板'!$D$36*'00参数面板'!$G$36))/'00参数面板'!$D$34)/12+2500000*0.05*0.4*(('00参数面板'!$G$34*'00参数面板'!$D$34)/('00参数面板'!$D$33*'00参数面板'!$G$33+'00参数面板'!$D$34*'00参数面板'!$G$34+'00参数面板'!$D$35*'00参数面板'!$G$35+'00参数面板'!$D$36*'00参数面板'!$G$36))/'00参数面板'!$D$34
A34: ='00参数面板'!$A$34 | B34: ='00参数面板'!$G$34 | C34: =('00参数面板'!$G$34*'00参数面板'!$D$34)/('00参数面板'!$D$33*'00参数面板'!$G$33+'00参数面板'!$D$34*'00参数面板'!$G$34+'00参数面板'!$D$35*'00参数面板'!$G$35+'00参数面板'!$D$36*'00参数面板'!$G$36) | D34: ='00参数面板'!$A$45 | E34: ='00参数面板'!$D$45 | F34: ='00参数面板'!$D$45/'00参数面板'!$C$25 | G34: =500000*(('00参数面板'!$G$34*'00参数面板'!$D$34)/('00参数面板'!$D$33*'00参数面板'!$G$33+'00参数面板'!$D$34*'00参数面板'!$G$34+'00参数面板'!$D$35*'00参数面板'!$G$35+'00参数面板'!$D$36*'00参数面板'!$G$36))/'00参数面板'!$D$34 | H34: =(500000*(('00参数面板'!$G$34*'00参数面板'!$D$34)/('00参数面板'!$D$33*'00参数面板'!$G$33+'00参数面板'!$D$34*'00参数面板'!$G$34+'00参数面板'!$D$35*'00参数面板'!$G$35+'00参数面板'!$D$36*'00参数面板'!$G$36))/'00参数面板'!$D$34)/'00参数面板'!$D$45 | I34: =(500000*(('00参数面板'!$G$34*'00参数面板'!$D$34)/('00参数面板'!$D$33*'00参数面板'!$G$33+'00参数面板'!$D$34*'00参数面板'!$G$34+'00参数面板'!$D$35*'00参数面板'!$G$35+'00参数面板'!$D$36*'00参数面板'!$G$36))/'00参数面板'!$D$34) | J34: =2500000*0.05*0.4*(('00参数面板'!$G$34*'00参数面板'!$D$34)/('00参数面板'!$D$33*'00参数面板'!$G$33+'00参数面板'!$D$34*'00参数面板'!$G$34+'00参数面板'!$D$35*'00参数面板'!$G$35+'00参数面板'!$D$36*'00参数面板'!$G$36))/'00参数面板'!$D$34 | K34: =(500000*(('00参数面板'!$G$34*'00参数面板'!$D$34)/('00参数面板'!$D$33*'00参数面板'!$G$33+'00参数面板'!$D$34*'00参数面板'!$G$34+'00参数面板'!$D$35*'00参数面板'!$G$35+'00参数面板'!$D$36*'00参数面板'!$G$36))/'00参数面板'!$D$34)/12+2500000*0.05*0.4*(('00参数面板'!$G$34*'00参数面板'!$D$34)/('00参数面板'!$D$33*'00参数面板'!$G$33+'00参数面板'!$D$34*'00参数面板'!$G$34+'00参数面板'!$D$35*'00参数面板'!$G$35+'00参数面板'!$D$36*'00参数面板'!$G$36))/'00参数面板'!$D$34
A35: ='00参数面板'!$A$34 | B35: ='00参数面板'!$G$34 | C35: =('00参数面板'!$G$34*'00参数面板'!$D$34)/('00参数面板'!$D$33*'00参数面板'!$G$33+'00参数面板'!$D$34*'00参数面板'!$G$34+'00参数面板'!$D$35*'00参数面板'!$G$35+'00参数面板'!$D$36*'00参数面板'!$G$36) | D35: ='00参数面板'!$A$46 | E35: ='00参数面板'!$D$46 | F35: ='00参数面板'!$D$46/'00参数面板'!$C$25 | G35: =500000*(('00参数面板'!$G$34*'00参数面板'!$D$34)/('00参数面板'!$D$33*'00参数面板'!$G$33+'00参数面板'!$D$34*'00参数面板'!$G$34+'00参数面板'!$D$35*'00参数面板'!$G$35+'00参数面板'!$D$36*'00参数面板'!$G$36))/'00参数面板'!$D$34 | H35: =(500000*(('00参数面板'!$G$34*'00参数面板'!$D$34)/('00参数面板'!$D$33*'00参数面板'!$G$33+'00参数面板'!$D$34*'00参数面板'!$G$34+'00参数面板'!$D$35*'00参数面板'!$G$35+'00参数面板'!$D$36*'00参数面板'!$G$36))/'00参数面板'!$D$34)/'00参数面板'!$D$46 | I35: =(500000*(('00参数面板'!$G$34*'00参数面板'!$D$34)/('00参数面板'!$D$33*'00参数面板'!$G$33+'00参数面板'!$D$34*'00参数面板'!$G$34+'00参数面板'!$D$35*'00参数面板'!$G$35+'00参数面板'!$D$36*'00参数面板'!$G$36))/'00参数面板'!$D$34) | J35: =2500000*0.05*0.4*(('00参数面板'!$G$34*'00参数面板'!$D$34)/('00参数面板'!$D$33*'00参数面板'!$G$33+'00参数面板'!$D$34*'00参数面板'!$G$34+'00参数面板'!$D$35*'00参数面板'!$G$35+'00参数面板'!$D$36*'00参数面板'!$G$36))/'00参数面板'!$D$34 | K35: =(500000*(('00参数面板'!$G$34*'00参数面板'!$D$34)/('00参数面板'!$D$33*'00参数面板'!$G$33+'00参数面板'!$D$34*'00参数面板'!$G$34+'00参数面板'!$D$35*'00参数面板'!$G$35+'00参数面板'!$D$36*'00参数面板'!$G$36))/'00参数面板'!$D$34)/12+2500000*0.05*0.4*(('00参数面板'!$G$34*'00参数面板'!$D$34)/('00参数面板'!$D$33*'00参数面板'!$G$33+'00参数面板'!$D$34*'00参数面板'!$G$34+'00参数面板'!$D$35*'00参数面板'!$G$35+'00参数面板'!$D$36*'00参数面板'!$G$36))/'00参数面板'!$D$34
A37: ='00参数面板'!$A$35 | B37: ='00参数面板'!$G$35 | C37: =('00参数面板'!$G$35*'00参数面板'!$D$35)/('00参数面板'!$D$33*'00参数面板'!$G$33+'00参数面板'!$D$34*'00参数面板'!$G$34+'00参数面板'!$D$35*'00参数面板'!$G$35+'00参数面板'!$D$36*'00参数面板'!$G$36) | D37: ='00参数面板'!$A$41 | E37: ='00参数面板'!$D$41 | F37: ='00参数面板'!$D$41/'00参数面板'!$C$25 | G37: =500000*(('00参数面板'!$G$35*'00参数面板'!$D$35)/('00参数面板'!$D$33*'00参数面板'!$G$33+'00参数面板'!$D$34*'00参数面板'!$G$34+'00参数面板'!$D$35*'00参数面板'!$G$35+'00参数面板'!$D$36*'00参数面板'!$G$36))/'00参数面板'!$D$35 | H37: =(500000*(('00参数面板'!$G$35*'00参数面板'!$D$35)/('00参数面板'!$D$33*'00参数面板'!$G$33+'00参数面板'!$D$34*'00参数面板'!$G$34+'00参数面板'!$D$35*'00参数面板'!$G$35+'00参数面板'!$D$36*'00参数面板'!$G$36))/'00参数面板'!$D$35)/'00参数面板'!$D$41 | I37: =(500000*(('00参数面板'!$G$35*'00参数面板'!$D$35)/('00参数面板'!$D$33*'00参数面板'!$G$33+'00参数面板'!$D$34*'00参数面板'!$G$34+'00参数面板'!$D$35*'00参数面板'!$G$35+'00参数面板'!$D$36*'00参数面板'!$G$36))/'00参数面板'!$D$35) | J37: =2500000*0.05*0.4*(('00参数面板'!$G$35*'00参数面板'!$D$35)/('00参数面板'!$D$33*'00参数面板'!$G$33+'00参数面板'!$D$34*'00参数面板'!$G$34+'00参数面板'!$D$35*'00参数面板'!$G$35+'00参数面板'!$D$36*'00参数面板'!$G$36))/'00参数面板'!$D$35 | K37: =(500000*(('00参数面板'!$G$35*'00参数面板'!$D$35)/('00参数面板'!$D$33*'00参数面板'!$G$33+'00参数面板'!$D$34*'00参数面板'!$G$34+'00参数面板'!$D$35*'00参数面板'!$G$35+'00参数面板'!$D$36*'00参数面板'!$G$36))/'00参数面板'!$D$35)/12+2500000*0.05*0.4*(('00参数面板'!$G$35*'00参数面板'!$D$35)/('00参数面板'!$D$33*'00参数面板'!$G$33+'00参数面板'!$D$34*'00参数面板'!$G$34+'00参数面板'!$D$35*'00参数面板'!$G$35+'00参数面板'!$D$36*'00参数面板'!$G$36))/'00参数面板'!$D$35
A38: ='00参数面板'!$A$35 | B38: ='00参数面板'!$G$35 | C38: =('00参数面板'!$G$35*'00参数面板'!$D$35)/('00参数面板'!$D$33*'00参数面板'!$G$33+'00参数面板'!$D$34*'00参数面板'!$G$34+'00参数面板'!$D$35*'00参数面板'!$G$35+'00参数面板'!$D$36*'00参数面板'!$G$36) | D38: ='00参数面板'!$A$42 | E38: ='00参数面板'!$D$42 | F38: ='00参数面板'!$D$42/'00参数面板'!$C$25 | G38: =500000*(('00参数面板'!$G$35*'00参数面板'!$D$35)/('00参数面板'!$D$33*'00参数面板'!$G$33+'00参数面板'!$D$34*'00参数面板'!$G$34+'00参数面板'!$D$35*'00参数面板'!$G$35+'00参数面板'!$D$36*'00参数面板'!$G$36))/'00参数面板'!$D$35 | H38: =(500000*(('00参数面板'!$G$35*'00参数面板'!$D$35)/('00参数面板'!$D$33*'00参数面板'!$G$33+'00参数面板'!$D$34*'00参数面板'!$G$34+'00参数面板'!$D$35*'00参数面板'!$G$35+'00参数面板'!$D$36*'00参数面板'!$G$36))/'00参数面板'!$D$35)/'00参数面板'!$D$42 | I38: =(500000*(('00参数面板'!$G$35*'00参数面板'!$D$35)/('00参数面板'!$D$33*'00参数面板'!$G$33+'00参数面板'!$D$34*'00参数面板'!$G$34+'00参数面板'!$D$35*'00参数面板'!$G$35+'00参数面板'!$D$36*'00参数面板'!$G$36))/'00参数面板'!$D$35) | J38: =2500000*0.05*0.4*(('00参数面板'!$G$35*'00参数面板'!$D$35)/('00参数面板'!$D$33*'00参数面板'!$G$33+'00参数面板'!$D$34*'00参数面板'!$G$34+'00参数面板'!$D$35*'00参数面板'!$G$35+'00参数面板'!$D$36*'00参数面板'!$G$36))/'00参数面板'!$D$35 | K38: =(500000*(('00参数面板'!$G$35*'00参数面板'!$D$35)/('00参数面板'!$D$33*'00参数面板'!$G$33+'00参数面板'!$D$34*'00参数面板'!$G$34+'00参数面板'!$D$35*'00参数面板'!$G$35+'00参数面板'!$D$36*'00参数面板'!$G$36))/'00参数面板'!$D$35)/12+2500000*0.05*0.4*(('00参数面板'!$G$35*'00参数面板'!$D$35)/('00参数面板'!$D$33*'00参数面板'!$G$33+'00参数面板'!$D$34*'00参数面板'!$G$34+'00参数面板'!$D$35*'00参数面板'!$G$35+'00参数面板'!$D$36*'00参数面板'!$G$36))/'00参数面板'!$D$35
A39: ='00参数面板'!$A$35 | B39: ='00参数面板'!$G$35 | C39: =('00参数面板'!$G$35*'00参数面板'!$D$35)/('00参数面板'!$D$33*'00参数面板'!$G$33+'00参数面板'!$D$34*'00参数面板'!$G$34+'00参数面板'!$D$35*'00参数面板'!$G$35+'00参数面板'!$D$36*'00参数面板'!$G$36) | D39: ='00参数面板'!$A$43 | E39: ='00参数面板'!$D$43 | F39: ='00参数面板'!$D$43/'00参数面板'!$C$25 | G39: =500000*(('00参数面板'!$G$35*'00参数面板'!$D$35)/('00参数面板'!$D$33*'00参数面板'!$G$33+'00参数面板'!$D$34*'00参数面板'!$G$34+'00参数面板'!$D$35*'00参数面板'!$G$35+'00参数面板'!$D$36*'00参数面板'!$G$36))/'00参数面板'!$D$35 | H39: =(500000*(('00参数面板'!$G$35*'00参数面板'!$D$35)/('00参数面板'!$D$33*'00参数面板'!$G$33+'00参数面板'!$D$34*'00参数面板'!$G$34+'00参数面板'!$D$35*'00参数面板'!$G$35+'00参数面板'!$D$36*'00参数面板'!$G$36))/'00参数面板'!$D$35)/'00参数面板'!$D$43 | I39: =(500000*(('00参数面板'!$G$35*'00参数面板'!$D$35)/('00参数面板'!$D$33*'00参数面板'!$G$33+'00参数面板'!$D$34*'00参数面板'!$G$34+'00参数面板'!$D$35*'00参数面板'!$G$35+'00参数面板'!$D$36*'00参数面板'!$G$36))/'00参数面板'!$D$35) | J39: =2500000*0.05*0.4*(('00参数面板'!$G$35*'00参数面板'!$D$35)/('00参数面板'!$D$33*'00参数面板'!$G$33+'00参数面板'!$D$34*'00参数面板'!$G$34+'00参数面板'!$D$35*'00参数面板'!$G$35+'00参数面板'!$D$36*'00参数面板'!$G$36))/'00参数面板'!$D$35 | K39: =(500000*(('00参数面板'!$G$35*'00参数面板'!$D$35)/('00参数面板'!$D$33*'00参数面板'!$G$33+'00参数面板'!$D$34*'00参数面板'!$G$34+'00参数面板'!$D$35*'00参数面板'!$G$35+'00参数面板'!$D$36*'00参数面板'!$G$36))/'00参数面板'!$D$35)/12+2500000*0.05*0.4*(('00参数面板'!$G$35*'00参数面板'!$D$35)/('00参数面板'!$D$33*'00参数面板'!$G$33+'00参数面板'!$D$34*'00参数面板'!$G$34+'00参数面板'!$D$35*'00参数面板'!$G$35+'00参数面板'!$D$36*'00参数面板'!$G$36))/'00参数面板'!$D$35
A40: ='00参数面板'!$A$35 | B40: ='00参数面板'!$G$35 | C40: =('00参数面板'!$G$35*'00参数面板'!$D$35)/('00参数面板'!$D$33*'00参数面板'!$G$33+'00参数面板'!$D$34*'00参数面板'!$G$34+'00参数面板'!$D$35*'00参数面板'!$G$35+'00参数面板'!$D$36*'00参数面板'!$G$36) | D40: ='00参数面板'!$A$44 | E40: ='00参数面板'!$D$44 | F40: ='00参数面板'!$D$44/'00参数面板'!$C$25 | G40: =500000*(('00参数面板'!$G$35*'00参数面板'!$D$35)/('00参数面板'!$D$33*'00参数面板'!$G$33+'00参数面板'!$D$34*'00参数面板'!$G$34+'00参数面板'!$D$35*'00参数面板'!$G$35+'00参数面板'!$D$36*'00参数面板'!$G$36))/'00参数面板'!$D$35 | H40: =(500000*(('00参数面板'!$G$35*'00参数面板'!$D$35)/('00参数面板'!$D$33*'00参数面板'!$G$33+'00参数面板'!$D$34*'00参数面板'!$G$34+'00参数面板'!$D$35*'00参数面板'!$G$35+'00参数面板'!$D$36*'00参数面板'!$G$36))/'00参数面板'!$D$35)/'00参数面板'!$D$44 | I40: =(500000*(('00参数面板'!$G$35*'00参数面板'!$D$35)/('00参数面板'!$D$33*'00参数面板'!$G$33+'00参数面板'!$D$34*'00参数面板'!$G$34+'00参数面板'!$D$35*'00参数面板'!$G$35+'00参数面板'!$D$36*'00参数面板'!$G$36))/'00参数面板'!$D$35) | J40: =2500000*0.05*0.4*(('00参数面板'!$G$35*'00参数面板'!$D$35)/('00参数面板'!$D$33*'00参数面板'!$G$33+'00参数面板'!$D$34*'00参数面板'!$G$34+'00参数面板'!$D$35*'00参数面板'!$G$35+'00参数面板'!$D$36*'00参数面板'!$G$36))/'00参数面板'!$D$35 | K40: =(500000*(('00参数面板'!$G$35*'00参数面板'!$D$35)/('00参数面板'!$D$33*'00参数面板'!$G$33+'00参数面板'!$D$34*'00参数面板'!$G$34+'00参数面板'!$D$35*'00参数面板'!$G$35+'00参数面板'!$D$36*'00参数面板'!$G$36))/'00参数面板'!$D$35)/12+2500000*0.05*0.4*(('00参数面板'!$G$35*'00参数面板'!$D$35)/('00参数面板'!$D$33*'00参数面板'!$G$33+'00参数面板'!$D$34*'00参数面板'!$G$34+'00参数面板'!$D$35*'00参数面板'!$G$35+'00参数面板'!$D$36*'00参数面板'!$G$36))/'00参数面板'!$D$35
A41: ='00参数面板'!$A$35 | B41: ='00参数面板'!$G$35 | C41: =('00参数面板'!$G$35*'00参数面板'!$D$35)/('00参数面板'!$D$33*'00参数面板'!$G$33+'00参数面板'!$D$34*'00参数面板'!$G$34+'00参数面板'!$D$35*'00参数面板'!$G$35+'00参数面板'!$D$36*'00参数面板'!$G$36) | D41: ='00参数面板'!$A$45 | E41: ='00参数面板'!$D$45 | F41: ='00参数面板'!$D$45/'00参数面板'!$C$25 | G41: =500000*(('00参数面板'!$G$35*'00参数面板'!$D$35)/('00参数面板'!$D$33*'00参数面板'!$G$33+'00参数面板'!$D$34*'00参数面板'!$G$34+'00参数面板'!$D$35*'00参数面板'!$G$35+'00参数面板'!$D$36*'00参数面板'!$G$36))/'00参数面板'!$D$35 | H41: =(500000*(('00参数面板'!$G$35*'00参数面板'!$D$35)/('00参数面板'!$D$33*'00参数面板'!$G$33+'00参数面板'!$D$34*'00参数面板'!$G$34+'00参数面板'!$D$35*'00参数面板'!$G$35+'00参数面板'!$D$36*'00参数面板'!$G$36))/'00参数面板'!$D$35)/'00参数面板'!$D$45 | I41: =(500000*(('00参数面板'!$G$35*'00参数面板'!$D$35)/('00参数面板'!$D$33*'00参数面板'!$G$33+'00参数面板'!$D$34*'00参数面板'!$G$34+'00参数面板'!$D$35*'00参数面板'!$G$35+'00参数面板'!$D$36*'00参数面板'!$G$36))/'00参数面板'!$D$35) | J41: =2500000*0.05*0.4*(('00参数面板'!$G$35*'00参数面板'!$D$35)/('00参数面板'!$D$33*'00参数面板'!$G$33+'00参数面板'!$D$34*'00参数面板'!$G$34+'00参数面板'!$D$35*'00参数面板'!$G$35+'00参数面板'!$D$36*'00参数面板'!$G$36))/'00参数面板'!$D$35 | K41: =(500000*(('00参数面板'!$G$35*'00参数面板'!$D$35)/('00参数面板'!$D$33*'00参数面板'!$G$33+'00参数面板'!$D$34*'00参数面板'!$G$34+'00参数面板'!$D$35*'00参数面板'!$G$35+'00参数面板'!$D$36*'00参数面板'!$G$36))/'00参数面板'!$D$35)/12+2500000*0.05*0.4*(('00参数面板'!$G$35*'00参数面板'!$D$35)/('00参数面板'!$D$33*'00参数面板'!$G$33+'00参数面板'!$D$34*'00参数面板'!$G$34+'00参数面板'!$D$35*'00参数面板'!$G$35+'00参数面板'!$D$36*'00参数面板'!$G$36))/'00参数面板'!$D$35
A42: ='00参数面板'!$A$35 | B42: ='00参数面板'!$G$35 | C42: =('00参数面板'!$G$35*'00参数面板'!$D$35)/('00参数面板'!$D$33*'00参数面板'!$G$33+'00参数面板'!$D$34*'00参数面板'!$G$34+'00参数面板'!$D$35*'00参数面板'!$G$35+'00参数面板'!$D$36*'00参数面板'!$G$36) | D42: ='00参数面板'!$A$46 | E42: ='00参数面板'!$D$46 | F42: ='00参数面板'!$D$46/'00参数面板'!$C$25 | G42: =500000*(('00参数面板'!$G$35*'00参数面板'!$D$35)/('00参数面板'!$D$33*'00参数面板'!$G$33+'00参数面板'!$D$34*'00参数面板'!$G$34+'00参数面板'!$D$35*'00参数面板'!$G$35+'00参数面板'!$D$36*'00参数面板'!$G$36))/'00参数面板'!$D$35 | H42: =(500000*(('00参数面板'!$G$35*'00参数面板'!$D$35)/('00参数面板'!$D$33*'00参数面板'!$G$33+'00参数面板'!$D$34*'00参数面板'!$G$34+'00参数面板'!$D$35*'00参数面板'!$G$35+'00参数面板'!$D$36*'00参数面板'!$G$36))/'00参数面板'!$D$35)/'00参数面板'!$D$46 | I42: =(500000*(('00参数面板'!$G$35*'00参数面板'!$D$35)/('00参数面板'!$D$33*'00参数面板'!$G$33+'00参数面板'!$D$34*'00参数面板'!$G$34+'00参数面板'!$D$35*'00参数面板'!$G$35+'00参数面板'!$D$36*'00参数面板'!$G$36))/'00参数面板'!$D$35) | J42: =2500000*0.05*0.4*(('00参数面板'!$G$35*'00参数面板'!$D$35)/('00参数面板'!$D$33*'00参数面板'!$G$33+'00参数面板'!$D$34*'00参数面板'!$G$34+'00参数面板'!$D$35*'00参数面板'!$G$35+'00参数面板'!$D$36*'00参数面板'!$G$36))/'00参数面板'!$D$35 | K42: =(500000*(('00参数面板'!$G$35*'00参数面板'!$D$35)/('00参数面板'!$D$33*'00参数面板'!$G$33+'00参数面板'!$D$34*'00参数面板'!$G$34+'00参数面板'!$D$35*'00参数面板'!$G$35+'00参数面板'!$D$36*'00参数面板'!$G$36))/'00参数面板'!$D$35)/12+2500000*0.05*0.4*(('00参数面板'!$G$35*'00参数面板'!$D$35)/('00参数面板'!$D$33*'00参数面板'!$G$33+'00参数面板'!$D$34*'00参数面板'!$G$34+'00参数面板'!$D$35*'00参数面板'!$G$35+'00参数面板'!$D$36*'00参数面板'!$G$36))/'00参数面板'!$D$35
A44: ='00参数面板'!$A$36 | B44: ='00参数面板'!$G$36 | C44: =('00参数面板'!$G$36*'00参数面板'!$D$36)/('00参数面板'!$D$33*'00参数面板'!$G$33+'00参数面板'!$D$34*'00参数面板'!$G$34+'00参数面板'!$D$35*'00参数面板'!$G$35+'00参数面板'!$D$36*'00参数面板'!$G$36) | D44: ='00参数面板'!$A$41 | E44: ='00参数面板'!$D$41 | F44: ='00参数面板'!$D$41/'00参数面板'!$C$25 | G44: =500000*(('00参数面板'!$G$36*'00参数面板'!$D$36)/('00参数面板'!$D$33*'00参数面板'!$G$33+'00参数面板'!$D$34*'00参数面板'!$G$34+'00参数面板'!$D$35*'00参数面板'!$G$35+'00参数面板'!$D$36*'00参数面板'!$G$36))/'00参数面板'!$D$36 | H44: =(500000*(('00参数面板'!$G$36*'00参数面板'!$D$36)/('00参数面板'!$D$33*'00参数面板'!$G$33+'00参数面板'!$D$34*'00参数面板'!$G$34+'00参数面板'!$D$35*'00参数面板'!$G$35+'00参数面板'!$D$36*'00参数面板'!$G$36))/'00参数面板'!$D$36)/'00参数面板'!$D$41 | I44: =(500000*(('00参数面板'!$G$36*'00参数面板'!$D$36)/('00参数面板'!$D$33*'00参数面板'!$G$33+'00参数面板'!$D$34*'00参数面板'!$G$34+'00参数面板'!$D$35*'00参数面板'!$G$35+'00参数面板'!$D$36*'00参数面板'!$G$36))/'00参数面板'!$D$36) | J44: =2500000*0.05*0.4*(('00参数面板'!$G$36*'00参数面板'!$D$36)/('00参数面板'!$D$33*'00参数面板'!$G$33+'00参数面板'!$D$34*'00参数面板'!$G$34+'00参数面板'!$D$35*'00参数面板'!$G$35+'00参数面板'!$D$36*'00参数面板'!$G$36))/'00参数面板'!$D$36 | K44: =(500000*(('00参数面板'!$G$36*'00参数面板'!$D$36)/('00参数面板'!$D$33*'00参数面板'!$G$33+'00参数面板'!$D$34*'00参数面板'!$G$34+'00参数面板'!$D$35*'00参数面板'!$G$35+'00参数面板'!$D$36*'00参数面板'!$G$36))/'00参数面板'!$D$36)/12+2500000*0.05*0.4*(('00参数面板'!$G$36*'00参数面板'!$D$36)/('00参数面板'!$D$33*'00参数面板'!$G$33+'00参数面板'!$D$34*'00参数面板'!$G$34+'00参数面板'!$D$35*'00参数面板'!$G$35+'00参数面板'!$D$36*'00参数面板'!$G$36))/'00参数面板'!$D$36
A45: ='00参数面板'!$A$36 | B45: ='00参数面板'!$G$36 | C45: =('00参数面板'!$G$36*'00参数面板'!$D$36)/('00参数面板'!$D$33*'00参数面板'!$G$33+'00参数面板'!$D$34*'00参数面板'!$G$34+'00参数面板'!$D$35*'00参数面板'!$G$35+'00参数面板'!$D$36*'00参数面板'!$G$36) | D45: ='00参数面板'!$A$42 | E45: ='00参数面板'!$D$42 | F45: ='00参数面板'!$D$42/'00参数面板'!$C$25 | G45: =500000*(('00参数面板'!$G$36*'00参数面板'!$D$36)/('00参数面板'!$D$33*'00参数面板'!$G$33+'00参数面板'!$D$34*'00参数面板'!$G$34+'00参数面板'!$D$35*'00参数面板'!$G$35+'00参数面板'!$D$36*'00参数面板'!$G$36))/'00参数面板'!$D$36 | H45: =(500000*(('00参数面板'!$G$36*'00参数面板'!$D$36)/('00参数面板'!$D$33*'00参数面板'!$G$33+'00参数面板'!$D$34*'00参数面板'!$G$34+'00参数面板'!$D$35*'00参数面板'!$G$35+'00参数面板'!$D$36*'00参数面板'!$G$36))/'00参数面板'!$D$36)/'00参数面板'!$D$42 | I45: =(500000*(('00参数面板'!$G$36*'00参数面板'!$D$36)/('00参数面板'!$D$33*'00参数面板'!$G$33+'00参数面板'!$D$34*'00参数面板'!$G$34+'00参数面板'!$D$35*'00参数面板'!$G$35+'00参数面板'!$D$36*'00参数面板'!$G$36))/'00参数面板'!$D$36) | J45: =2500000*0.05*0.4*(('00参数面板'!$G$36*'00参数面板'!$D$36)/('00参数面板'!$D$33*'00参数面板'!$G$33+'00参数面板'!$D$34*'00参数面板'!$G$34+'00参数面板'!$D$35*'00参数面板'!$G$35+'00参数面板'!$D$36*'00参数面板'!$G$36))/'00参数面板'!$D$36 | K45: =(500000*(('00参数面板'!$G$36*'00参数面板'!$D$36)/('00参数面板'!$D$33*'00参数面板'!$G$33+'00参数面板'!$D$34*'00参数面板'!$G$34+'00参数面板'!$D$35*'00参数面板'!$G$35+'00参数面板'!$D$36*'00参数面板'!$G$36))/'00参数面板'!$D$36)/12+2500000*0.05*0.4*(('00参数面板'!$G$36*'00参数面板'!$D$36)/('00参数面板'!$D$33*'00参数面板'!$G$33+'00参数面板'!$D$34*'00参数面板'!$G$34+'00参数面板'!$D$35*'00参数面板'!$G$35+'00参数面板'!$D$36*'00参数面板'!$G$36))/'00参数面板'!$D$36
A46: ='00参数面板'!$A$36 | B46: ='00参数面板'!$G$36 | C46: =('00参数面板'!$G$36*'00参数面板'!$D$36)/('00参数面板'!$D$33*'00参数面板'!$G$33+'00参数面板'!$D$34*'00参数面板'!$G$34+'00参数面板'!$D$35*'00参数面板'!$G$35+'00参数面板'!$D$36*'00参数面板'!$G$36) | D46: ='00参数面板'!$A$43 | E46: ='00参数面板'!$D$43 | F46: ='00参数面板'!$D$43/'00参数面板'!$C$25 | G46: =500000*(('00参数面板'!$G$36*'00参数面板'!$D$36)/('00参数面板'!$D$33*'00参数面板'!$G$33+'00参数面板'!$D$34*'00参数面板'!$G$34+'00参数面板'!$D$35*'00参数面板'!$G$35+'00参数面板'!$D$36*'00参数面板'!$G$36))/'00参数面板'!$D$36 | H46: =(500000*(('00参数面板'!$G$36*'00参数面板'!$D$36)/('00参数面板'!$D$33*'00参数面板'!$G$33+'00参数面板'!$D$34*'00参数面板'!$G$34+'00参数面板'!$D$35*'00参数面板'!$G$35+'00参数面板'!$D$36*'00参数面板'!$G$36))/'00参数面板'!$D$36)/'00参数面板'!$D$43 | I46: =(500000*(('00参数面板'!$G$36*'00参数面板'!$D$36)/('00参数面板'!$D$33*'00参数面板'!$G$33+'00参数面板'!$D$34*'00参数面板'!$G$34+'00参数面板'!$D$35*'00参数面板'!$G$35+'00参数面板'!$D$36*'00参数面板'!$G$36))/'00参数面板'!$D$36) | J46: =2500000*0.05*0.4*(('00参数面板'!$G$36*'00参数面板'!$D$36)/('00参数面板'!$D$33*'00参数面板'!$G$33+'00参数面板'!$D$34*'00参数面板'!$G$34+'00参数面板'!$D$35*'00参数面板'!$G$35+'00参数面板'!$D$36*'00参数面板'!$G$36))/'00参数面板'!$D$36 | K46: =(500000*(('00参数面板'!$G$36*'00参数面板'!$D$36)/('00参数面板'!$D$33*'00参数面板'!$G$33+'00参数面板'!$D$34*'00参数面板'!$G$34+'00参数面板'!$D$35*'00参数面板'!$G$35+'00参数面板'!$D$36*'00参数面板'!$G$36))/'00参数面板'!$D$36)/12+2500000*0.05*0.4*(('00参数面板'!$G$36*'00参数面板'!$D$36)/('00参数面板'!$D$33*'00参数面板'!$G$33+'00参数面板'!$D$34*'00参数面板'!$G$34+'00参数面板'!$D$35*'00参数面板'!$G$35+'00参数面板'!$D$36*'00参数面板'!$G$36))/'00参数面板'!$D$36
A47: ='00参数面板'!$A$36 | B47: ='00参数面板'!$G$36 | C47: =('00参数面板'!$G$36*'00参数面板'!$D$36)/('00参数面板'!$D$33*'00参数面板'!$G$33+'00参数面板'!$D$34*'00参数面板'!$G$34+'00参数面板'!$D$35*'00参数面板'!$G$35+'00参数面板'!$D$36*'00参数面板'!$G$36) | D47: ='00参数面板'!$A$44 | E47: ='00参数面板'!$D$44 | F47: ='00参数面板'!$D$44/'00参数面板'!$C$25 | G47: =500000*(('00参数面板'!$G$36*'00参数面板'!$D$36)/('00参数面板'!$D$33*'00参数面板'!$G$33+'00参数面板'!$D$34*'00参数面板'!$G$34+'00参数面板'!$D$35*'00参数面板'!$G$35+'00参数面板'!$D$36*'00参数面板'!$G$36))/'00参数面板'!$D$36 | H47: =(500000*(('00参数面板'!$G$36*'00参数面板'!$D$36)/('00参数面板'!$D$33*'00参数面板'!$G$33+'00参数面板'!$D$34*'00参数面板'!$G$34+'00参数面板'!$D$35*'00参数面板'!$G$35+'00参数面板'!$D$36*'00参数面板'!$G$36))/'00参数面板'!$D$36)/'00参数面板'!$D$44 | I47: =(500000*(('00参数面板'!$G$36*'00参数面板'!$D$36)/('00参数面板'!$D$33*'00参数面板'!$G$33+'00参数面板'!$D$34*'00参数面板'!$G$34+'00参数面板'!$D$35*'00参数面板'!$G$35+'00参数面板'!$D$36*'00参数面板'!$G$36))/'00参数面板'!$D$36) | J47: =2500000*0.05*0.4*(('00参数面板'!$G$36*'00参数面板'!$D$36)/('00参数面板'!$D$33*'00参数面板'!$G$33+'00参数面板'!$D$34*'00参数面板'!$G$34+'00参数面板'!$D$35*'00参数面板'!$G$35+'00参数面板'!$D$36*'00参数面板'!$G$36))/'00参数面板'!$D$36 | K47: =(500000*(('00参数面板'!$G$36*'00参数面板'!$D$36)/('00参数面板'!$D$33*'00参数面板'!$G$33+'00参数面板'!$D$34*'00参数面板'!$G$34+'00参数面板'!$D$35*'00参数面板'!$G$35+'00参数面板'!$D$36*'00参数面板'!$G$36))/'00参数面板'!$D$36)/12+2500000*0.05*0.4*(('00参数面板'!$G$36*'00参数面板'!$D$36)/('00参数面板'!$D$33*'00参数面板'!$G$33+'00参数面板'!$D$34*'00参数面板'!$G$34+'00参数面板'!$D$35*'00参数面板'!$G$35+'00参数面板'!$D$36*'00参数面板'!$G$36))/'00参数面板'!$D$36
A48: ='00参数面板'!$A$36 | B48: ='00参数面板'!$G$36 | C48: =('00参数面板'!$G$36*'00参数面板'!$D$36)/('00参数面板'!$D$33*'00参数面板'!$G$33+'00参数面板'!$D$34*'00参数面板'!$G$34+'00参数面板'!$D$35*'00参数面板'!$G$35+'00参数面板'!$D$36*'00参数面板'!$G$36) | D48: ='00参数面板'!$A$45 | E48: ='00参数面板'!$D$45 | F48: ='00参数面板'!$D$45/'00参数面板'!$C$25 | G48: =500000*(('00参数面板'!$G$36*'00参数面板'!$D$36)/('00参数面板'!$D$33*'00参数面板'!$G$33+'00参数面板'!$D$34*'00参数面板'!$G$34+'00参数面板'!$D$35*'00参数面板'!$G$35+'00参数面板'!$D$36*'00参数面板'!$G$36))/'00参数面板'!$D$36 | H48: =(500000*(('00参数面板'!$G$36*'00参数面板'!$D$36)/('00参数面板'!$D$33*'00参数面板'!$G$33+'00参数面板'!$D$34*'00参数面板'!$G$34+'00参数面板'!$D$35*'00参数面板'!$G$35+'00参数面板'!$D$36*'00参数面板'!$G$36))/'00参数面板'!$D$36)/'00参数面板'!$D$45 | I48: =(500000*(('00参数面板'!$G$36*'00参数面板'!$D$36)/('00参数面板'!$D$33*'00参数面板'!$G$33+'00参数面板'!$D$34*'00参数面板'!$G$34+'00参数面板'!$D$35*'00参数面板'!$G$35+'00参数面板'!$D$36*'00参数面板'!$G$36))/'00参数面板'!$D$36) | J48: =2500000*0.05*0.4*(('00参数面板'!$G$36*'00参数面板'!$D$36)/('00参数面板'!$D$33*'00参数面板'!$G$33+'00参数面板'!$D$34*'00参数面板'!$G$34+'00参数面板'!$D$35*'00参数面板'!$G$35+'00参数面板'!$D$36*'00参数面板'!$G$36))/'00参数面板'!$D$36 | K48: =(500000*(('00参数面板'!$G$36*'00参数面板'!$D$36)/('00参数面板'!$D$33*'00参数面板'!$G$33+'00参数面板'!$D$34*'00参数面板'!$G$34+'00参数面板'!$D$35*'00参数面板'!$G$35+'00参数面板'!$D$36*'00参数面板'!$G$36))/'00参数面板'!$D$36)/12+2500000*0.05*0.4*(('00参数面板'!$G$36*'00参数面板'!$D$36)/('00参数面板'!$D$33*'00参数面板'!$G$33+'00参数面板'!$D$34*'00参数面板'!$G$34+'00参数面板'!$D$35*'00参数面板'!$G$35+'00参数面板'!$D$36*'00参数面板'!$G$36))/'00参数面板'!$D$36
A49: ='00参数面板'!$A$36 | B49: ='00参数面板'!$G$36 | C49: =('00参数面板'!$G$36*'00参数面板'!$D$36)/('00参数面板'!$D$33*'00参数面板'!$G$33+'00参数面板'!$D$34*'00参数面板'!$G$34+'00参数面板'!$D$35*'00参数面板'!$G$35+'00参数面板'!$D$36*'00参数面板'!$G$36) | D49: ='00参数面板'!$A$46 | E49: ='00参数面板'!$D$46 | F49: ='00参数面板'!$D$46/'00参数面板'!$C$25 | G49: =500000*(('00参数面板'!$G$36*'00参数面板'!$D$36)/('00参数面板'!$D$33*'00参数面板'!$G$33+'00参数面板'!$D$34*'00参数面板'!$G$34+'00参数面板'!$D$35*'00参数面板'!$G$35+'00参数面板'!$D$36*'00参数面板'!$G$36))/'00参数面板'!$D$36 | H49: =(500000*(('00参数面板'!$G$36*'00参数面板'!$D$36)/('00参数面板'!$D$33*'00参数面板'!$G$33+'00参数面板'!$D$34*'00参数面板'!$G$34+'00参数面板'!$D$35*'00参数面板'!$G$35+'00参数面板'!$D$36*'00参数面板'!$G$36))/'00参数面板'!$D$36)/'00参数面板'!$D$46 | I49: =(500000*(('00参数面板'!$G$36*'00参数面板'!$D$36)/('00参数面板'!$D$33*'00参数面板'!$G$33+'00参数面板'!$D$34*'00参数面板'!$G$34+'00参数面板'!$D$35*'00参数面板'!$G$35+'00参数面板'!$D$36*'00参数面板'!$G$36))/'00参数面板'!$D$36) | J49: =2500000*0.05*0.4*(('00参数面板'!$G$36*'00参数面板'!$D$36)/('00参数面板'!$D$33*'00参数面板'!$G$33+'00参数面板'!$D$34*'00参数面板'!$G$34+'00参数面板'!$D$35*'00参数面板'!$G$35+'00参数面板'!$D$36*'00参数面板'!$G$36))/'00参数面板'!$D$36 | K49: =(500000*(('00参数面板'!$G$36*'00参数面板'!$D$36)/('00参数面板'!$D$33*'00参数面板'!$G$33+'00参数面板'!$D$34*'00参数面板'!$G$34+'00参数面板'!$D$35*'00参数面板'!$G$35+'00参数面板'!$D$36*'00参数面板'!$G$36))/'00参数面板'!$D$36)/12+2500000*0.05*0.4*(('00参数面板'!$G$36*'00参数面板'!$D$36)/('00参数面板'!$D$33*'00参数面板'!$G$33+'00参数面板'!$D$34*'00参数面板'!$G$34+'00参数面板'!$D$35*'00参数面板'!$G$35+'00参数面板'!$D$36*'00参数面板'!$G$36))/'00参数面板'!$D$36

Sheet 03节点收益全景矩阵
A1: 节点收益全景矩阵（母子双币 × 6价格阶段）— 全公式联动参数面板
A2: 🔒 固定 | E2: 📝 可变 | I2: 📊 计算结果 | N2: 修改参数面板 → 全表自动联动
A4: ▌ 综合收益矩阵：4节点 × 6价格阶段 × 18列指标（全部Excel公式联动）
A5: 节点 | B5: 投资额(U) | C5: 私募价($) | D5: 持有母TOKEN(枚) | E5: 价格阶段 | F5: 母TOKEN价($) | G5: 子TOKEN价($) | H5: 持仓市值(U) | I5: 市值/成本× | J5: 日USDT(U) | K5: 30天USDT(U) | L5: 空投价值(U) | M5: 月打新收益(U) | N5: 月子币税分红(U) | O5: 月综合收益(U) | P5: 月收益率(%投资) | Q5: 总资产(U) | R5: 总资产/成本×
A6: ='00参数面板'!$A$33 | B6: ='00参数面板'!$C$33 | C6: ='00参数面板'!$E$33 | D6: ='00参数面板'!$C$33/'00参数面板'!$E$33 | E6: ='00参数面板'!$A$41 | F6: ='00参数面板'!$C$41 | G6: ='00参数面板'!$D$41 | H6: =('00参数面板'!$C$33/'00参数面板'!$E$33)*'00参数面板'!$C$41 | I6: =('00参数面板'!$C$33/'00参数面板'!$E$33)*'00参数面板'!$C$41/'00参数面板'!$C$33 | J6: ='00参数面板'!$F$33 | K6: ='00参数面板'!$F$33*30 | L6: ='00参数面板'!$H$33*'00参数面板'!$C$41 | M6: =500000*(('00参数面板'!$G$33*'00参数面板'!$D$33)/('00参数面板'!$D$33*'00参数面板'!$G$33+'00参数面板'!$D$34*'00参数面板'!$G$34+'00参数面板'!$D$35*'00参数面板'!$G$35+'00参数面板'!$D$36*'00参数面板'!$G$36))/'00参数面板'!$D$33/12 | N6: =2500000*0.05*0.4*(('00参数面板'!$G$33*'00参数面板'!$D$33)/('00参数面板'!$D$33*'00参数面板'!$G$33+'00参数面板'!$D$34*'00参数面板'!$G$34+'00参数面板'!$D$35*'00参数面板'!$G$35+'00参数面板'!$D$36*'00参数面板'!$G$36))/'00参数面板'!$D$33 | O6: ='00参数面板'!$F$33*30/30*30+2500000*0.05*0.4*(('00参数面板'!$G$33*'00参数面板'!$D$33)/('00参数面板'!$D$33*'00参数面板'!$G$33+'00参数面板'!$D$34*'00参数面板'!$G$34+'00参数面板'!$D$35*'00参数面板'!$G$35+'00参数面板'!$D$36*'00参数面板'!$G$36))/'00参数面板'!$D$33+500000*(('00参数面板'!$G$33*'00参数面板'!$D$33)/('00参数面板'!$D$33*'00参数面板'!$G$33+'00参数面板'!$D$34*'00参数面板'!$G$34+'00参数面板'!$D$35*'00参数面板'!$G$35+'00参数面板'!$D$36*'00参数面板'!$G$36))/'00参数面板'!$D$33/12 | P6: =('00参数面板'!$F$33*30/30*30+2500000*0.05*0.4*(('00参数面板'!$G$33*'00参数面板'!$D$33)/('00参数面板'!$D$33*'00参数面板'!$G$33+'00参数面板'!$D$34*'00参数面板'!$G$34+'00参数面板'!$D$35*'00参数面板'!$G$35+'00参数面板'!$D$36*'00参数面板'!$G$36))/'00参数面板'!$D$33+500000*(('00参数面板'!$G$33*'00参数面板'!$D$33)/('00参数面板'!$D$33*'00参数面板'!$G$33+'00参数面板'!$D$34*'00参数面板'!$G$34+'00参数面板'!$D$35*'00参数面板'!$G$35+'00参数面板'!$D$36*'00参数面板'!$G$36))/'00参数面板'!$D$33/12)/'00参数面板'!$C$33 | Q6: =(('00参数面板'!$C$33/'00参数面板'!$E$33)*'00参数面板'!$C$41)+'00参数面板'!$F$33*30+'00参数面板'!$H$33*'00参数面板'!$C$41 | R6: =((('00参数面板'!$C$33/'00参数面板'!$E$33)*'00参数面板'!$C$41)+'00参数面板'!$F$33*30+'00参数面板'!$H$33*'00参数面板'!$C$41)/'00参数面板'!$C$33
A7: ='00参数面板'!$A$33 | B7: ='00参数面板'!$C$33 | C7: ='00参数面板'!$E$33 | D7: ='00参数面板'!$C$33/'00参数面板'!$E$33 | E7: ='00参数面板'!$A$42 | F7: ='00参数面板'!$C$42 | G7: ='00参数面板'!$D$42 | H7: =('00参数面板'!$C$33/'00参数面板'!$E$33)*'00参数面板'!$C$42 | I7: =('00参数面板'!$C$33/'00参数面板'!$E$33)*'00参数面板'!$C$42/'00参数面板'!$C$33 | J7: ='00参数面板'!$F$33 | K7: ='00参数面板'!$F$33*30 | L7: ='00参数面板'!$H$33*'00参数面板'!$C$42 | M7: =500000*(('00参数面板'!$G$33*'00参数面板'!$D$33)/('00参数面板'!$D$33*'00参数面板'!$G$33+'00参数面板'!$D$34*'00参数面板'!$G$34+'00参数面板'!$D$35*'00参数面板'!$G$35+'00参数面板'!$D$36*'00参数面板'!$G$36))/'00参数面板'!$D$33/12 | N7: =2500000*0.05*0.4*(('00参数面板'!$G$33*'00参数面板'!$D$33)/('00参数面板'!$D$33*'00参数面板'!$G$33+'00参数面板'!$D$34*'00参数面板'!$G$34+'00参数面板'!$D$35*'00参数面板'!$G$35+'00参数面板'!$D$36*'00参数面板'!$G$36))/'00参数面板'!$D$33 | O7: ='00参数面板'!$F$33*30/30*30+2500000*0.05*0.4*(('00参数面板'!$G$33*'00参数面板'!$D$33)/('00参数面板'!$D$33*'00参数面板'!$G$33+'00参数面板'!$D$34*'00参数面板'!$G$34+'00参数面板'!$D$35*'00参数面板'!$G$35+'00参数面板'!$D$36*'00参数面板'!$G$36))/'00参数面板'!$D$33+500000*(('00参数面板'!$G$33*'00参数面板'!$D$33)/('00参数面板'!$D$33*'00参数面板'!$G$33+'00参数面板'!$D$34*'00参数面板'!$G$34+'00参数面板'!$D$35*'00参数面板'!$G$35+'00参数面板'!$D$36*'00参数面板'!$G$36))/'00参数面板'!$D$33/12 | P7: =('00参数面板'!$F$33*30/30*30+2500000*0.05*0.4*(('00参数面板'!$G$33*'00参数面板'!$D$33)/('00参数面板'!$D$33*'00参数面板'!$G$33+'00参数面板'!$D$34*'00参数面板'!$G$34+'00参数面板'!$D$35*'00参数面板'!$G$35+'00参数面板'!$D$36*'00参数面板'!$G$36))/'00参数面板'!$D$33+500000*(('00参数面板'!$G$33*'00参数面板'!$D$33)/('00参数面板'!$D$33*'00参数面板'!$G$33+'00参数面板'!$D$34*'00参数面板'!$G$34+'00参数面板'!$D$35*'00参数面板'!$G$35+'00参数面板'!$D$36*'00参数面板'!$G$36))/'00参数面板'!$D$33/12)/'00参数面板'!$C$33 | Q7: =(('00参数面板'!$C$33/'00参数面板'!$E$33)*'00参数面板'!$C$42)+'00参数面板'!$F$33*30+'00参数面板'!$H$33*'00参数面板'!$C$42 | R7: =((('00参数面板'!$C$33/'00参数面板'!$E$33)*'00参数面板'!$C$42)+'00参数面板'!$F$33*30+'00参数面板'!$H$33*'00参数面板'!$C$42)/'00参数面板'!$C$33
A8: ='00参数面板'!$A$33 | B8: ='00参数面板'!$C$33 | C8: ='00参数面板'!$E$33 | D8: ='00参数面板'!$C$33/'00参数面板'!$E$33 | E8: ='00参数面板'!$A$43 | F8: ='00参数面板'!$C$43 | G8: ='00参数面板'!$D$43 | H8: =('00参数面板'!$C$33/'00参数面板'!$E$33)*'00参数面板'!$C$43 | I8: =('00参数面板'!$C$33/'00参数面板'!$E$33)*'00参数面板'!$C$43/'00参数面板'!$C$33 | J8: ='00参数面板'!$F$33 | K8: ='00参数面板'!$F$33*30 | L8: ='00参数面板'!$H$33*'00参数面板'!$C$43 | M8: =500000*(('00参数面板'!$G$33*'00参数面板'!$D$33)/('00参数面板'!$D$33*'00参数面板'!$G$33+'00参数面板'!$D$34*'00参数面板'!$G$34+'00参数面板'!$D$35*'00参数面板'!$G$35+'00参数面板'!$D$36*'00参数面板'!$G$36))/'00参数面板'!$D$33/12 | N8: =2500000*0.05*0.4*(('00参数面板'!$G$33*'00参数面板'!$D$33)/('00参数面板'!$D$33*'00参数面板'!$G$33+'00参数面板'!$D$34*'00参数面板'!$G$34+'00参数面板'!$D$35*'00参数面板'!$G$35+'00参数面板'!$D$36*'00参数面板'!$G$36))/'00参数面板'!$D$33 | O8: ='00参数面板'!$F$33*30/30*30+2500000*0.05*0.4*(('00参数面板'!$G$33*'00参数面板'!$D$33)/('00参数面板'!$D$33*'00参数面板'!$G$33+'00参数面板'!$D$34*'00参数面板'!$G$34+'00参数面板'!$D$35*'00参数面板'!$G$35+'00参数面板'!$D$36*'00参数面板'!$G$36))/'00参数面板'!$D$33+500000*(('00参数面板'!$G$33*'00参数面板'!$D$33)/('00参数面板'!$D$33*'00参数面板'!$G$33+'00参数面板'!$D$34*'00参数面板'!$G$34+'00参数面板'!$D$35*'00参数面板'!$G$35+'00参数面板'!$D$36*'00参数面板'!$G$36))/'00参数面板'!$D$33/12 | P8: =('00参数面板'!$F$33*30/30*30+2500000*0.05*0.4*(('00参数面板'!$G$33*'00参数面板'!$D$33)/('00参数面板'!$D$33*'00参数面板'!$G$33+'00参数面板'!$D$34*'00参数面板'!$G$34+'00参数面板'!$D$35*'00参数面板'!$G$35+'00参数面板'!$D$36*'00参数面板'!$G$36))/'00参数面板'!$D$33+500000*(('00参数面板'!$G$33*'00参数面板'!$D$33)/('00参数面板'!$D$33*'00参数面板'!$G$33+'00参数面板'!$D$34*'00参数面板'!$G$34+'00参数面板'!$D$35*'00参数面板'!$G$35+'00参数面板'!$D$36*'00参数面板'!$G$36))/'00参数面板'!$D$33/12)/'00参数面板'!$C$33 | Q8: =(('00参数面板'!$C$33/'00参数面板'!$E$33)*'00参数面板'!$C$43)+'00参数面板'!$F$33*30+'00参数面板'!$H$33*'00参数面板'!$C$43 | R8: =((('00参数面板'!$C$33/'00参数面板'!$E$33)*'00参数面板'!$C$43)+'00参数面板'!$F$33*30+'00参数面板'!$H$33*'00参数面板'!$C$43)/'00参数面板'!$C$33
A9: ='00参数面板'!$A$33 | B9: ='00参数面板'!$C$33 | C9: ='00参数面板'!$E$33 | D9: ='00参数面板'!$C$33/'00参数面板'!$E$33 | E9: ='00参数面板'!$A$44 | F9: ='00参数面板'!$C$44 | G9: ='00参数面板'!$D$44 | H9: =('00参数面板'!$C$33/'00参数面板'!$E$33)*'00参数面板'!$C$44 | I9: =('00参数面板'!$C$33/'00参数面板'!$E$33)*'00参数面板'!$C$44/'00参数面板'!$C$33 | J9: ='00参数面板'!$F$33 | K9: ='00参数面板'!$F$33*30 | L9: ='00参数面板'!$H$33*'00参数面板'!$C$44 | M9: =500000*(('00参数面板'!$G$33*'00参数面板'!$D$33)/('00参数面板'!$D$33*'00参数面板'!$G$33+'00参数面板'!$D$34*'00参数面板'!$G$34+'00参数面板'!$D$35*'00参数面板'!$G$35+'00参数面板'!$D$36*'00参数面板'!$G$36))/'00参数面板'!$D$33/12 | N9: =2500000*0.05*0.4*(('00参数面板'!$G$33*'00参数面板'!$D$33)/('00参数面板'!$D$33*'00参数面板'!$G$33+'00参数面板'!$D$34*'00参数面板'!$G$34+'00参数面板'!$D$35*'00参数面板'!$G$35+'00参数面板'!$D$36*'00参数面板'!$G$36))/'00参数面板'!$D$33 | O9: ='00参数面板'!$F$33*30/30*30+2500000*0.05*0.4*(('00参数面板'!$G$33*'00参数面板'!$D$33)/('00参数面板'!$D$33*'00参数面板'!$G$33+'00参数面板'!$D$34*'00参数面板'!$G$34+'00参数面板'!$D$35*'00参数面板'!$G$35+'00参数面板'!$D$36*'00参数面板'!$G$36))/'00参数面板'!$D$33+500000*(('00参数面板'!$G$33*'00参数面板'!$D$33)/('00参数面板'!$D$33*'00参数面板'!$G$33+'00参数面板'!$D$34*'00参数面板'!$G$34+'00参数面板'!$D$35*'00参数面板'!$G$35+'00参数面板'!$D$36*'00参数面板'!$G$36))/'00参数面板'!$D$33/12 | P9: =('00参数面板'!$F$33*30/30*30+2500000*0.05*0.4*(('00参数面板'!$G$33*'00参数面板'!$D$33)/('00参数面板'!$D$33*'00参数面板'!$G$33+'00参数面板'!$D$34*'00参数面板'!$G$34+'00参数面板'!$D$35*'00参数面板'!$G$35+'00参数面板'!$D$36*'00参数面板'!$G$36))/'00参数面板'!$D$33+500000*(('00参数面板'!$G$33*'00参数面板'!$D$33)/('00参数面板'!$D$33*'00参数面板'!$G$33+'00参数面板'!$D$34*'00参数面板'!$G$34+'00参数面板'!$D$35*'00参数面板'!$G$35+'00参数面板'!$D$36*'00参数面板'!$G$36))/'00参数面板'!$D$33/12)/'00参数面板'!$C$33 | Q9: =(('00参数面板'!$C$33/'00参数面板'!$E$33)*'00参数面板'!$C$44)+'00参数面板'!$F$33*30+'00参数面板'!$H$33*'00参数面板'!$C$44 | R9: =((('00参数面板'!$C$33/'00参数面板'!$E$33)*'00参数面板'!$C$44)+'00参数面板'!$F$33*30+'00参数面板'!$H$33*'00参数面板'!$C$44)/'00参数面板'!$C$33
A10: ='00参数面板'!$A$33 | B10: ='00参数面板'!$C$33 | C10: ='00参数面板'!$E$33 | D10: ='00参数面板'!$C$33/'00参数面板'!$E$33 | E10: ='00参数面板'!$A$45 | F10: ='00参数面板'!$C$45 | G10: ='00参数面板'!$D$45 | H10: =('00参数面板'!$C$33/'00参数面板'!$E$33)*'00参数面板'!$C$45 | I10: =('00参数面板'!$C$33/'00参数面板'!$E$33)*'00参数面板'!$C$45/'00参数面板'!$C$33 | J10: ='00参数面板'!$F$33 | K10: ='00参数面板'!$F$33*30 | L10: ='00参数面板'!$H$33*'00参数面板'!$C$45 | M10: =500000*(('00参数面板'!$G$33*'00参数面板'!$D$33)/('00参数面板'!$D$33*'00参数面板'!$G$33+'00参数面板'!$D$34*'00参数面板'!$G$34+'00参数面板'!$D$35*'00参数面板'!$G$35+'00参数面板'!$D$36*'00参数面板'!$G$36))/'00参数面板'!$D$33/12 | N10: =2500000*0.05*0.4*(('00参数面板'!$G$33*'00参数面板'!$D$33)/('00参数面板'!$D$33*'00参数面板'!$G$33+'00参数面板'!$D$34*'00参数面板'!$G$34+'00参数面板'!$D$35*'00参数面板'!$G$35+'00参数面板'!$D$36*'00参数面板'!$G$36))/'00参数面板'!$D$33 | O10: ='00参数面板'!$F$33*30/30*30+2500000*0.05*0.4*(('00参数面板'!$G$33*'00参数面板'!$D$33)/('00参数面板'!$D$33*'00参数面板'!$G$33+'00参数面板'!$D$34*'00参数面板'!$G$34+'00参数面板'!$D$35*'00参数面板'!$G$35+'00参数面板'!$D$36*'00参数面板'!$G$36))/'00参数面板'!$D$33+500000*(('00参数面板'!$G$33*'00参数面板'!$D$33)/('00参数面板'!$D$33*'00参数面板'!$G$33+'00参数面板'!$D$34*'00参数面板'!$G$34+'00参数面板'!$D$35*'00参数面板'!$G$35+'00参数面板'!$D$36*'00参数面板'!$G$36))/'00参数面板'!$D$33/12 | P10: =('00参数面板'!$F$33*30/30*30+2500000*0.05*0.4*(('00参数面板'!$G$33*'00参数面板'!$D$33)/('00参数面板'!$D$33*'00参数面板'!$G$33+'00参数面板'!$D$34*'00参数面板'!$G$34+'00参数面板'!$D$35*'00参数面板'!$G$35+'00参数面板'!$D$36*'00参数面板'!$G$36))/'00参数面板'!$D$33+500000*(('00参数面板'!$G$33*'00参数面板'!$D$33)/('00参数面板'!$D$33*'00参数面板'!$G$33+'00参数面板'!$D$34*'00参数面板'!$G$34+'00参数面板'!$D$35*'00参数面板'!$G$35+'00参数面板'!$D$36*'00参数面板'!$G$36))/'00参数面板'!$D$33/12)/'00参数面板'!$C$33 | Q10: =(('00参数面板'!$C$33/'00参数面板'!$E$33)*'00参数面板'!$C$45)+'00参数面板'!$F$33*30+'00参数面板'!$H$33*'00参数面板'!$C$45 | R10: =((('00参数面板'!$C$33/'00参数面板'!$E$33)*'00参数面板'!$C$45)+'00参数面板'!$F$33*30+'00参数面板'!$H$33*'00参数面板'!$C$45)/'00参数面板'!$C$33
A11: ='00参数面板'!$A$33 | B11: ='00参数面板'!$C$33 | C11: ='00参数面板'!$E$33 | D11: ='00参数面板'!$C$33/'00参数面板'!$E$33 | E11: ='00参数面板'!$A$46 | F11: ='00参数面板'!$C$46 | G11: ='00参数面板'!$D$46 | H11: =('00参数面板'!$C$33/'00参数面板'!$E$33)*'00参数面板'!$C$46 | I11: =('00参数面板'!$C$33/'00参数面板'!$E$33)*'00参数面板'!$C$46/'00参数面板'!$C$33 | J11: ='00参数面板'!$F$33 | K11: ='00参数面板'!$F$33*30 | L11: ='00参数面板'!$H$33*'00参数面板'!$C$46 | M11: =500000*(('00参数面板'!$G$33*'00参数面板'!$D$33)/('00参数面板'!$D$33*'00参数面板'!$G$33+'00参数面板'!$D$34*'00参数面板'!$G$34+'00参数面板'!$D$35*'00参数面板'!$G$35+'00参数面板'!$D$36*'00参数面板'!$G$36))/'00参数面板'!$D$33/12 | N11: =2500000*0.05*0.4*(('00参数面板'!$G$33*'00参数面板'!$D$33)/('00参数面板'!$D$33*'00参数面板'!$G$33+'00参数面板'!$D$34*'00参数面板'!$G$34+'00参数面板'!$D$35*'00参数面板'!$G$35+'00参数面板'!$D$36*'00参数面板'!$G$36))/'00参数面板'!$D$33 | O11: ='00参数面板'!$F$33*30/30*30+2500000*0.05*0.4*(('00参数面板'!$G$33*'00参数面板'!$D$33)/('00参数面板'!$D$33*'00参数面板'!$G$33+'00参数面板'!$D$34*'00参数面板'!$G$34+'00参数面板'!$D$35*'00参数面板'!$G$35+'00参数面板'!$D$36*'00参数面板'!$G$36))/'00参数面板'!$D$33+500000*(('00参数面板'!$G$33*'00参数面板'!$D$33)/('00参数面板'!$D$33*'00参数面板'!$G$33+'00参数面板'!$D$34*'00参数面板'!$G$34+'00参数面板'!$D$35*'00参数面板'!$G$35+'00参数面板'!$D$36*'00参数面板'!$G$36))/'00参数面板'!$D$33/12 | P11: =('00参数面板'!$F$33*30/30*30+2500000*0.05*0.4*(('00参数面板'!$G$33*'00参数面板'!$D$33)/('00参数面板'!$D$33*'00参数面板'!$G$33+'00参数面板'!$D$34*'00参数面板'!$G$34+'00参数面板'!$D$35*'00参数面板'!$G$35+'00参数面板'!$D$36*'00参数面板'!$G$36))/'00参数面板'!$D$33+500000*(('00参数面板'!$G$33*'00参数面板'!$D$33)/('00参数面板'!$D$33*'00参数面板'!$G$33+'00参数面板'!$D$34*'00参数面板'!$G$34+'00参数面板'!$D$35*'00参数面板'!$G$35+'00参数面板'!$D$36*'00参数面板'!$G$36))/'00参数面板'!$D$33/12)/'00参数面板'!$C$33 | Q11: =(('00参数面板'!$C$33/'00参数面板'!$E$33)*'00参数面板'!$C$46)+'00参数面板'!$F$33*30+'00参数面板'!$H$33*'00参数面板'!$C$46 | R11: =((('00参数面板'!$C$33/'00参数面板'!$E$33)*'00参数面板'!$C$46)+'00参数面板'!$F$33*30+'00参数面板'!$H$33*'00参数面板'!$C$46)/'00参数面板'!$C$33
A13: ='00参数面板'!$A$34 | B13: ='00参数面板'!$C$34 | C13: ='00参数面板'!$E$34 | D13: ='00参数面板'!$C$34/'00参数面板'!$E$34 | E13: ='00参数面板'!$A$41 | F13: ='00参数面板'!$C$41 | G13: ='00参数面板'!$D$41 | H13: =('00参数面板'!$C$34/'00参数面板'!$E$34)*'00参数面板'!$C$41 | I13: =('00参数面板'!$C$34/'00参数面板'!$E$34)*'00参数面板'!$C$41/'00参数面板'!$C$34 | J13: ='00参数面板'!$F$34 | K13: ='00参数面板'!$F$34*30 | L13: ='00参数面板'!$H$34*'00参数面板'!$C$41 | M13: =500000*(('00参数面板'!$G$34*'00参数面板'!$D$34)/('00参数面板'!$D$33*'00参数面板'!$G$33+'00参数面板'!$D$34*'00参数面板'!$G$34+'00参数面板'!$D$35*'00参数面板'!$G$35+'00参数面板'!$D$36*'00参数面板'!$G$36))/'00参数面板'!$D$34/12 | N13: =2500000*0.05*0.4*(('00参数面板'!$G$34*'00参数面板'!$D$34)/('00参数面板'!$D$33*'00参数面板'!$G$33+'00参数面板'!$D$34*'00参数面板'!$G$34+'00参数面板'!$D$35*'00参数面板'!$G$35+'00参数面板'!$D$36*'00参数面板'!$G$36))/'00参数面板'!$D$34 | O13: ='00参数面板'!$F$34*30/30*30+2500000*0.05*0.4*(('00参数面板'!$G$34*'00参数面板'!$D$34)/('00参数面板'!$D$33*'00参数面板'!$G$33+'00参数面板'!$D$34*'00参数面板'!$G$34+'00参数面板'!$D$35*'00参数面板'!$G$35+'00参数面板'!$D$36*'00参数面板'!$G$36))/'00参数面板'!$D$34+500000*(('00参数面板'!$G$34*'00参数面板'!$D$34)/('00参数面板'!$D$33*'00参数面板'!$G$33+'00参数面板'!$D$34*'00参数面板'!$G$34+'00参数面板'!$D$35*'00参数面板'!$G$35+'00参数面板'!$D$36*'00参数面板'!$G$36))/'00参数面板'!$D$34/12 | P13: =('00参数面板'!$F$34*30/30*30+2500000*0.05*0.4*(('00参数面板'!$G$34*'00参数面板'!$D$34)/('00参数面板'!$D$33*'00参数面板'!$G$33+'00参数面板'!$D$34*'00参数面板'!$G$34+'00参数面板'!$D$35*'00参数面板'!$G$35+'00参数面板'!$D$36*'00参数面板'!$G$36))/'00参数面板'!$D$34+500000*(('00参数面板'!$G$34*'00参数面板'!$D$34)/('00参数面板'!$D$33*'00参数面板'!$G$33+'00参数面板'!$D$34*'00参数面板'!$G$34+'00参数面板'!$D$35*'00参数面板'!$G$35+'00参数面板'!$D$36*'00参数面板'!$G$36))/'00参数面板'!$D$34/12)/'00参数面板'!$C$34 | Q13: =(('00参数面板'!$C$34/'00参数面板'!$E$34)*'00参数面板'!$C$41)+'00参数面板'!$F$34*30+'00参数面板'!$H$34*'00参数面板'!$C$41 | R13: =((('00参数面板'!$C$34/'00参数面板'!$E$34)*'00参数面板'!$C$41)+'00参数面板'!$F$34*30+'00参数面板'!$H$34*'00参数面板'!$C$41)/'00参数面板'!$C$34
A14: ='00参数面板'!$A$34 | B14: ='00参数面板'!$C$34 | C14: ='00参数面板'!$E$34 | D14: ='00参数面板'!$C$34/'00参数面板'!$E$34 | E14: ='00参数面板'!$A$42 | F14: ='00参数面板'!$C$42 | G14: ='00参数面板'!$D$42 | H14: =('00参数面板'!$C$34/'00参数面板'!$E$34)*'00参数面板'!$C$42 | I14: =('00参数面板'!$C$34/'00参数面板'!$E$34)*'00参数面板'!$C$42/'00参数面板'!$C$34 | J14: ='00参数面板'!$F$34 | K14: ='00参数面板'!$F$34*30 | L14: ='00参数面板'!$H$34*'00参数面板'!$C$42 | M14: =500000*(('00参数面板'!$G$34*'00参数面板'!$D$34)/('00参数面板'!$D$33*'00参数面板'!$G$33+'00参数面板'!$D$34*'00参数面板'!$G$34+'00参数面板'!$D$35*'00参数面板'!$G$35+'00参数面板'!$D$36*'00参数面板'!$G$36))/'00参数面板'!$D$34/12 | N14: =2500000*0.05*0.4*(('00参数面板'!$G$34*'00参数面板'!$D$34)/('00参数面板'!$D$33*'00参数面板'!$G$33+'00参数面板'!$D$34*'00参数面板'!$G$34+'00参数面板'!$D$35*'00参数面板'!$G$35+'00参数面板'!$D$36*'00参数面板'!$G$36))/'00参数面板'!$D$34 | O14: ='00参数面板'!$F$34*30/30*30+2500000*0.05*0.4*(('00参数面板'!$G$34*'00参数面板'!$D$34)/('00参数面板'!$D$33*'00参数面板'!$G$33+'00参数面板'!$D$34*'00参数面板'!$G$34+'00参数面板'!$D$35*'00参数面板'!$G$35+'00参数面板'!$D$36*'00参数面板'!$G$36))/'00参数面板'!$D$34+500000*(('00参数面板'!$G$34*'00参数面板'!$D$34)/('00参数面板'!$D$33*'00参数面板'!$G$33+'00参数面板'!$D$34*'00参数面板'!$G$34+'00参数面板'!$D$35*'00参数面板'!$G$35+'00参数面板'!$D$36*'00参数面板'!$G$36))/'00参数面板'!$D$34/12 | P14: =('00参数面板'!$F$34*30/30*30+2500000*0.05*0.4*(('00参数面板'!$G$34*'00参数面板'!$D$34)/('00参数面板'!$D$33*'00参数面板'!$G$33+'00参数面板'!$D$34*'00参数面板'!$G$34+'00参数面板'!$D$35*'00参数面板'!$G$35+'00参数面板'!$D$36*'00参数面板'!$G$36))/'00参数面板'!$D$34+500000*(('00参数面板'!$G$34*'00参数面板'!$D$34)/('00参数面板'!$D$33*'00参数面板'!$G$33+'00参数面板'!$D$34*'00参数面板'!$G$34+'00参数面板'!$D$35*'00参数面板'!$G$35+'00参数面板'!$D$36*'00参数面板'!$G$36))/'00参数面板'!$D$34/12)/'00参数面板'!$C$34 | Q14: =(('00参数面板'!$C$34/'00参数面板'!$E$34)*'00参数面板'!$C$42)+'00参数面板'!$F$34*30+'00参数面板'!$H$34*'00参数面板'!$C$42 | R14: =((('00参数面板'!$C$34/'00参数面板'!$E$34)*'00参数面板'!$C$42)+'00参数面板'!$F$34*30+'00参数面板'!$H$34*'00参数面板'!$C$42)/'00参数面板'!$C$34
A15: ='00参数面板'!$A$34 | B15: ='00参数面板'!$C$34 | C15: ='00参数面板'!$E$34 | D15: ='00参数面板'!$C$34/'00参数面板'!$E$34 | E15: ='00参数面板'!$A$43 | F15: ='00参数面板'!$C$43 | G15: ='00参数面板'!$D$43 | H15: =('00参数面板'!$C$34/'00参数面板'!$E$34)*'00参数面板'!$C$43 | I15: =('00参数面板'!$C$34/'00参数面板'!$E$34)*'00参数面板'!$C$43/'00参数面板'!$C$34 | J15: ='00参数面板'!$F$34 | K15: ='00参数面板'!$F$34*30 | L15: ='00参数面板'!$H$34*'00参数面板'!$C$43 | M15: =500000*(('00参数面板'!$G$34*'00参数面板'!$D$34)/('00参数面板'!$D$33*'00参数面板'!$G$33+'00参数面板'!$D$34*'00参数面板'!$G$34+'00参数面板'!$D$35*'00参数面板'!$G$35+'00参数面板'!$D$36*'00参数面板'!$G$36))/'00参数面板'!$D$34/12 | N15: =2500000*0.05*0.4*(('00参数面板'!$G$34*'00参数面板'!$D$34)/('00参数面板'!$D$33*'00参数面板'!$G$33+'00参数面板'!$D$34*'00参数面板'!$G$34+'00参数面板'!$D$35*'00参数面板'!$G$35+'00参数面板'!$D$36*'00参数面板'!$G$36))/'00参数面板'!$D$34 | O15: ='00参数面板'!$F$34*30/30*30+2500000*0.05*0.4*(('00参数面板'!$G$34*'00参数面板'!$D$34)/('00参数面板'!$D$33*'00参数面板'!$G$33+'00参数面板'!$D$34*'00参数面板'!$G$34+'00参数面板'!$D$35*'00参数面板'!$G$35+'00参数面板'!$D$36*'00参数面板'!$G$36))/'00参数面板'!$D$34+500000*(('00参数面板'!$G$34*'00参数面板'!$D$34)/('00参数面板'!$D$33*'00参数面板'!$G$33+'00参数面板'!$D$34*'00参数面板'!$G$34+'00参数面板'!$D$35*'00参数面板'!$G$35+'00参数面板'!$D$36*'00参数面板'!$G$36))/'00参数面板'!$D$34/12 | P15: =('00参数面板'!$F$34*30/30*30+2500000*0.05*0.4*(('00参数面板'!$G$34*'00参数面板'!$D$34)/('00参数面板'!$D$33*'00参数面板'!$G$33+'00参数面板'!$D$34*'00参数面板'!$G$34+'00参数面板'!$D$35*'00参数面板'!$G$35+'00参数面板'!$D$36*'00参数面板'!$G$36))/'00参数面板'!$D$34+500000*(('00参数面板'!$G$34*'00参数面板'!$D$34)/('00参数面板'!$D$33*'00参数面板'!$G$33+'00参数面板'!$D$34*'00参数面板'!$G$34+'00参数面板'!$D$35*'00参数面板'!$G$35+'00参数面板'!$D$36*'00参数面板'!$G$36))/'00参数面板'!$D$34/12)/'00参数面板'!$C$34 | Q15: =(('00参数面板'!$C$34/'00参数面板'!$E$34)*'00参数面板'!$C$43)+'00参数面板'!$F$34*30+'00参数面板'!$H$34*'00参数面板'!$C$43 | R15: =((('00参数面板'!$C$34/'00参数面板'!$E$34)*'00参数面板'!$C$43)+'00参数面板'!$F$34*30+'00参数面板'!$H$34*'00参数面板'!$C$43)/'00参数面板'!$C$34
A16: ='00参数面板'!$A$34 | B16: ='00参数面板'!$C$34 | C16: ='00参数面板'!$E$34 | D16: ='00参数面板'!$C$34/'00参数面板'!$E$34 | E16: ='00参数面板'!$A$44 | F16: ='00参数面板'!$C$44 | G16: ='00参数面板'!$D$44 | H16: =('00参数面板'!$C$34/'00参数面板'!$E$34)*'00参数面板'!$C$44 | I16: =('00参数面板'!$C$34/'00参数面板'!$E$34)*'00参数面板'!$C$44/'00参数面板'!$C$34 | J16: ='00参数面板'!$F$34 | K16: ='00参数面板'!$F$34*30 | L16: ='00参数面板'!$H$34*'00参数面板'!$C$44 | M16: =500000*(('00参数面板'!$G$34*'00参数面板'!$D$34)/('00参数面板'!$D$33*'00参数面板'!$G$33+'00参数面板'!$D$34*'00参数面板'!$G$34+'00参数面板'!$D$35*'00参数面板'!$G$35+'00参数面板'!$D$36*'00参数面板'!$G$36))/'00参数面板'!$D$34/12 | N16: =2500000*0.05*0.4*(('00参数面板'!$G$34*'00参数面板'!$D$34)/('00参数面板'!$D$33*'00参数面板'!$G$33+'00参数面板'!$D$34*'00参数面板'!$G$34+'00参数面板'!$D$35*'00参数面板'!$G$35+'00参数面板'!$D$36*'00参数面板'!$G$36))/'00参数面板'!$D$34 | O16: ='00参数面板'!$F$34*30/30*30+2500000*0.05*0.4*(('00参数面板'!$G$34*'00参数面板'!$D$34)/('00参数面板'!$D$33*'00参数面板'!$G$33+'00参数面板'!$D$34*'00参数面板'!$G$34+'00参数面板'!$D$35*'00参数面板'!$G$35+'00参数面板'!$D$36*'00参数面板'!$G$36))/'00参数面板'!$D$34+500000*(('00参数面板'!$G$34*'00参数面板'!$D$34)/('00参数面板'!$D$33*'00参数面板'!$G$33+'00参数面板'!$D$34*'00参数面板'!$G$34+'00参数面板'!$D$35*'00参数面板'!$G$35+'00参数面板'!$D$36*'00参数面板'!$G$36))/'00参数面板'!$D$34/12 | P16: =('00参数面板'!$F$34*30/30*30+2500000*0.05*0.4*(('00参数面板'!$G$34*'00参数面板'!$D$34)/('00参数面板'!$D$33*'00参数面板'!$G$33+'00参数面板'!$D$34*'00参数面板'!$G$34+'00参数面板'!$D$35*'00参数面板'!$G$35+'00参数面板'!$D$36*'00参数面板'!$G$36))/'00参数面板'!$D$34+500000*(('00参数面板'!$G$34*'00参数面板'!$D$34)/('00参数面板'!$D$33*'00参数面板'!$G$33+'00参数面板'!$D$34*'00参数面板'!$G$34+'00参数面板'!$D$35*'00参数面板'!$G$35+'00参数面板'!$D$36*'00参数面板'!$G$36))/'00参数面板'!$D$34/12)/'00参数面板'!$C$34 | Q16: =(('00参数面板'!$C$34/'00参数面板'!$E$34)*'00参数面板'!$C$44)+'00参数面板'!$F$34*30+'00参数面板'!$H$34*'00参数面板'!$C$44 | R16: =((('00参数面板'!$C$34/'00参数面板'!$E$34)*'00参数面板'!$C$44)+'00参数面板'!$F$34*30+'00参数面板'!$H$34*'00参数面板'!$C$44)/'00参数面板'!$C$34
A17: ='00参数面板'!$A$34 | B17: ='00参数面板'!$C$34 | C17: ='00参数面板'!$E$34 | D17: ='00参数面板'!$C$34/'00参数面板'!$E$34 | E17: ='00参数面板'!$A$45 | F17: ='00参数面板'!$C$45 | G17: ='00参数面板'!$D$45 | H17: =('00参数面板'!$C$34/'00参数面板'!$E$34)*'00参数面板'!$C$45 | I17: =('00参数面板'!$C$34/'00参数面板'!$E$34)*'00参数面板'!$C$45/'00参数面板'!$C$34 | J17: ='00参数面板'!$F$34 | K17: ='00参数面板'!$F$34*30 | L17: ='00参数面板'!$H$34*'00参数面板'!$C$45 | M17: =500000*(('00参数面板'!$G$34*'00参数面板'!$D$34)/('00参数面板'!$D$33*'00参数面板'!$G$33+'00参数面板'!$D$34*'00参数面板'!$G$34+'00参数面板'!$D$35*'00参数面板'!$G$35+'00参数面板'!$D$36*'00参数面板'!$G$36))/'00参数面板'!$D$34/12 | N17: =2500000*0.05*0.4*(('00参数面板'!$G$34*'00参数面板'!$D$34)/('00参数面板'!$D$33*'00参数面板'!$G$33+'00参数面板'!$D$34*'00参数面板'!$G$34+'00参数面板'!$D$35*'00参数面板'!$G$35+'00参数面板'!$D$36*'00参数面板'!$G$36))/'00参数面板'!$D$34 | O17: ='00参数面板'!$F$34*30/30*30+2500000*0.05*0.4*(('00参数面板'!$G$34*'00参数面板'!$D$34)/('00参数面板'!$D$33*'00参数面板'!$G$33+'00参数面板'!$D$34*'00参数面板'!$G$34+'00参数面板'!$D$35*'00参数面板'!$G$35+'00参数面板'!$D$36*'00参数面板'!$G$36))/'00参数面板'!$D$34+500000*(('00参数面板'!$G$34*'00参数面板'!$D$34)/('00参数面板'!$D$33*'00参数面板'!$G$33+'00参数面板'!$D$34*'00参数面板'!$G$34+'00参数面板'!$D$35*'00参数面板'!$G$35+'00参数面板'!$D$36*'00参数面板'!$G$36))/'00参数面板'!$D$34/12 | P17: =('00参数面板'!$F$34*30/30*30+2500000*0.05*0.4*(('00参数面板'!$G$34*'00参数面板'!$D$34)/('00参数面板'!$D$33*'00参数面板'!$G$33+'00参数面板'!$D$34*'00参数面板'!$G$34+'00参数面板'!$D$35*'00参数面板'!$G$35+'00参数面板'!$D$36*'00参数面板'!$G$36))/'00参数面板'!$D$34+500000*(('00参数面板'!$G$34*'00参数面板'!$D$34)/('00参数面板'!$D$33*'00参数面板'!$G$33+'00参数面板'!$D$34*'00参数面板'!$G$34+'00参数面板'!$D$35*'00参数面板'!$G$35+'00参数面板'!$D$36*'00参数面板'!$G$36))/'00参数面板'!$D$34/12)/'00参数面板'!$C$34 | Q17: =(('00参数面板'!$C$34/'00参数面板'!$E$34)*'00参数面板'!$C$45)+'00参数面板'!$F$34*30+'00参数面板'!$H$34*'00参数面板'!$C$45 | R17: =((('00参数面板'!$C$34/'00参数面板'!$E$34)*'00参数面板'!$C$45)+'00参数面板'!$F$34*30+'00参数面板'!$H$34*'00参数面板'!$C$45)/'00参数面板'!$C$34
A18: ='00参数面板'!$A$34 | B18: ='00参数面板'!$C$34 | C18: ='00参数面板'!$E$34 | D18: ='00参数面板'!$C$34/'00参数面板'!$E$34 | E18: ='00参数面板'!$A$46 | F18: ='00参数面板'!$C$46 | G18: ='00参数面板'!$D$46 | H18: =('00参数面板'!$C$34/'00参数面板'!$E$34)*'00参数面板'!$C$46 | I18: =('00参数面板'!$C$34/'00参数面板'!$E$34)*'00参数面板'!$C$46/'00参数面板'!$C$34 | J18: ='00参数面板'!$F$34 | K18: ='00参数面板'!$F$34*30 | L18: ='00参数面板'!$H$34*'00参数面板'!$C$46 | M18: =500000*(('00参数面板'!$G$34*'00参数面板'!$D$34)/('00参数面板'!$D$33*'00参数面板'!$G$33+'00参数面板'!$D$34*'00参数面板'!$G$34+'00参数面板'!$D$35*'00参数面板'!$G$35+'00参数面板'!$D$36*'00参数面板'!$G$36))/'00参数面板'!$D$34/12 | N18: =2500000*0.05*0.4*(('00参数面板'!$G$34*'00参数面板'!$D$34)/('00参数面板'!$D$33*'00参数面板'!$G$33+'00参数面板'!$D$34*'00参数面板'!$G$34+'00参数面板'!$D$35*'00参数面板'!$G$35+'00参数面板'!$D$36*'00参数面板'!$G$36))/'00参数面板'!$D$34 | O18: ='00参数面板'!$F$34*30/30*30+2500000*0.05*0.4*(('00参数面板'!$G$34*'00参数面板'!$D$34)/('00参数面板'!$D$33*'00参数面板'!$G$33+'00参数面板'!$D$34*'00参数面板'!$G$34+'00参数面板'!$D$35*'00参数面板'!$G$35+'00参数面板'!$D$36*'00参数面板'!$G$36))/'00参数面板'!$D$34+500000*(('00参数面板'!$G$34*'00参数面板'!$D$34)/('00参数面板'!$D$33*'00参数面板'!$G$33+'00参数面板'!$D$34*'00参数面板'!$G$34+'00参数面板'!$D$35*'00参数面板'!$G$35+'00参数面板'!$D$36*'00参数面板'!$G$36))/'00参数面板'!$D$34/12 | P18: =('00参数面板'!$F$34*30/30*30+2500000*0.05*0.4*(('00参数面板'!$G$34*'00参数面板'!$D$34)/('00参数面板'!$D$33*'00参数面板'!$G$33+'00参数面板'!$D$34*'00参数面板'!$G$34+'00参数面板'!$D$35*'00参数面板'!$G$35+'00参数面板'!$D$36*'00参数面板'!$G$36))/'00参数面板'!$D$34+500000*(('00参数面板'!$G$34*'00参数面板'!$D$34)/('00参数面板'!$D$33*'00参数面板'!$G$33+'00参数面板'!$D$34*'00参数面板'!$G$34+'00参数面板'!$D$35*'00参数面板'!$G$35+'00参数面板'!$D$36*'00参数面板'!$G$36))/'00参数面板'!$D$34/12)/'00参数面板'!$C$34 | Q18: =(('00参数面板'!$C$34/'00参数面板'!$E$34)*'00参数面板'!$C$46)+'00参数面板'!$F$34*30+'00参数面板'!$H$34*'00参数面板'!$C$46 | R18: =((('00参数面板'!$C$34/'00参数面板'!$E$34)*'00参数面板'!$C$46)+'00参数面板'!$F$34*30+'00参数面板'!$H$34*'00参数面板'!$C$46)/'00参数面板'!$C$34
A20: ='00参数面板'!$A$35 | B20: ='00参数面板'!$C$35 | C20: ='00参数面板'!$E$35 | D20: ='00参数面板'!$C$35/'00参数面板'!$E$35 | E20: ='00参数面板'!$A$41 | F20: ='00参数面板'!$C$41 | G20: ='00参数面板'!$D$41 | H20: =('00参数面板'!$C$35/'00参数面板'!$E$35)*'00参数面板'!$C$41 | I20: =('00参数面板'!$C$35/'00参数面板'!$E$35)*'00参数面板'!$C$41/'00参数面板'!$C$35 | J20: ='00参数面板'!$F$35 | K20: ='00参数面板'!$F$35*30 | L20: ='00参数面板'!$H$35*'00参数面板'!$C$41 | M20: =500000*(('00参数面板'!$G$35*'00参数面板'!$D$35)/('00参数面板'!$D$33*'00参数面板'!$G$33+'00参数面板'!$D$34*'00参数面板'!$G$34+'00参数面板'!$D$35*'00参数面板'!$G$35+'00参数面板'!$D$36*'00参数面板'!$G$36))/'00参数面板'!$D$35/12 | N20: =2500000*0.05*0.4*(('00参数面板'!$G$35*'00参数面板'!$D$35)/('00参数面板'!$D$33*'00参数面板'!$G$33+'00参数面板'!$D$34*'00参数面板'!$G$34+'00参数面板'!$D$35*'00参数面板'!$G$35+'00参数面板'!$D$36*'00参数面板'!$G$36))/'00参数面板'!$D$35 | O20: ='00参数面板'!$F$35*30/30*30+2500000*0.05*0.4*(('00参数面板'!$G$35*'00参数面板'!$D$35)/('00参数面板'!$D$33*'00参数面板'!$G$33+'00参数面板'!$D$34*'00参数面板'!$G$34+'00参数面板'!$D$35*'00参数面板'!$G$35+'00参数面板'!$D$36*'00参数面板'!$G$36))/'00参数面板'!$D$35+500000*(('00参数面板'!$G$35*'00参数面板'!$D$35)/('00参数面板'!$D$33*'00参数面板'!$G$33+'00参数面板'!$D$34*'00参数面板'!$G$34+'00参数面板'!$D$35*'00参数面板'!$G$35+'00参数面板'!$D$36*'00参数面板'!$G$36))/'00参数面板'!$D$35/12 | P20: =('00参数面板'!$F$35*30/30*30+2500000*0.05*0.4*(('00参数面板'!$G$35*'00参数面板'!$D$35)/('00参数面板'!$D$33*'00参数面板'!$G$33+'00参数面板'!$D$34*'00参数面板'!$G$34+'00参数面板'!$D$35*'00参数面板'!$G$35+'00参数面板'!$D$36*'00参数面板'!$G$36))/'00参数面板'!$D$35+500000*(('00参数面板'!$G$35*'00参数面板'!$D$35)/('00参数面板'!$D$33*'00参数面板'!$G$33+'00参数面板'!$D$34*'00参数面板'!$G$34+'00参数面板'!$D$35*'00参数面板'!$G$35+'00参数面板'!$D$36*'00参数面板'!$G$36))/'00参数面板'!$D$35/12)/'00参数面板'!$C$35 | Q20: =(('00参数面板'!$C$35/'00参数面板'!$E$35)*'00参数面板'!$C$41)+'00参数面板'!$F$35*30+'00参数面板'!$H$35*'00参数面板'!$C$41 | R20: =((('00参数面板'!$C$35/'00参数面板'!$E$35)*'00参数面板'!$C$41)+'00参数面板'!$F$35*30+'00参数面板'!$H$35*'00参数面板'!$C$41)/'00参数面板'!$C$35
A21: ='00参数面板'!$A$35 | B21: ='00参数面板'!$C$35 | C21: ='00参数面板'!$E$35 | D21: ='00参数面板'!$C$35/'00参数面板'!$E$35 | E21: ='00参数面板'!$A$42 | F21: ='00参数面板'!$C$42 | G21: ='00参数面板'!$D$42 | H21: =('00参数面板'!$C$35/'00参数面板'!$E$35)*'00参数面板'!$C$42 | I21: =('00参数面板'!$C$35/'00参数面板'!$E$35)*'00参数面板'!$C$42/'00参数面板'!$C$35 | J21: ='00参数面板'!$F$35 | K21: ='00参数面板'!$F$35*30 | L21: ='00参数面板'!$H$35*'00参数面板'!$C$42 | M21: =500000*(('00参数面板'!$G$35*'00参数面板'!$D$35)/('00参数面板'!$D$33*'00参数面板'!$G$33+'00参数面板'!$D$34*'00参数面板'!$G$34+'00参数面板'!$D$35*'00参数面板'!$G$35+'00参数面板'!$D$36*'00参数面板'!$G$36))/'00参数面板'!$D$35/12 | N21: =2500000*0.05*0.4*(('00参数面板'!$G$35*'00参数面板'!$D$35)/('00参数面板'!$D$33*'00参数面板'!$G$33+'00参数面板'!$D$34*'00参数面板'!$G$34+'00参数面板'!$D$35*'00参数面板'!$G$35+'00参数面板'!$D$36*'00参数面板'!$G$36))/'00参数面板'!$D$35 | O21: ='00参数面板'!$F$35*30/30*30+2500000*0.05*0.4*(('00参数面板'!$G$35*'00参数面板'!$D$35)/('00参数面板'!$D$33*'00参数面板'!$G$33+'00参数面板'!$D$34*'00参数面板'!$G$34+'00参数面板'!$D$35*'00参数面板'!$G$35+'00参数面板'!$D$36*'00参数面板'!$G$36))/'00参数面板'!$D$35+500000*(('00参数面板'!$G$35*'00参数面板'!$D$35)/('00参数面板'!$D$33*'00参数面板'!$G$33+'00参数面板'!$D$34*'00参数面板'!$G$34+'00参数面板'!$D$35*'00参数面板'!$G$35+'00参数面板'!$D$36*'00参数面板'!$G$36))/'00参数面板'!$D$35/12 | P21: =('00参数面板'!$F$35*30/30*30+2500000*0.05*0.4*(('00参数面板'!$G$35*'00参数面板'!$D$35)/('00参数面板'!$D$33*'00参数面板'!$G$33+'00参数面板'!$D$34*'00参数面板'!$G$34+'00参数面板'!$D$35*'00参数面板'!$G$35+'00参数面板'!$D$36*'00参数面板'!$G$36))/'00参数面板'!$D$35+500000*(('00参数面板'!$G$35*'00参数面板'!$D$35)/('00参数面板'!$D$33*'00参数面板'!$G$33+'00参数面板'!$D$34*'00参数面板'!$G$34+'00参数面板'!$D$35*'00参数面板'!$G$35+'00参数面板'!$D$36*'00参数面板'!$G$36))/'00参数面板'!$D$35/12)/'00参数面板'!$C$35 | Q21: =(('00参数面板'!$C$35/'00参数面板'!$E$35)*'00参数面板'!$C$42)+'00参数面板'!$F$35*30+'00参数面板'!$H$35*'00参数面板'!$C$42 | R21: =((('00参数面板'!$C$35/'00参数面板'!$E$35)*'00参数面板'!$C$42)+'00参数面板'!$F$35*30+'00参数面板'!$H$35*'00参数面板'!$C$42)/'00参数面板'!$C$35
A22: ='00参数面板'!$A$35 | B22: ='00参数面板'!$C$35 | C22: ='00参数面板'!$E$35 | D22: ='00参数面板'!$C$35/'00参数面板'!$E$35 | E22: ='00参数面板'!$A$43 | F22: ='00参数面板'!$C$43 | G22: ='00参数面板'!$D$43 | H22: =('00参数面板'!$C$35/'00参数面板'!$E$35)*'00参数面板'!$C$43 | I22: =('00参数面板'!$C$35/'00参数面板'!$E$35)*'00参数面板'!$C$43/'00参数面板'!$C$35 | J22: ='00参数面板'!$F$35 | K22: ='00参数面板'!$F$35*30 | L22: ='00参数面板'!$H$35*'00参数面板'!$C$43 | M22: =500000*(('00参数面板'!$G$35*'00参数面板'!$D$35)/('00参数面板'!$D$33*'00参数面板'!$G$33+'00参数面板'!$D$34*'00参数面板'!$G$34+'00参数面板'!$D$35*'00参数面板'!$G$35+'00参数面板'!$D$36*'00参数面板'!$G$36))/'00参数面板'!$D$35/12 | N22: =2500000*0.05*0.4*(('00参数面板'!$G$35*'00参数面板'!$D$35)/('00参数面板'!$D$33*'00参数面板'!$G$33+'00参数面板'!$D$34*'00参数面板'!$G$34+'00参数面板'!$D$35*'00参数面板'!$G$35+'00参数面板'!$D$36*'00参数面板'!$G$36))/'00参数面板'!$D$35 | O22: ='00参数面板'!$F$35*30/30*30+2500000*0.05*0.4*(('00参数面板'!$G$35*'00参数面板'!$D$35)/('00参数面板'!$D$33*'00参数面板'!$G$33+'00参数面板'!$D$34*'00参数面板'!$G$34+'00参数面板'!$D$35*'00参数面板'!$G$35+'00参数面板'!$D$36*'00参数面板'!$G$36))/'00参数面板'!$D$35+500000*(('00参数面板'!$G$35*'00参数面板'!$D$35)/('00参数面板'!$D$33*'00参数面板'!$G$33+'00参数面板'!$D$34*'00参数面板'!$G$34+'00参数面板'!$D$35*'00参数面板'!$G$35+'00参数面板'!$D$36*'00参数面板'!$G$36))/'00参数面板'!$D$35/12 | P22: =('00参数面板'!$F$35*30/30*30+2500000*0.05*0.4*(('00参数面板'!$G$35*'00参数面板'!$D$35)/('00参数面板'!$D$33*'00参数面板'!$G$33+'00参数面板'!$D$34*'00参数面板'!$G$34+'00参数面板'!$D$35*'00参数面板'!$G$35+'00参数面板'!$D$36*'00参数面板'!$G$36))/'00参数面板'!$D$35+500000*(('00参数面板'!$G$35*'00参数面板'!$D$35)/('00参数面板'!$D$33*'00参数面板'!$G$33+'00参数面板'!$D$34*'00参数面板'!$G$34+'00参数面板'!$D$35*'00参数面板'!$G$35+'00参数面板'!$D$36*'00参数面板'!$G$36))/'00参数面板'!$D$35/12)/'00参数面板'!$C$35 | Q22: =(('00参数面板'!$C$35/'00参数面板'!$E$35)*'00参数面板'!$C$43)+'00参数面板'!$F$35*30+'00参数面板'!$H$35*'00参数面板'!$C$43 | R22: =((('00参数面板'!$C$35/'00参数面板'!$E$35)*'00参数面板'!$C$43)+'00参数面板'!$F$35*30+'00参数面板'!$H$35*'00参数面板'!$C$43)/'00参数面板'!$C$35
A23: ='00参数面板'!$A$35 | B23: ='00参数面板'!$C$35 | C23: ='00参数面板'!$E$35 | D23: ='00参数面板'!$C$35/'00参数面板'!$E$35 | E23: ='00参数面板'!$A$44 | F23: ='00参数面板'!$C$44 | G23: ='00参数面板'!$D$44 | H23: =('00参数面板'!$C$35/'00参数面板'!$E$35)*'00参数面板'!$C$44 | I23: =('00参数面板'!$C$35/'00参数面板'!$E$35)*'00参数面板'!$C$44/'00参数面板'!$C$35 | J23: ='00参数面板'!$F$35 | K23: ='00参数面板'!$F$35*30 | L23: ='00参数面板'!$H$35*'00参数面板'!$C$44 | M23: =500000*(('00参数面板'!$G$35*'00参数面板'!$D$35)/('00参数面板'!$D$33*'00参数面板'!$G$33+'00参数面板'!$D$34*'00参数面板'!$G$34+'00参数面板'!$D$35*'00参数面板'!$G$35+'00参数面板'!$D$36*'00参数面板'!$G$36))/'00参数面板'!$D$35/12 | N23: =2500000*0.05*0.4*(('00参数面板'!$G$35*'00参数面板'!$D$35)/('00参数面板'!$D$33*'00参数面板'!$G$33+'00参数面板'!$D$34*'00参数面板'!$G$34+'00参数面板'!$D$35*'00参数面板'!$G$35+'00参数面板'!$D$36*'00参数面板'!$G$36))/'00参数面板'!$D$35 | O23: ='00参数面板'!$F$35*30/30*30+2500000*0.05*0.4*(('00参数面板'!$G$35*'00参数面板'!$D$35)/('00参数面板'!$D$33*'00参数面板'!$G$33+'00参数面板'!$D$34*'00参数面板'!$G$34+'00参数面板'!$D$35*'00参数面板'!$G$35+'00参数面板'!$D$36*'00参数面板'!$G$36))/'00参数面板'!$D$35+500000*(('00参数面板'!$G$35*'00参数面板'!$D$35)/('00参数面板'!$D$33*'00参数面板'!$G$33+'00参数面板'!$D$34*'00参数面板'!$G$34+'00参数面板'!$D$35*'00参数面板'!$G$35+'00参数面板'!$D$36*'00参数面板'!$G$36))/'00参数面板'!$D$35/12 | P23: =('00参数面板'!$F$35*30/30*30+2500000*0.05*0.4*(('00参数面板'!$G$35*'00参数面板'!$D$35)/('00参数面板'!$D$33*'00参数面板'!$G$33+'00参数面板'!$D$34*'00参数面板'!$G$34+'00参数面板'!$D$35*'00参数面板'!$G$35+'00参数面板'!$D$36*'00参数面板'!$G$36))/'00参数面板'!$D$35+500000*(('00参数面板'!$G$35*'00参数面板'!$D$35)/('00参数面板'!$D$33*'00参数面板'!$G$33+'00参数面板'!$D$34*'00参数面板'!$G$34+'00参数面板'!$D$35*'00参数面板'!$G$35+'00参数面板'!$D$36*'00参数面板'!$G$36))/'00参数面板'!$D$35/12)/'00参数面板'!$C$35 | Q23: =(('00参数面板'!$C$35/'00参数面板'!$E$35)*'00参数面板'!$C$44)+'00参数面板'!$F$35*30+'00参数面板'!$H$35*'00参数面板'!$C$44 | R23: =((('00参数面板'!$C$35/'00参数面板'!$E$35)*'00参数面板'!$C$44)+'00参数面板'!$F$35*30+'00参数面板'!$H$35*'00参数面板'!$C$44)/'00参数面板'!$C$35
A24: ='00参数面板'!$A$35 | B24: ='00参数面板'!$C$35 | C24: ='00参数面板'!$E$35 | D24: ='00参数面板'!$C$35/'00参数面板'!$E$35 | E24: ='00参数面板'!$A$45 | F24: ='00参数面板'!$C$45 | G24: ='00参数面板'!$D$45 | H24: =('00参数面板'!$C$35/'00参数面板'!$E$35)*'00参数面板'!$C$45 | I24: =('00参数面板'!$C$35/'00参数面板'!$E$35)*'00参数面板'!$C$45/'00参数面板'!$C$35 | J24: ='00参数面板'!$F$35 | K24: ='00参数面板'!$F$35*30 | L24: ='00参数面板'!$H$35*'00参数面板'!$C$45 | M24: =500000*(('00参数面板'!$G$35*'00参数面板'!$D$35)/('00参数面板'!$D$33*'00参数面板'!$G$33+'00参数面板'!$D$34*'00参数面板'!$G$34+'00参数面板'!$D$35*'00参数面板'!$G$35+'00参数面板'!$D$36*'00参数面板'!$G$36))/'00参数面板'!$D$35/12 | N24: =2500000*0.05*0.4*(('00参数面板'!$G$35*'00参数面板'!$D$35)/('00参数面板'!$D$33*'00参数面板'!$G$33+'00参数面板'!$D$34*'00参数面板'!$G$34+'00参数面板'!$D$35*'00参数面板'!$G$35+'00参数面板'!$D$36*'00参数面板'!$G$36))/'00参数面板'!$D$35 | O24: ='00参数面板'!$F$35*30/30*30+2500000*0.05*0.4*(('00参数面板'!$G$35*'00参数面板'!$D$35)/('00参数面板'!$D$33*'00参数面板'!$G$33+'00参数面板'!$D$34*'00参数面板'!$G$34+'00参数面板'!$D$35*'00参数面板'!$G$35+'00参数面板'!$D$36*'00参数面板'!$G$36))/'00参数面板'!$D$35+500000*(('00参数面板'!$G$35*'00参数面板'!$D$35)/('00参数面板'!$D$33*'00参数面板'!$G$33+'00参数面板'!$D$34*'00参数面板'!$G$34+'00参数面板'!$D$35*'00参数面板'!$G$35+'00参数面板'!$D$36*'00参数面板'!$G$36))/'00参数面板'!$D$35/12 | P24: =('00参数面板'!$F$35*30/30*30+2500000*0.05*0.4*(('00参数面板'!$G$35*'00参数面板'!$D$35)/('00参数面板'!$D$33*'00参数面板'!$G$33+'00参数面板'!$D$34*'00参数面板'!$G$34+'00参数面板'!$D$35*'00参数面板'!$G$35+'00参数面板'!$D$36*'00参数面板'!$G$36))/'00参数面板'!$D$35+500000*(('00参数面板'!$G$35*'00参数面板'!$D$35)/('00参数面板'!$D$33*'00参数面板'!$G$33+'00参数面板'!$D$34*'00参数面板'!$G$34+'00参数面板'!$D$35*'00参数面板'!$G$35+'00参数面板'!$D$36*'00参数面板'!$G$36))/'00参数面板'!$D$35/12)/'00参数面板'!$C$35 | Q24: =(('00参数面板'!$C$35/'00参数面板'!$E$35)*'00参数面板'!$C$45)+'00参数面板'!$F$35*30+'00参数面板'!$H$35*'00参数面板'!$C$45 | R24: =((('00参数面板'!$C$35/'00参数面板'!$E$35)*'00参数面板'!$C$45)+'00参数面板'!$F$35*30+'00参数面板'!$H$35*'00参数面板'!$C$45)/'00参数面板'!$C$35
A25: ='00参数面板'!$A$35 | B25: ='00参数面板'!$C$35 | C25: ='00参数面板'!$E$35 | D25: ='00参数面板'!$C$35/'00参数面板'!$E$35 | E25: ='00参数面板'!$A$46 | F25: ='00参数面板'!$C$46 | G25: ='00参数面板'!$D$46 | H25: =('00参数面板'!$C$35/'00参数面板'!$E$35)*'00参数面板'!$C$46 | I25: =('00参数面板'!$C$35/'00参数面板'!$E$35)*'00参数面板'!$C$46/'00参数面板'!$C$35 | J25: ='00参数面板'!$F$35 | K25: ='00参数面板'!$F$35*30 | L25: ='00参数面板'!$H$35*'00参数面板'!$C$46 | M25: =500000*(('00参数面板'!$G$35*'00参数面板'!$D$35)/('00参数面板'!$D$33*'00参数面板'!$G$33+'00参数面板'!$D$34*'00参数面板'!$G$34+'00参数面板'!$D$35*'00参数面板'!$G$35+'00参数面板'!$D$36*'00参数面板'!$G$36))/'00参数面板'!$D$35/12 | N25: =2500000*0.05*0.4*(('00参数面板'!$G$35*'00参数面板'!$D$35)/('00参数面板'!$D$33*'00参数面板'!$G$33+'00参数面板'!$D$34*'00参数面板'!$G$34+'00参数面板'!$D$35*'00参数面板'!$G$35+'00参数面板'!$D$36*'00参数面板'!$G$36))/'00参数面板'!$D$35 | O25: ='00参数面板'!$F$35*30/30*30+2500000*0.05*0.4*(('00参数面板'!$G$35*'00参数面板'!$D$35)/('00参数面板'!$D$33*'00参数面板'!$G$33+'00参数面板'!$D$34*'00参数面板'!$G$34+'00参数面板'!$D$35*'00参数面板'!$G$35+'00参数面板'!$D$36*'00参数面板'!$G$36))/'00参数面板'!$D$35+500000*(('00参数面板'!$G$35*'00参数面板'!$D$35)/('00参数面板'!$D$33*'00参数面板'!$G$33+'00参数面板'!$D$34*'00参数面板'!$G$34+'00参数面板'!$D$35*'00参数面板'!$G$35+'00参数面板'!$D$36*'00参数面板'!$G$36))/'00参数面板'!$D$35/12 | P25: =('00参数面板'!$F$35*30/30*30+2500000*0.05*0.4*(('00参数面板'!$G$35*'00参数面板'!$D$35)/('00参数面板'!$D$33*'00参数面板'!$G$33+'00参数面板'!$D$34*'00参数面板'!$G$34+'00参数面板'!$D$35*'00参数面板'!$G$35+'00参数面板'!$D$36*'00参数面板'!$G$36))/'00参数面板'!$D$35+500000*(('00参数面板'!$G$35*'00参数面板'!$D$35)/('00参数面板'!$D$33*'00参数面板'!$G$33+'00参数面板'!$D$34*'00参数面板'!$G$34+'00参数面板'!$D$35*'00参数面板'!$G$35+'00参数面板'!$D$36*'00参数面板'!$G$36))/'00参数面板'!$D$35/12)/'00参数面板'!$C$35 | Q25: =(('00参数面板'!$C$35/'00参数面板'!$E$35)*'00参数面板'!$C$46)+'00参数面板'!$F$35*30+'00参数面板'!$H$35*'00参数面板'!$C$46 | R25: =((('00参数面板'!$C$35/'00参数面板'!$E$35)*'00参数面板'!$C$46)+'00参数面板'!$F$35*30+'00参数面板'!$H$35*'00参数面板'!$C$46)/'00参数面板'!$C$35
A27: ='00参数面板'!$A$36 | B27: ='00参数面板'!$C$36 | C27: ='00参数面板'!$E$36 | D27: ='00参数面板'!$C$36/'00参数面板'!$E$36 | E27: ='00参数面板'!$A$41 | F27: ='00参数面板'!$C$41 | G27: ='00参数面板'!$D$41 | H27: =('00参数面板'!$C$36/'00参数面板'!$E$36)*'00参数面板'!$C$41 | I27: =('00参数面板'!$C$36/'00参数面板'!$E$36)*'00参数面板'!$C$41/'00参数面板'!$C$36 | J27: ='00参数面板'!$F$36 | K27: ='00参数面板'!$F$36*30 | L27: ='00参数面板'!$H$36*'00参数面板'!$C$41 | M27: =500000*(('00参数面板'!$G$36*'00参数面板'!$D$36)/('00参数面板'!$D$33*'00参数面板'!$G$33+'00参数面板'!$D$34*'00参数面板'!$G$34+'00参数面板'!$D$35*'00参数面板'!$G$35+'00参数面板'!$D$36*'00参数面板'!$G$36))/'00参数面板'!$D$36/12 | N27: =2500000*0.05*0.4*(('00参数面板'!$G$36*'00参数面板'!$D$36)/('00参数面板'!$D$33*'00参数面板'!$G$33+'00参数面板'!$D$34*'00参数面板'!$G$34+'00参数面板'!$D$35*'00参数面板'!$G$35+'00参数面板'!$D$36*'00参数面板'!$G$36))/'00参数面板'!$D$36 | O27: ='00参数面板'!$F$36*30/30*30+2500000*0.05*0.4*(('00参数面板'!$G$36*'00参数面板'!$D$36)/('00参数面板'!$D$33*'00参数面板'!$G$33+'00参数面板'!$D$34*'00参数面板'!$G$34+'00参数面板'!$D$35*'00参数面板'!$G$35+'00参数面板'!$D$36*'00参数面板'!$G$36))/'00参数面板'!$D$36+500000*(('00参数面板'!$G$36*'00参数面板'!$D$36)/('00参数面板'!$D$33*'00参数面板'!$G$33+'00参数面板'!$D$34*'00参数面板'!$G$34+'00参数面板'!$D$35*'00参数面板'!$G$35+'00参数面板'!$D$36*'00参数面板'!$G$36))/'00参数面板'!$D$36/12 | P27: =('00参数面板'!$F$36*30/30*30+2500000*0.05*0.4*(('00参数面板'!$G$36*'00参数面板'!$D$36)/('00参数面板'!$D$33*'00参数面板'!$G$33+'00参数面板'!$D$34*'00参数面板'!$G$34+'00参数面板'!$D$35*'00参数面板'!$G$35+'00参数面板'!$D$36*'00参数面板'!$G$36))/'00参数面板'!$D$36+500000*(('00参数面板'!$G$36*'00参数面板'!$D$36)/('00参数面板'!$D$33*'00参数面板'!$G$33+'00参数面板'!$D$34*'00参数面板'!$G$34+'00参数面板'!$D$35*'00参数面板'!$G$35+'00参数面板'!$D$36*'00参数面板'!$G$36))/'00参数面板'!$D$36/12)/'00参数面板'!$C$36 | Q27: =(('00参数面板'!$C$36/'00参数面板'!$E$36)*'00参数面板'!$C$41)+'00参数面板'!$F$36*30+'00参数面板'!$H$36*'00参数面板'!$C$41 | R27: =((('00参数面板'!$C$36/'00参数面板'!$E$36)*'00参数面板'!$C$41)+'00参数面板'!$F$36*30+'00参数面板'!$H$36*'00参数面板'!$C$41)/'00参数面板'!$C$36
A28: ='00参数面板'!$A$36 | B28: ='00参数面板'!$C$36 | C28: ='00参数面板'!$E$36 | D28: ='00参数面板'!$C$36/'00参数面板'!$E$36 | E28: ='00参数面板'!$A$42 | F28: ='00参数面板'!$C$42 | G28: ='00参数面板'!$D$42 | H28: =('00参数面板'!$C$36/'00参数面板'!$E$36)*'00参数面板'!$C$42 | I28: =('00参数面板'!$C$36/'00参数面板'!$E$36)*'00参数面板'!$C$42/'00参数面板'!$C$36 | J28: ='00参数面板'!$F$36 | K28: ='00参数面板'!$F$36*30 | L28: ='00参数面板'!$H$36*'00参数面板'!$C$42 | M28: =500000*(('00参数面板'!$G$36*'00参数面板'!$D$36)/('00参数面板'!$D$33*'00参数面板'!$G$33+'00参数面板'!$D$34*'00参数面板'!$G$34+'00参数面板'!$D$35*'00参数面板'!$G$35+'00参数面板'!$D$36*'00参数面板'!$G$36))/'00参数面板'!$D$36/12 | N28: =2500000*0.05*0.4*(('00参数面板'!$G$36*'00参数面板'!$D$36)/('00参数面板'!$D$33*'00参数面板'!$G$33+'00参数面板'!$D$34*'00参数面板'!$G$34+'00参数面板'!$D$35*'00参数面板'!$G$35+'00参数面板'!$D$36*'00参数面板'!$G$36))/'00参数面板'!$D$36 | O28: ='00参数面板'!$F$36*30/30*30+2500000*0.05*0.4*(('00参数面板'!$G$36*'00参数面板'!$D$36)/('00参数面板'!$D$33*'00参数面板'!$G$33+'00参数面板'!$D$34*'00参数面板'!$G$34+'00参数面板'!$D$35*'00参数面板'!$G$35+'00参数面板'!$D$36*'00参数面板'!$G$36))/'00参数面板'!$D$36+500000*(('00参数面板'!$G$36*'00参数面板'!$D$36)/('00参数面板'!$D$33*'00参数面板'!$G$33+'00参数面板'!$D$34*'00参数面板'!$G$34+'00参数面板'!$D$35*'00参数面板'!$G$35+'00参数面板'!$D$36*'00参数面板'!$G$36))/'00参数面板'!$D$36/12 | P28: =('00参数面板'!$F$36*30/30*30+2500000*0.05*0.4*(('00参数面板'!$G$36*'00参数面板'!$D$36)/('00参数面板'!$D$33*'00参数面板'!$G$33+'00参数面板'!$D$34*'00参数面板'!$G$34+'00参数面板'!$D$35*'00参数面板'!$G$35+'00参数面板'!$D$36*'00参数面板'!$G$36))/'00参数面板'!$D$36+500000*(('00参数面板'!$G$36*'00参数面板'!$D$36)/('00参数面板'!$D$33*'00参数面板'!$G$33+'00参数面板'!$D$34*'00参数面板'!$G$34+'00参数面板'!$D$35*'00参数面板'!$G$35+'00参数面板'!$D$36*'00参数面板'!$G$36))/'00参数面板'!$D$36/12)/'00参数面板'!$C$36 | Q28: =(('00参数面板'!$C$36/'00参数面板'!$E$36)*'00参数面板'!$C$42)+'00参数面板'!$F$36*30+'00参数面板'!$H$36*'00参数面板'!$C$42 | R28: =((('00参数面板'!$C$36/'00参数面板'!$E$36)*'00参数面板'!$C$42)+'00参数面板'!$F$36*30+'00参数面板'!$H$36*'00参数面板'!$C$42)/'00参数面板'!$C$36
A29: ='00参数面板'!$A$36 | B29: ='00参数面板'!$C$36 | C29: ='00参数面板'!$E$36 | D29: ='00参数面板'!$C$36/'00参数面板'!$E$36 | E29: ='00参数面板'!$A$43 | F29: ='00参数面板'!$C$43 | G29: ='00参数面板'!$D$43 | H29: =('00参数面板'!$C$36/'00参数面板'!$E$36)*'00参数面板'!$C$43 | I29: =('00参数面板'!$C$36/'00参数面板'!$E$36)*'00参数面板'!$C$43/'00参数面板'!$C$36 | J29: ='00参数面板'!$F$36 | K29: ='00参数面板'!$F$36*30 | L29: ='00参数面板'!$H$36*'00参数面板'!$C$43 | M29: =500000*(('00参数面板'!$G$36*'00参数面板'!$D$36)/('00参数面板'!$D$33*'00参数面板'!$G$33+'00参数面板'!$D$34*'00参数面板'!$G$34+'00参数面板'!$D$35*'00参数面板'!$G$35+'00参数面板'!$D$36*'00参数面板'!$G$36))/'00参数面板'!$D$36/12 | N29: =2500000*0.05*0.4*(('00参数面板'!$G$36*'00参数面板'!$D$36)/('00参数面板'!$D$33*'00参数面板'!$G$33+'00参数面板'!$D$34*'00参数面板'!$G$34+'00参数面板'!$D$35*'00参数面板'!$G$35+'00参数面板'!$D$36*'00参数面板'!$G$36))/'00参数面板'!$D$36 | O29: ='00参数面板'!$F$36*30/30*30+2500000*0.05*0.4*(('00参数面板'!$G$36*'00参数面板'!$D$36)/('00参数面板'!$D$33*'00参数面板'!$G$33+'00参数面板'!$D$34*'00参数面板'!$G$34+'00参数面板'!$D$35*'00参数面板'!$G$35+'00参数面板'!$D$36*'00参数面板'!$G$36))/'00参数面板'!$D$36+500000*(('00参数面板'!$G$36*'00参数面板'!$D$36)/('00参数面板'!$D$33*'00参数面板'!$G$33+'00参数面板'!$D$34*'00参数面板'!$G$34+'00参数面板'!$D$35*'00参数面板'!$G$35+'00参数面板'!$D$36*'00参数面板'!$G$36))/'00参数面板'!$D$36/12 | P29: =('00参数面板'!$F$36*30/30*30+2500000*0.05*0.4*(('00参数面板'!$G$36*'00参数面板'!$D$36)/('00参数面板'!$D$33*'00参数面板'!$G$33+'00参数面板'!$D$34*'00参数面板'!$G$34+'00参数面板'!$D$35*'00参数面板'!$G$35+'00参数面板'!$D$36*'00参数面板'!$G$36))/'00参数面板'!$D$36+500000*(('00参数面板'!$G$36*'00参数面板'!$D$36)/('00参数面板'!$D$33*'00参数面板'!$G$33+'00参数面板'!$D$34*'00参数面板'!$G$34+'00参数面板'!$D$35*'00参数面板'!$G$35+'00参数面板'!$D$36*'00参数面板'!$G$36))/'00参数面板'!$D$36/12)/'00参数面板'!$C$36 | Q29: =(('00参数面板'!$C$36/'00参数面板'!$E$36)*'00参数面板'!$C$43)+'00参数面板'!$F$36*30+'00参数面板'!$H$36*'00参数面板'!$C$43 | R29: =((('00参数面板'!$C$36/'00参数面板'!$E$36)*'00参数面板'!$C$43)+'00参数面板'!$F$36*30+'00参数面板'!$H$36*'00参数面板'!$C$43)/'00参数面板'!$C$36
A30: ='00参数面板'!$A$36 | B30: ='00参数面板'!$C$36 | C30: ='00参数面板'!$E$36 | D30: ='00参数面板'!$C$36/'00参数面板'!$E$36 | E30: ='00参数面板'!$A$44 | F30: ='00参数面板'!$C$44 | G30: ='00参数面板'!$D$44 | H30: =('00参数面板'!$C$36/'00参数面板'!$E$36)*'00参数面板'!$C$44 | I30: =('00参数面板'!$C$36/'00参数面板'!$E$36)*'00参数面板'!$C$44/'00参数面板'!$C$36 | J30: ='00参数面板'!$F$36 | K30: ='00参数面板'!$F$36*30 | L30: ='00参数面板'!$H$36*'00参数面板'!$C$44 | M30: =500000*(('00参数面板'!$G$36*'00参数面板'!$D$36)/('00参数面板'!$D$33*'00参数面板'!$G$33+'00参数面板'!$D$34*'00参数面板'!$G$34+'00参数面板'!$D$35*'00参数面板'!$G$35+'00参数面板'!$D$36*'00参数面板'!$G$36))/'00参数面板'!$D$36/12 | N30: =2500000*0.05*0.4*(('00参数面板'!$G$36*'00参数面板'!$D$36)/('00参数面板'!$D$33*'00参数面板'!$G$33+'00参数面板'!$D$34*'00参数面板'!$G$34+'00参数面板'!$D$35*'00参数面板'!$G$35+'00参数面板'!$D$36*'00参数面板'!$G$36))/'00参数面板'!$D$36 | O30: ='00参数面板'!$F$36*30/30*30+2500000*0.05*0.4*(('00参数面板'!$G$36*'00参数面板'!$D$36)/('00参数面板'!$D$33*'00参数面板'!$G$33+'00参数面板'!$D$34*'00参数面板'!$G$34+'00参数面板'!$D$35*'00参数面板'!$G$35+'00参数面板'!$D$36*'00参数面板'!$G$36))/'00参数面板'!$D$36+500000*(('00参数面板'!$G$36*'00参数面板'!$D$36)/('00参数面板'!$D$33*'00参数面板'!$G$33+'00参数面板'!$D$34*'00参数面板'!$G$34+'00参数面板'!$D$35*'00参数面板'!$G$35+'00参数面板'!$D$36*'00参数面板'!$G$36))/'00参数面板'!$D$36/12 | P30: =('00参数面板'!$F$36*30/30*30+2500000*0.05*0.4*(('00参数面板'!$G$36*'00参数面板'!$D$36)/('00参数面板'!$D$33*'00参数面板'!$G$33+'00参数面板'!$D$34*'00参数面板'!$G$34+'00参数面板'!$D$35*'00参数面板'!$G$35+'00参数面板'!$D$36*'00参数面板'!$G$36))/'00参数面板'!$D$36+500000*(('00参数面板'!$G$36*'00参数面板'!$D$36)/('00参数面板'!$D$33*'00参数面板'!$G$33+'00参数面板'!$D$34*'00参数面板'!$G$34+'00参数面板'!$D$35*'00参数面板'!$G$35+'00参数面板'!$D$36*'00参数面板'!$G$36))/'00参数面板'!$D$36/12)/'00参数面板'!$C$36 | Q30: =(('00参数面板'!$C$36/'00参数面板'!$E$36)*'00参数面板'!$C$44)+'00参数面板'!$F$36*30+'00参数面板'!$H$36*'00参数面板'!$C$44 | R30: =((('00参数面板'!$C$36/'00参数面板'!$E$36)*'00参数面板'!$C$44)+'00参数面板'!$F$36*30+'00参数面板'!$H$36*'00参数面板'!$C$44)/'00参数面板'!$C$36
A31: ='00参数面板'!$A$36 | B31: ='00参数面板'!$C$36 | C31: ='00参数面板'!$E$36 | D31: ='00参数面板'!$C$36/'00参数面板'!$E$36 | E31: ='00参数面板'!$A$45 | F31: ='00参数面板'!$C$45 | G31: ='00参数面板'!$D$45 | H31: =('00参数面板'!$C$36/'00参数面板'!$E$36)*'00参数面板'!$C$45 | I31: =('00参数面板'!$C$36/'00参数面板'!$E$36)*'00参数面板'!$C$45/'00参数面板'!$C$36 | J31: ='00参数面板'!$F$36 | K31: ='00参数面板'!$F$36*30 | L31: ='00参数面板'!$H$36*'00参数面板'!$C$45 | M31: =500000*(('00参数面板'!$G$36*'00参数面板'!$D$36)/('00参数面板'!$D$33*'00参数面板'!$G$33+'00参数面板'!$D$34*'00参数面板'!$G$34+'00参数面板'!$D$35*'00参数面板'!$G$35+'00参数面板'!$D$36*'00参数面板'!$G$36))/'00参数面板'!$D$36/12 | N31: =2500000*0.05*0.4*(('00参数面板'!$G$36*'00参数面板'!$D$36)/('00参数面板'!$D$33*'00参数面板'!$G$33+'00参数面板'!$D$34*'00参数面板'!$G$34+'00参数面板'!$D$35*'00参数面板'!$G$35+'00参数面板'!$D$36*'00参数面板'!$G$36))/'00参数面板'!$D$36 | O31: ='00参数面板'!$F$36*30/30*30+2500000*0.05*0.4*(('00参数面板'!$G$36*'00参数面板'!$D$36)/('00参数面板'!$D$33*'00参数面板'!$G$33+'00参数面板'!$D$34*'00参数面板'!$G$34+'00参数面板'!$D$35*'00参数面板'!$G$35+'00参数面板'!$D$36*'00参数面板'!$G$36))/'00参数面板'!$D$36+500000*(('00参数面板'!$G$36*'00参数面板'!$D$36)/('00参数面板'!$D$33*'00参数面板'!$G$33+'00参数面板'!$D$34*'00参数面板'!$G$34+'00参数面板'!$D$35*'00参数面板'!$G$35+'00参数面板'!$D$36*'00参数面板'!$G$36))/'00参数面板'!$D$36/12 | P31: =('00参数面板'!$F$36*30/30*30+2500000*0.05*0.4*(('00参数面板'!$G$36*'00参数面板'!$D$36)/('00参数面板'!$D$33*'00参数面板'!$G$33+'00参数面板'!$D$34*'00参数面板'!$G$34+'00参数面板'!$D$35*'00参数面板'!$G$35+'00参数面板'!$D$36*'00参数面板'!$G$36))/'00参数面板'!$D$36+500000*(('00参数面板'!$G$36*'00参数面板'!$D$36)/('00参数面板'!$D$33*'00参数面板'!$G$33+'00参数面板'!$D$34*'00参数面板'!$G$34+'00参数面板'!$D$35*'00参数面板'!$G$35+'00参数面板'!$D$36*'00参数面板'!$G$36))/'00参数面板'!$D$36/12)/'00参数面板'!$C$36 | Q31: =(('00参数面板'!$C$36/'00参数面板'!$E$36)*'00参数面板'!$C$45)+'00参数面板'!$F$36*30+'00参数面板'!$H$36*'00参数面板'!$C$45 | R31: =((('00参数面板'!$C$36/'00参数面板'!$E$36)*'00参数面板'!$C$45)+'00参数面板'!$F$36*30+'00参数面板'!$H$36*'00参数面板'!$C$45)/'00参数面板'!$C$36
A32: ='00参数面板'!$A$36 | B32: ='00参数面板'!$C$36 | C32: ='00参数面板'!$E$36 | D32: ='00参数面板'!$C$36/'00参数面板'!$E$36 | E32: ='00参数面板'!$A$46 | F32: ='00参数面板'!$C$46 | G32: ='00参数面板'!$D$46 | H32: =('00参数面板'!$C$36/'00参数面板'!$E$36)*'00参数面板'!$C$46 | I32: =('00参数面板'!$C$36/'00参数面板'!$E$36)*'00参数面板'!$C$46/'00参数面板'!$C$36 | J32: ='00参数面板'!$F$36 | K32: ='00参数面板'!$F$36*30 | L32: ='00参数面板'!$H$36*'00参数面板'!$C$46 | M32: =500000*(('00参数面板'!$G$36*'00参数面板'!$D$36)/('00参数面板'!$D$33*'00参数面板'!$G$33+'00参数面板'!$D$34*'00参数面板'!$G$34+'00参数面板'!$D$35*'00参数面板'!$G$35+'00参数面板'!$D$36*'00参数面板'!$G$36))/'00参数面板'!$D$36/12 | N32: =2500000*0.05*0.4*(('00参数面板'!$G$36*'00参数面板'!$D$36)/('00参数面板'!$D$33*'00参数面板'!$G$33+'00参数面板'!$D$34*'00参数面板'!$G$34+'00参数面板'!$D$35*'00参数面板'!$G$35+'00参数面板'!$D$36*'00参数面板'!$G$36))/'00参数面板'!$D$36 | O32: ='00参数面板'!$F$36*30/30*30+2500000*0.05*0.4*(('00参数面板'!$G$36*'00参数面板'!$D$36)/('00参数面板'!$D$33*'00参数面板'!$G$33+'00参数面板'!$D$34*'00参数面板'!$G$34+'00参数面板'!$D$35*'00参数面板'!$G$35+'00参数面板'!$D$36*'00参数面板'!$G$36))/'00参数面板'!$D$36+500000*(('00参数面板'!$G$36*'00参数面板'!$D$36)/('00参数面板'!$D$33*'00参数面板'!$G$33+'00参数面板'!$D$34*'00参数面板'!$G$34+'00参数面板'!$D$35*'00参数面板'!$G$35+'00参数面板'!$D$36*'00参数面板'!$G$36))/'00参数面板'!$D$36/12 | P32: =('00参数面板'!$F$36*30/30*30+2500000*0.05*0.4*(('00参数面板'!$G$36*'00参数面板'!$D$36)/('00参数面板'!$D$33*'00参数面板'!$G$33+'00参数面板'!$D$34*'00参数面板'!$G$34+'00参数面板'!$D$35*'00参数面板'!$G$35+'00参数面板'!$D$36*'00参数面板'!$G$36))/'00参数面板'!$D$36+500000*(('00参数面板'!$G$36*'00参数面板'!$D$36)/('00参数面板'!$D$33*'00参数面板'!$G$33+'00参数面板'!$D$34*'00参数面板'!$G$34+'00参数面板'!$D$35*'00参数面板'!$G$35+'00参数面板'!$D$36*'00参数面板'!$G$36))/'00参数面板'!$D$36/12)/'00参数面板'!$C$36 | Q32: =(('00参数面板'!$C$36/'00参数面板'!$E$36)*'00参数面板'!$C$46)+'00参数面板'!$F$36*30+'00参数面板'!$H$36*'00参数面板'!$C$46 | R32: =((('00参数面板'!$C$36/'00参数面板'!$E$36)*'00参数面板'!$C$46)+'00参数面板'!$F$36*30+'00参数面板'!$H$36*'00参数面板'!$C$46)/'00参数面板'!$C$36
A35: ▌ 图表数据（总资产引用矩阵列17）
A36: 节点\阶段 | B36: ='00参数面板'!$A$41 | C36: ='00参数面板'!$A$42 | D36: ='00参数面板'!$A$43 | E36: ='00参数面板'!$A$44 | F36: ='00参数面板'!$A$45 | G36: ='00参数面板'!$A$46
A37: ='00参数面板'!$A$33 | B37: =Q6 | C37: =Q7 | D37: =Q8 | E37: =Q9 | F37: =Q10 | G37: =Q11
A38: ='00参数面板'!$A$34 | B38: =Q13 | C38: =Q14 | D38: =Q15 | E38: =Q16 | F38: =Q17 | G38: =Q18
A39: ='00参数面板'!$A$35 | B39: =Q20 | C39: =Q21 | D39: =Q22 | E39: =Q23 | F39: =Q24 | G39: =Q25
A40: ='00参数面板'!$A$36 | B40: =Q27 | C40: =Q28 | D40: =Q29 | E40: =Q30 | F40: =Q31 | G40: =Q32
A42: 节点\月收益 | B42: ='00参数面板'!$A$41 | C42: ='00参数面板'!$A$42 | D42: ='00参数面板'!$A$43 | E42: ='00参数面板'!$A$44 | F42: ='00参数面板'!$A$45 | G42: ='00参数面板'!$A$46
A43: ='00参数面板'!$A$33 | B43: =O6 | C43: =O7 | D43: =O8 | E43: =O9 | F43: =O10 | G43: =O11
A44: ='00参数面板'!$A$34 | B44: =O13 | C44: =O14 | D44: =O15 | E44: =O16 | F44: =O17 | G44: =O18
A45: ='00参数面板'!$A$35 | B45: =O20 | C45: =O21 | D45: =O22 | E45: =O23 | F45: =O24 | G45: =O25
A46: ='00参数面板'!$A$36 | B46: =O27 | C46: =O28 | D46: =O29 | E46: =O30 | F46: =O31 | G46: =O32
